Workbook
Name \A: #REF!
Name \B: #REF!
Name \BUR: #REF!
Name \C: #REF!
Name \D: #REF!
Name \F: #REF!
Name \FOREX: #REF!
Name \g: #REF!
Name \M: #REF!
Name \O: #REF!
Name \Q: #REF!
Name \R: #REF!
Name \s: #REF!
Name \T: #REF!
Name \X: #REF!
Name \Z: #REF!
Name _1: #REF!
Name _1_????????: #REF!
Name _10A6: [3]LOAN!#REF!
Name _10A6: #REF!
Name _11: #REF!
Name _11A66: [3]LOAN!#REF!
Name _11A66: #REF!
Name _12EFF: #REF!
Name _13PORTFO: #REF!
Name _2_????????????12: #REF!
Name _2000_0630100000_Umsatzerlöse: #REF!
Name _2000_0630160000_Konsortialanteile_Umsatzerlöse__UPL__verb.: #REF!
Name _2000_0630160100_Untervergabe_an_verb._Unternehmen__UPL: #REF!
Name _2000_0630180000_Umsatzerlöse__UPL: #REF!
Name _2000_0630440000_Auftragskosten__UKV: #REF!
Name _2000_0630440010_Auftragskosten_des_Umsatzes__UKV: #REF!
Name _2000_0630440020_Konsortialanteile_in_Auftragskosten__UKV: #REF!
Name _2000_0630440021_Untervergabe_an_verb._Unternehmen__UKV: #REF!
Name _2000_0630440030_Auftragskosten_des_Umsatzes_für_ZG__UKV: #REF!
Name _2000_0630450000_Auflösung_Rückst._Nachlaufkosten__UKV: #REF!
Name _2000_0630460000_Deckungsabweichung__UKV: #REF!
Name _2000_0630470000_Garantiekosten__UKV: #REF!
Name _2000_0630480000_Forschung_und_Entwicklung__UKV: #REF!
Name _2000_0630490000_Vertriebskosten__UKV: #REF!
Name _2000_0630500000_Sonstige_betriebliche_Erträge: #REF!
Name _2000_0630500010_Ertr.aus_dem_Abgang_von_Gegenst._des_AV: #REF!
Name _2000_0630500022_Ertr.aus_der_Zuschreib._zu_Gegenst._d._Finanz: #REF!
Name _2000_0630500023_Ertr.aus_der_Zuschreib._Goodwill: #REF!
Name _2000_0630500030_Ertr.aus_der_Aufl.von_Rückstellungen: #REF!
Name _2000_0630500040_Ertr.aus_der_Aufl.des_Sonderp.mit_Rueckl.Ant.: #REF!
Name _2000_0630500300_Ertr.aus_dem_Abgang_von_Gegenst._des_AV__UKV: #REF!
Name _2000_0630500305_Ertr.aus_dem_Abgang_von_Finanzanlagever._UKV: #REF!
Name _2000_0630500310_Ertr.aus_Wertaufholung_Anlageverm.__UKV: #REF!
Name _2000_0630500320_Garantierückstellung_Auflösung__UKV: #REF!
Name _2000_0630500330_Auflösung_sonstige_Rückstellung__UKV: #REF!
Name _2000_0630500335_Auflösung_poc_Rückstellung__UKV: #REF!
Name _2000_0630500340_Kursgewinne_Ford._und_Verb._UKV: #REF!
Name _2000_0630500350_WB_auf_Forderungen_Auflösung__UKV: #REF!
Name _2000_0630500360_Ertr._aus_Änderungen_Bewertungsmeth.__UKV: #REF!
Name _2000_0630500370_Management_fees_Ertrag__UKV: #REF!
Name _2000_0630500380_Ertr._aus_Umlagen__UKV: #REF!
Name _2000_0630500390_Umlagen_KöSt.__Solz__UKV: #REF!
Name _2000_0630500400_Umlagen_Gewerbeertragsteuer__UKV: #REF!
Name _2000_0630500410_Umlagen_im_Ausland_gez._Steuern__UKV: #REF!

Sheet SCB-CP
A1: S.No. | B1: WBS | C1: SO | D1: Qty | E1: Equipment Name | F1: scope | G1: Planner | H1: Zero Date | I1: CDD | J1: Equipment Weight in KG | K1: Manufacturing Planned Hours | P1: Manufacturing Utilization Hours | U1: Available Capacity SCB | Z1: Actual Capacity SCB | AG1: Actual Welding | AV1: Actual Milling Machining | BK1: Actual CNC Lathe Machining | BZ1: Actual Assembly
K2: Welding | L2: Milling Machining | M2: CNC Lathe Machining | N2: Assembly | O2: Total Hours | P2: Welding | Q2: Milling Machining | R2: CNC Lathe Machining | S2: Assembly | T2: Total Hours | U2: Welding | V2: Milling Machining | W2: CNC Lathe Machining | X2: Assembly | Y2: Total Hours | Z2: Welding | AA2: Milling Machining | AB2: CNC Lathe Machining | AC2: Assembly | AD2: Total Hours | AE2: Order | AF2: Category | AG2: 46174 | AH2: 46204 | AI2: 46235 | AJ2: 46266 | AK2: 46296 | AL2: 46327 | AM2: 46357 | AN2: 46388 | AO2: 46419 | AP2: 46447 | AQ2: 46478 | AR2: 46508 | AS2: Total | AT2: Order | AU2: Category | AV2: 46174 | AW2: 46204 | AX2: 46235 | AY2: 46266 | AZ2: 46296 | BA2: 46327 | BB2: 46357 | BC2: 46388 | BD2: 46419 | BE2: 46447 | BF2: 46478 | BG2: 46508 | BH2: Total | BI2: Order | BJ2: Category | BK2: 46174 | BL2: 46204 | BM2: 46235 | BN2: 46266 | BO2: 46296 | BP2: 46327 | BQ2: 46357 | BR2: 46388 | BS2: 46419 | BT2: 46447 | BU2: 46478 | BV2: 46508 | BW2: Total | BX2: Order | BY2: Category | BZ2: 46174 | CA2: 46204 | CB2: 46235 | CC2: 46266 | CD2: 46296 | CE2: 46327 | CF2: 46357 | CG2: 46388 | CH2: 46419 | CI2: 46447 | CJ2: 46478 | CK2: 46508 | CL2: Total | CM2: Diff-FAB | CN2: Diff-MILL | CO2: Diff-LATHE | CP2: Diff-ASS
A3: 1 | B3: C00450X010.99.1000 | E3: Turret Base | F3: NA | G3: AVIJIT SAHA | H3: 44671 | I3: 44895 | J3: 9700 | K3: 1308 | L3: 125 | O3: =SUM(K3:N3) -> 1433 | P3: 2295.14 | Q3: 64 | R3: 57.2 | T3: =SUM(P3:S3) -> 2416.34 | U3: =K3-P3 -> -987.14 | V3: =L3-Q3 -> 61 | W3: =M3-R3 -> -57.2 | X3: =N3-S3 -> 0 | Y3: =SUM(U3:X3) -> -983.34 | Z3: =AS3 -> 0 | AA3: =BH3 -> 0 | AB3: =BW3 -> 0 | AC3: =CL3 -> 0 | AD3: =SUM(Z3:AC3) -> 0 | AE3: Contract | AF3: DIRECT | AS3: =SUM(AG3:AR3) -> 0 | AT3: Contract | AU3: DIRECT | BH3: =SUM(AV3:BG3) -> 0 | BI3: Contract | BJ3: DIRECT | BW3: =SUM(BK3:BV3) -> 0 | BX3: Contract | BY3: DIRECT | CL3: =SUM(BZ3:CK3) -> 0 | CM3: =U3-Z3 -> -987.14 | CN3: =V3-AA3 -> 61 | CO3: =W3-AB3 -> -57.2 | CP3: =X3-AC3 -> 0
A4: 2 | B4: C00525X010.1000 | E4: LADLE TURRET WEDGE TYPE 1 | F4: NA | G4: AVIJIT SAHA | H4: 44805 | I4: 44834 | K4: 300 | O4: =SUM(K4:N4) -> 300 | P4: 4 | Q4: 73.8 | T4: =SUM(P4:S4) -> 77.8 | U4: =K4-P4 -> 296 | V4: =L4-Q4 -> -73.8 | W4: =M4-R4 -> 0 | X4: =N4-S4 -> 0 | Y4: =SUM(U4:X4) -> 222.2 | Z4: =AS4 -> 0 | AA4: =BH4 -> 0 | AB4: =BW4 -> 0 | AC4: =CL4 -> 0 | AD4: =SUM(Z4:AC4) -> 0 | AE4: Contract | AF4: DIRECT | AS4: =SUM(AG4:AR4) -> 0 | AT4: Contract | AU4: DIRECT | BH4: =SUM(AV4:BG4) -> 0 | BI4: Contract | BJ4: DIRECT | BW4: =SUM(BK4:BV4) -> 0 | BX4: Contract | BY4: DIRECT | CL4: =SUM(BZ4:CK4) -> 0 | CM4: =U4-Z4 -> 296 | CN4: =V4-AA4 -> -73.8 | CO4: =W4-AB4 -> 0 | CP4: =X4-AC4 -> 0
A5: 3 | B5: A03394M220.20.10.10P1000 | C5: WBS | E5: Converter vessel | F5: NA | G5: KRISHNASIS | H5: 45054 | I5: 45381 | J5: 22000 | K5: 8000 | L5: 54 | O5: =SUM(K5:N5) -> 8054 | P5: 7108.64 | Q5: 52 | R5: 102.9 | T5: =SUM(P5:S5) -> 7263.54 | U5: =K5-P5 -> 891.36 | V5: =L5-Q5 -> 2 | W5: =M5-R5 -> -102.9 | X5: =N5-S5 -> 0 | Y5: =SUM(U5:X5) -> 790.46 | Z5: =AS5 -> 407 | AA5: =BH5 -> 0 | AB5: =BW5 -> 0 | AC5: =CL5 -> 0 | AD5: =SUM(Z5:AC5) -> 407 | AE5: OTH | AF5: WBS | AG5: 407 | AS5: =SUM(AG5:AR5) -> 407 | AT5: OTH | AU5: WBS | BH5: =SUM(AV5:BG5) -> 0 | BI5: OTH | BJ5: WBS | BW5: =SUM(BK5:BV5) -> 0 | BX5: OTH | BY5: WBS | CL5: =SUM(BZ5:CK5) -> 0 | CM5: =U5-Z5 -> 484.36 | CN5: =V5-AA5 -> 2 | CO5: =W5-AB5 -> -102.9 | CP5: =X5-AC5 -> 0
A6: 4 | B6: A03520M220.20.20P0110 | C6: WBS | E6: Blowing lance body | F6: NA | G6: Kameshwaran | H6: 45427 | J6: 5000 | K6: 1024 | M6: 55 | O6: =SUM(K6:N6) -> 1079 | P6: 1391 | Q6: 8.5 | T6: =SUM(P6:S6) -> 1399.5 | U6: =K6-P6 -> -367 | V6: =L6-Q6 -> -8.5 | W6: =M6-R6 -> 55 | X6: =N6-S6 -> 0 | Y6: =SUM(U6:X6) -> -320.5 | Z6: =AS6 -> 0 | AA6: =BH6 -> 0 | AB6: =BW6 -> 0 | AC6: =CL6 -> 0 | AD6: =SUM(Z6:AC6) -> 0 | AE6: OTH | AF6: WBS | AS6: =SUM(AG6:AR6) -> 0 | AT6: OTH | AU6: WBS | BH6: =SUM(AV6:BG6) -> 0 | BI6: OTH | BJ6: WBS | BW6: =SUM(BK6:BV6) -> 0 | BX6: OTH | BY6: WBS | CL6: =SUM(BZ6:CK6) -> 0 | CM6: =U6-Z6 -> -367 | CN6: =V6-AA6 -> -8.5 | CO6: =W6-AB6 -> 55 | CP6: =X6-AC6 -> 0
A7: 5 | B7: A03520M220.85P1000 | C7: WBS | E7: operational change parts oxygen lance | G7: Kameshwaran | H7: 45427 | J7: 5000 | K7: 1024 | L7: 55 | O7: =SUM(K7:N7) -> 1079 | P7: 1497 | R7: 5 | T7: =SUM(P7:S7) -> 1502 | U7: =K7-P7 -> -473 | V7: =L7-Q7 -> 55 | W7: =M7-R7 -> -5 | X7: =N7-S7 -> 0 | Y7: =SUM(U7:X7) -> -423 | Z7: =AS7 -> 200 | AA7: =BH7 -> 55 | AB7: =BW7 -> 0 | AC7: =CL7 -> 0 | AD7: =SUM(Z7:AC7) -> 255 | AE7: OTH | AF7: WBS | AG7: 200 | AS7: =SUM(AG7:AR7) -> 200 | AT7: OTH | AU7: WBS | AV7: 55 | BH7: =SUM(AV7:BG7) -> 55 | BI7: OTH | BJ7: WBS | BW7: =SUM(BK7:BV7) -> 0 | BX7: OTH | BY7: WBS | CL7: =SUM(BZ7:CK7) -> 0 | CM7: =U7-Z7 -> -673 | CN7: =V7-AA7 -> 0 | CO7: =W7-AB7 -> -5 | CP7: =X7-AC7 -> 0
A8: 6 | B8: A03520M220.40.10.50P1010 | C8: WBS | E8: Electrode Arms - PCA | F8: NA only ass | G8: Ravi Ranjan | I8: 45657 | J8: 15890 | K8: 5960 | L8: 280 | M8: 150 | N8: 300 | O8: =SUM(K8:N8) -> 6690 | P8: 8422 | Q8: 474.2 | R8: 303 | T8: =SUM(P8:S8) -> 9199.2 | U8: =K8-P8 -> -2462 | V8: =L8-Q8 -> -194.2 | W8: =M8-R8 -> -153 | X8: =N8-S8 -> 300 | Y8: =SUM(U8:X8) -> -2509.2 | Z8: =AS8 -> 0 | AA8: =BH8 -> 0 | AB8: =BW8 -> 0 | AC8: =CL8 -> 0 | AD8: =SUM(Z8:AC8) -> 0 | AE8: OTH | AF8: WBS | AS8: =SUM(AG8:AR8) -> 0 | AT8: OTH | AU8: WBS | BH8: =SUM(AV8:BG8) -> 0 | BI8: OTH | BJ8: WBS | BW8: =SUM(BK8:BV8) -> 0 | BX8: OTH | BY8: WBS | CL8: =SUM(BZ8:CK8) -> 0 | CM8: =U8-Z8 -> -2462 | CN8: =V8-AA8 -> -194.2 | CO8: =W8-AB8 -> -153 | CP8: =X8-AC8 -> 300
A9: 7 | B9: A03520M220.86.30P0100 | C9: WBS | E9: Electrode Clamp Assbly-Spare | F9: NA only ass | G9: Ravi Ranjan | I9: 45657 | J9: 732 | O9: =SUM(K9:N9) -> 0 | T9: =SUM(P9:S9) -> 0 | U9: =K9-P9 -> 0 | V9: =L9-Q9 -> 0 | W9: =M9-R9 -> 0 | X9: =N9-S9 -> 0 | Y9: =SUM(U9:X9) -> 0 | Z9: =AS9 -> 0 | AA9: =BH9 -> 0 | AB9: =BW9 -> 0 | AC9: =CL9 -> 0 | AD9: =SUM(Z9:AC9) -> 0 | AE9: OTH | AF9: WBS | AS9: =SUM(AG9:AR9) -> 0 | AT9: OTH | AU9: WBS | BH9: =SUM(AV9:BG9) -> 0 | BI9: OTH | BJ9: WBS | BW9: =SUM(BK9:BV9) -> 0 | BX9: OTH | BY9: WBS | CL9: =SUM(BZ9:CK9) -> 0 | CM9: =U9-Z9 -> 0 | CN9: =V9-AA9 -> 0 | CO9: =W9-AB9 -> 0 | CP9: =X9-AC9 -> 0
A10: 8 | B10: A03520M220.86.30P0200 | C10: WBS | E10: Contact Pad- Spare | F10: NA | G10: Ravi Ranjan | I10: 45657 | J10: 236 | O10: =SUM(K10:N10) -> 0 | T10: =SUM(P10:S10) -> 0 | U10: =K10-P10 -> 0 | V10: =L10-Q10 -> 0 | W10: =M10-R10 -> 0 | X10: =N10-S10 -> 0 | Y10: =SUM(U10:X10) -> 0 | Z10: =AS10 -> 0 | AA10: =BH10 -> 0 | AB10: =BW10 -> 0 | AC10: =CL10 -> 0 | AD10: =SUM(Z10:AC10) -> 0 | AE10: OTH | AF10: WBS | AS10: =SUM(AG10:AR10) -> 0 | AT10: OTH | AU10: WBS | BH10: =SUM(AV10:BG10) -> 0 | BI10: OTH | BJ10: WBS | BW10: =SUM(BK10:BV10) -> 0 | BX10: OTH | BY10: WBS | CL10: =SUM(BZ10:CK10) -> 0 | CM10: =U10-Z10 -> 0 | CN10: =V10-AA10 -> 0 | CO10: =W10-AB10 -> 0 | CP10: =X10-AC10 -> 0
A11: 9 | B11: A03508M120.10.12P3000 A03508M120.96.01P2000 | C11: WBS | E11: TUYERE STOCK (MAIN -24+SPARE -5) MOUNTING JIG REFRACTORY JIG DOWNLEG & ELBOW-BLOWPIPE DISMANTLING DEVICE | F11: NA | G11: Ravi Ranjan | H11: 45463 | I11: 45736 | J11: 60000 | K11: 6000 | L11: 172 | O11: =SUM(K11:N11) -> 6172 | P11: 8267.67 | Q11: 24 | R11: 231 | S11: 7 | T11: =SUM(P11:S11) -> 8529.67 | U11: =K11-P11 -> -2267.67 | V11: =L11-Q11 -> 148 | W11: =M11-R11 -> -231 | X11: =N11-S11 -> -7 | Y11: =SUM(U11:X11) -> -2357.67 | Z11: =AS11 -> 0 | AA11: =BH11 -> 0 | AB11: =BW11 -> 0 | AC11: =CL11 -> 0 | AD11: =SUM(Z11:AC11) -> 0 | AE11: OTH | AF11: WBS | AS11: =SUM(AG11:AR11) -> 0 | AT11: OTH | AU11: WBS | BH11: =SUM(AV11:BG11) -> 0 | BI11: OTH | BJ11: WBS | BW11: =SUM(BK11:BV11) -> 0 | BX11: OTH | BY11: WBS | CL11: =SUM(BZ11:CK11) -> 0 | CM11: =U11-Z11 -> -2267.67 | CN11: =V11-AA11 -> 148 | CO11: =W11-AB11 -> -231 | CP11: =X11-AC11 -> -7
A12: 10 | B12: ET560067341 | C12: 72003581 | E12: FINAL MACHINING & ASSEMBLY OF WORK ROLL CHOCKS - 2 SETS | F12: NA | G12: Ravi Ranjan | H12: 44748 | I12: 45026 | L12: 450 | N12: 200 | O12: =SUM(K12:N12) -> 650 | P12: 204 | Q12: 1462.8 | R12: 133.4 | S12: 838 | T12: =SUM(P12:S12) -> 2638.2 | U12: =K12-P12 -> -204 | V12: =L12-Q12 -> -1012.8 | W12: =M12-R12 -> -133.4 | X12: =N12-S12 -> -638 | Y12: =SUM(U12:X12) -> -1988.2 | Z12: =AS12 -> 0 | AA12: =BH12 -> 0 | AB12: =BW12 -> 0 | AC12: =CL12 -> 0 | AD12: =SUM(Z12:AC12) -> 0 | AE12: OTH | AF12: SERVICE | AS12: =SUM(AG12:AR12) -> 0 | AT12: OTH | AU12: SERVICE | BH12: =SUM(AV12:BG12) -> 0 | BI12: OTH | BJ12: SERVICE | BW12: =SUM(BK12:BV12) -> 0 | BX12: OTH | BY12: SERVICE | CL12: =SUM(BZ12:CK12) -> 0 | CM12: =U12-Z12 -> -204 | CN12: =V12-AA12 -> -1012.8 | CO12: =W12-AB12 -> -133.4 | CP12: =X12-AC12 -> -638
A13: 11 | B13: ET560065841 | C13: 72003480 | E13: Mandrel Spares | F13: NA | G13: Ravi Ranjan | H13: 44687 | I13: 45949 | O13: =SUM(K13:N13) -> 0 | R13: 3 | S13: 1000 | T13: =SUM(P13:S13) -> 1003 | U13: =K13-P13 -> 0 | V13: =L13-Q13 -> 0 | W13: =M13-R13 -> -3 | X13: =N13-S13 -> -1000 | Y13: =SUM(U13:X13) -> -1003 | Z13: =AS13 -> 0 | AA13: =BH13 -> 0 | AB13: =BW13 -> 0 | AC13: =CL13 -> 0 | AD13: =SUM(Z13:AC13) -> 0 | AE13: OTH | AF13: SERVICE | AS13: =SUM(AG13:AR13) -> 0 | AT13: OTH | AU13: SERVICE | BH13: =SUM(AV13:BG13) -> 0 | BI13: OTH | BJ13: SERVICE | BW13: =SUM(BK13:BV13) -> 0 | BX13: OTH | BY13: SERVICE | CL13: =SUM(BZ13:CK13) -> 0 | CM13: =U13-Z13 -> 0 | CN13: =V13-AA13 -> 0 | CO13: =W13-AB13 -> -3 | CP13: =X13-AC13 -> -1000
A14: 12 | B14: ET560076197 | C14: 72004059 | E14: Mandrel Spares -Segments | F14: NA | G14: Ravi Ranjan | H14: 44925 | I14: 45949 | S14: 520 | T14: =SUM(P14:S14) -> 520 | U14: =K14-P14 -> 0 | V14: =L14-Q14 -> 0 | W14: =M14-R14 -> 0 | X14: =N14-S14 -> -520 | Y14: =SUM(U14:X14) -> -520 | Z14: =AS14 -> 0 | AA14: =BH14 -> 0 | AB14: =BW14 -> 0 | AC14: =CL14 -> 0 | AD14: =SUM(Z14:AC14) -> 0 | AE14: OTH | AF14: SERVICE | AS14: =SUM(AG14:AR14) -> 0 | AT14: OTH | AU14: SERVICE | BH14: =SUM(AV14:BG14) -> 0 | BI14: OTH | BJ14: SERVICE | BW14: =SUM(BK14:BV14) -> 0 | BX14: OTH | BY14: SERVICE | CL14: =SUM(BZ14:CK14) -> 0 | CM14: =U14-Z14 -> 0 | CN14: =V14-AA14 -> 0 | CO14: =W14-AB14 -> 0 | CP14: =X14-AC14 -> -520
A15: 13 | B15: ET430084421 | C15: 72004601 | E15: FIXED HOOD LD2 | G15: Rejeesh | H15: 45394 | I15: 45777 | J15: 35000 | K15: 8000 | M15: 30 | O15: =SUM(K15:N15) -> 8030 | P15: 2311 | T15: =SUM(P15:S15) -> 2311 | U15: =K15-P15 -> 5689 | V15: =L15-Q15 -> 0 | W15: =M15-R15 -> 30 | X15: =N15-S15 -> 0 | Y15: =SUM(U15:X15) -> 5719 | Z15: =AS15 -> 8689 | AA15: =BH15 -> 0 | AB15: =BW15 -> 30 | AC15: =CL15 -> 0 | AD15: =SUM(Z15:AC15) -> 8719 | AE15: OTH | AF15: SERVICE | AG15: 2173 | AH15: 2172 | AI15: 2172 | AJ15: 2172 | AS15: =SUM(AG15:AR15) -> 8689 | AT15: OTH | AU15: SERVICE | BH15: =SUM(AV15:BG15) -> 0 | BI15: OTH | BJ15: SERVICE | BK15: 30 | BW15: =SUM(BK15:BV15) -> 30 | BX15: OTH | BY15: SERVICE | CL15: =SUM(BZ15:CK15) -> 0 | CM15: =U15-Z15 -> -3000 | CN15: =V15-AA15 -> 0 | CO15: =W15-AB15 -> 0 | CP15: =X15-AC15 -> 0
A16: 14 | B16: ET430095286 | C16: 72005231 | E16: SEGMENT 9_14 | F16: NA only ass | G16: Amulya Jena | H16: 45407 | I16: 45777 | J16: 60000 | K16: 6652 | L16: 1440 | N16: 2500 | O16: =SUM(K16:N16) -> 10592 | P16: 8434.45 | Q16: 777 | R16: 597 | S16: 12 | T16: =SUM(P16:S16) -> 9820.45 | U16: =K16-P16 -> -1782.45 | V16: =L16-Q16 -> 663 | W16: =M16-R16 -> -597 | X16: =N16-S16 -> 2488 | Y16: =SUM(U16:X16) -> 771.55 | Z16: =AS16 -> 0 | AA16: =BH16 -> 0 | AB16: =BW16 -> 0 | AC16: =CL16 -> 2488 | AD16: =SUM(Z16:AC16) -> 2488 | AE16: OTH | AF16: SERVICE | AS16: =SUM(AG16:AR16) -> 0 | AT16: OTH | AU16: SERVICE | BH16: =SUM(AV16:BG16) -> 0 | BI16: OTH | BJ16: SERVICE | BW16: =SUM(BK16:BV16) -> 0 | BX16: OTH | BY16: SERVICE | CA16: 1244 | CB16: 1244 | CL16: =SUM(BZ16:CK16) -> 2488 | CM16: =U16-Z16 -> -1782.45 | CN16: =V16-AA16 -> 663 | CO16: =W16-AB16 -> -597 | CP16: =X16-AC16 -> 0
A17: 15 | B17: ET460096489 | C17: 72005405 | E17: COOLING STACK 1 to 5 & COVER | F17: NA | G17: Rejeesh | H17: 45470 | I17: 45816 | J17: 40000 | K17: 12000 | M17: 330 | O17: =SUM(K17:N17) -> 12330 | P17: 4616 | T17: =SUM(P17:S17) -> 4616 | U17: =K17-P17 -> 7384 | V17: =L17-Q17 -> 0 | W17: =M17-R17 -> 330 | X17: =N17-S17 -> 0 | Y17: =SUM(U17:X17) -> 7714 | Z17: =AS17 -> 0 | AA17: =BH17 -> 0 | AB17: =BW17 -> 0 | AC17: =CL17 -> 0 | AD17: =SUM(Z17:AC17) -> 0 | AE17: OTH | AF17: SERVICE | AS17: =SUM(AG17:AR17) -> 0 | AT17: OTH | AU17: SERVICE | BH17: =SUM(AV17:BG17) -> 0 | BI17: OTH | BJ17: SERVICE | BW17: =SUM(BK17:BV17) -> 0 | BX17: OTH | BY17: SERVICE | CL17: =SUM(BZ17:CK17) -> 0 | CM17: =U17-Z17 -> 7384 | CN17: =V17-AA17 -> 0 | CO17: =W17-AB17 -> 330 | CP17: =X17-AC17 -> 0
A18: 16 | B18: ET460096654 | C18: 72005582 | E18: EAF TILTING PLATFORM & SUBSTRUCTRES | G18: Amulya Jena | H18: 45558 | I18: 45930 | J18: 30000 | K18: 9759.08 | L18: 140 | M18: 100 | O18: =SUM(K18:N18) -> 9999.08 | T18: =SUM(P18:S18) -> 0 | U18: =K18-P18 -> 9759.08 | V18: =L18-Q18 -> 140 | W18: =M18-R18 -> 100 | X18: =N18-S18 -> 0 | Y18: =SUM(U18:X18) -> 9999.08 | Z18: =AS18 -> 9759 | AA18: =BH18 -> 140 | AB18: =BW18 -> 100 | AC18: =CL18 -> 0 | AD18: =SUM(Z18:AC18) -> 9999 | AE18: OTH | AF18: SERVICE | AG18: 3253 | AH18: 3253 | AI18: 3253 | AS18: =SUM(AG18:AR18) -> 9759 | AT18: OTH | AU18: SERVICE | AV18: 140 | BH18: =SUM(AV18:BG18) -> 140 | BI18: OTH | BJ18: SERVICE | BK18: 100 | BW18: =SUM(BK18:BV18) -> 100 | BX18: OTH | BY18: SERVICE | CL18: =SUM(BZ18:CK18) -> 0 | CM18: =U18-Z18 -> 0.08 | CN18: =V18-AA18 -> 0 | CO18: =W18-AB18 -> 0 | CP18: =X18-AC18 -> 0
A19: 17 | B19: ET300093198 | C19: 72005103 | E19: Main cylinder with platten with bush | F19: NA | G19: SHASHIKUMAR | H19: 45604 | J19: 4000 | K19: 1231 | L19: 196 | O19: =SUM(K19:N19) -> 1427 | P19: 1687.3 | Q19: 416.4 | R19: 68.1 | T19: =SUM(P19:S19) -> 2171.8 | U19: =K19-P19 -> -456.3 | V19: =L19-Q19 -> -220.4 | W19: =M19-R19 -> -68.1 | X19: =N19-S19 -> 0 | Y19: =SUM(U19:X19) -> -744.8 | Z19: =AS19 -> 0 | AA19: =BH19 -> 0 | AB19: =BW19 -> 0 | AC19: =CL19 -> 0 | AD19: =SUM(Z19:AC19) -> 0 | AE19: OTH | AF19: SERVICE | AS19: =SUM(AG19:AR19) -> 0 | AT19: OTH | AU19: SERVICE | BH19: =SUM(AV19:BG19) -> 0 | BI19: OTH | BJ19: SERVICE | BW19: =SUM(BK19:BV19) -> 0 | BX19: OTH | BY19: SERVICE | CL19: =SUM(BZ19:CK19) -> 0 | CM19: =U19-Z19 -> -456.3 | CN19: =V19-AA19 -> -220.4 | CO19: =W19-AB19 -> -68.1 | CP19: =X19-AC19 -> 0
A20: 18 | B20: ET430096681 | C20: 72005606 | E20: MOLD OSCILLATION UNIT & MOLD CARRIER | G20: Kameshwaran | H20: 45562 | I20: 46067 | J20: 20000 | K20: 3630 | L20: 280 | M20: 130 | N20: 550 | O20: =SUM(K20:N20) -> 4590 | P20: 4067.17 | Q20: 238.3 | R20: 76.55 | T20: =SUM(P20:S20) -> 4382.02 | U20: =K20-P20 -> -437.17 | V20: =L20-Q20 -> 41.7 | W20: =M20-R20 -> 53.45 | X20: =N20-S20 -> 550 | Y20: =SUM(U20:X20) -> 207.98 | Z20: =AS20 -> 0 | AA20: =BH20 -> 42 | AB20: =BW20 -> 53 | AC20: =CL20 -> 550 | AD20: =SUM(Z20:AC20) -> 645 | AE20: OTH | AF20: SERVICE | AS20: =SUM(AG20:AR20) -> 0 | AT20: OTH | AU20: SERVICE | AV20: 42 | BH20: =SUM(AV20:BG20) -> 42 | BI20: OTH | BJ20: SERVICE | BK20: 53 | BW20: =SUM(BK20:BV20) -> 53 | BX20: OTH | BY20: SERVICE | BZ20: 550 | CL20: =SUM(BZ20:CK20) -> 550 | CM20: =U20-Z20 -> -437.17 | CN20: =V20-AA20 -> -0.3 | CO20: =W20-AB20 -> 0.45 | CP20: =X20-AC20 -> 0
A21: 19 | B21: A03533M120.10.12P3000 A03533M120.80.01P3020 A03533M120.80.01P4000 | C21: WBS | D21: 52 | E21: Tuyere Stock BF 2Yr Spare - Tuyere stock BF - Comm Spare - Tuyere stock | F21: PANKAJ | G21: Ravi Ranjan | H21: 45492 | I21: 45736 | J21: 180000 | K21: 16422 | M21: 678 | O21: =SUM(K21:N21) -> 17100 | P21: 10925 | Q21: 13 | R21: 139.05 | T21: =SUM(P21:S21) -> 11077.05 | U21: =K21-P21 -> 5497 | V21: =L21-Q21 -> -13 | W21: =M21-R21 -> 538.95 | X21: =N21-S21 -> 0 | Y21: =SUM(U21:X21) -> 6022.95 | Z21: =AS21 -> 5497 | AA21: =BH21 -> 0 | AB21: =BW21 -> 539 | AC21: =CL21 -> 0 | AD21: =SUM(Z21:AC21) -> 6036 | AE21: OTH | AF21: WBS | AG21: 1833 | AH21: 1832 | AI21: 1832 | AS21: =SUM(AG21:AR21) -> 5497 | AT21: OTH | AU21: WBS | BH21: =SUM(AV21:BG21) -> 0 | BI21: OTH | BJ21: WBS | BK21: 539 | BW21: =SUM(BK21:BV21) -> 539 | BX21: OTH | BY21: WBS | CL21: =SUM(BZ21:CK21) -> 0 | CM21: =U21-Z21 -> 0 | CN21: =V21-AA21 -> -13 | CO21: =W21-AB21 -> -0.05 | CP21: =X21-AC21 -> 0
A22: 20 | B22: A03533M120.80.01P3005 | C22: WBS | E22: BF 2Yr Spare - Centering and Wear device | F22: NA | G22: SANGRAM SWAIN | H22: 45429 | O22: =SUM(K22:N22) -> 0 | T22: =SUM(P22:S22) -> 0 | U22: =K22-P22 -> 0 | V22: =L22-Q22 -> 0 | W22: =M22-R22 -> 0 | X22: =N22-S22 -> 0 | Y22: =SUM(U22:X22) -> 0 | Z22: =AS22 -> 0 | AA22: =BH22 -> 0 | AB22: =BW22 -> 0 | AC22: =CL22 -> 0 | AD22: =SUM(Z22:AC22) -> 0 | AE22: OTH | AF22: WBS | AS22: =SUM(AG22:AR22) -> 0 | AT22: OTH | AU22: WBS | BH22: =SUM(AV22:BG22) -> 0 | BI22: OTH | BJ22: WBS | BW22: =SUM(BK22:BV22) -> 0 | BX22: OTH | BY22: WBS | CL22: =SUM(BZ22:CK22) -> 0 | CM22: =U22-Z22 -> 0 | CN22: =V22-AA22 -> 0 | CO22: =W22-AB22 -> 0 | CP22: =X22-AC22 -> 0
A23: 21 | B23: A03520M220.20.70.44P0500 | C23: WBS | D23: 1 | E23: INTERCONNECTING PIPING | F23: NA | G23: Kameshwaran | H23: 45513 | K23: 132 | M23: 26 | O23: =SUM(K23:N23) -> 158 | P23: 141 | R23: 3 | T23: =SUM(P23:S23) -> 144 | U23: =K23-P23 -> -9 | V23: =L23-Q23 -> 0 | W23: =M23-R23 -> 23 | X23: =N23-S23 -> 0 | Y23: =SUM(U23:X23) -> 14 | Z23: =AS23 -> 0 | AA23: =BH23 -> 0 | AB23: =BW23 -> 0 | AC23: =CL23 -> 0 | AD23: =SUM(Z23:AC23) -> 0 | AE23: OTH | AF23: WBS | AS23: =SUM(AG23:AR23) -> 0 | AT23: OTH | AU23: WBS | BH23: =SUM(AV23:BG23) -> 0 | BI23: OTH | BJ23: WBS | BW23: =SUM(BK23:BV23) -> 0 | BX23: OTH | BY23: WBS | CL23: =SUM(BZ23:CK23) -> 0 | CM23: =U23-Z23 -> -9 | CN23: =V23-AA23 -> 0 | CO23: =W23-AB23 -> 23 | CP23: =X23-AC23 -> 0
A24: 22 | B24: A03520M220.35.20.40P1100 | C24: WBS | D24: 2 | E24: TEEMING LADLE TRANSFER CAR AT LF | F24: NA | G24: Ravi Ranjan | H24: 45548 | J24: 85000 | K24: 5185 | L24: 672 | M24: 160 | N24: 750 | O24: =SUM(K24:N24) -> 6767 | P24: 5830.686 | Q24: 658.5 | R24: 575.5 | T24: =SUM(P24:S24) -> 7064.686 | U24: =K24-P24 -> -645.686 | V24: =L24-Q24 -> 13.5 | W24: =M24-R24 -> -415.5 | X24: =N24-S24 -> 750 | Y24: =SUM(U24:X24) -> -297.686 | Z24: =AS24 -> 0 | AA24: =BH24 -> 0 | AB24: =BW24 -> 0 | AC24: =CL24 -> 750 | AD24: =SUM(Z24:AC24) -> 750 | AE24: OTH | AF24: WBS | AS24: =SUM(AG24:AR24) -> 0 | AT24: OTH | AU24: WBS | BH24: =SUM(AV24:BG24) -> 0 | BI24: OTH | BJ24: WBS | BW24: =SUM(BK24:BV24) -> 0 | BX24: OTH | BY24: WBS | BZ24: 750 | CL24: =SUM(BZ24:CK24) -> 750 | CM24: =U24-Z24 -> -645.686 | CN24: =V24-AA24 -> 13.5 | CO24: =W24-AB24 -> -415.5 | CP24: =X24-AC24 -> 0
A25: 23 | B25: A03613M120.25P1500 | C25: WBS | D25: 1 | E25: GOGGLE VALVE ND 1600 SLIDE TYPE | G25: SANGRAM SWAIN | H25: 45575 | J25: 7000 | K25: 2411.88 | L25: 680 | M25: 200 | N25: 800 | O25: =SUM(K25:N25) -> 4091.88 | P25: 3501.01 | Q25: 350.2 | R25: 298 | T25: =SUM(P25:S25) -> 4149.21 | U25: =K25-P25 -> -1089.13 | V25: =L25-Q25 -> 329.8 | W25: =M25-R25 -> -98 | X25: =N25-S25 -> 800 | Y25: =SUM(U25:X25) -> -57.33 | Z25: =AS25 -> 0 | AA25: =BH25 -> 330 | AB25: =BW25 -> 0 | AC25: =CL25 -> 800 | AD25: =SUM(Z25:AC25) -> 1130 | AE25: OTH | AF25: WBS | AS25: =SUM(AG25:AR25) -> 0 | AT25: OTH | AU25: WBS | AV25: 165 | AW25: 165 | BH25: =SUM(AV25:BG25) -> 330 | BI25: OTH | BJ25: WBS | BW25: =SUM(BK25:BV25) -> 0 | BX25: OTH | BY25: WBS | BZ25: 800 | CL25: =SUM(BZ25:CK25) -> 800 | CM25: =U25-Z25 -> -1089.13 | CN25: =V25-AA25 -> -0.2 | CO25: =W25-AB25 -> -98 | CP25: =X25-AC25 -> 0
A26: 24 | B26: A03613M120.25P1525 | C26: WBS | D26: 1 | E26: COMBUSTION GAS ENRICHMENT GOGGLE VALVE DN 450 | F26: NA | G26: SANGRAM SWAIN | H26: 45575 | J26: 15000 | K26: 1896 | L26: 188 | N26: 800 | O26: =SUM(K26:N26) -> 2884 | P26: 919 | Q26: 169.6 | R26: 207 | T26: =SUM(P26:S26) -> 1295.6 | U26: =K26-P26 -> 977 | V26: =L26-Q26 -> 18.4 | W26: =M26-R26 -> -207 | X26: =N26-S26 -> 800 | Y26: =SUM(U26:X26) -> 1588.4 | Z26: =AS26 -> 0 | AA26: =BH26 -> 0 | AB26: =BW26 -> 0 | AC26: =CL26 -> 0 | AD26: =SUM(Z26:AC26) -> 0 | AE26: OTH | AF26: WBS | AS26: =SUM(AG26:AR26) -> 0 | AT26: OTH | AU26: WBS | BH26: =SUM(AV26:BG26) -> 0 | BI26: OTH | BJ26: WBS | BW26: =SUM(BK26:BV26) -> 0 | BX26: OTH | BY26: WBS | CL26: =SUM(BZ26:CK26) -> 0 | CM26: =U26-Z26 -> 977 | CN26: =V26-AA26 -> 18.4 | CO26: =W26-AB26 -> -207 | CP26: =X26-AC26 -> 800
A27: 25 | B27: 8564 | C27: SO | D27: 2 | E27: TWIN LADLE FURNACE WATER COOLED ROOF | F27: APEX | G27: Rejeesh | H27: 45623 | J27: 14000 | K27: 5732 | L27: 80 | O27: =SUM(K27:N27) -> 5812 | T27: =SUM(P27:S27) -> 0 | U27: =K27-P27 -> 5732 | V27: =L27-Q27 -> 80 | W27: =M27-R27 -> 0 | X27: =N27-S27 -> 0 | Y27: =SUM(U27:X27) -> 5812 | Z27: =AS27 -> 0 | AA27: =BH27 -> 0 | AB27: =BW27 -> 0 | AC27: =CL27 -> 0 | AD27: =SUM(Z27:AC27) -> 0 | AE27: OTH | AF27: SERVICE | AS27: =SUM(AG27:AR27) -> 0 | AT27: OTH | AU27: SERVICE | BH27: =SUM(AV27:BG27) -> 0 | BI27: OTH | BJ27: SERVICE | BW27: =SUM(BK27:BV27) -> 0 | BX27: OTH | BY27: SERVICE | CL27: =SUM(BZ27:CK27) -> 0 | CM27: =U27-Z27 -> 5732 | CN27: =V27-AA27 -> 80 | CO27: =W27-AB27 -> 0 | CP27: =X27-AC27 -> 0
A28: 26 | B28: A03520M220.86.40P0200 | C28: WBS | E28: SPARES FOR LADLE TRANSFER CARS-GEARBOX,COUPLINGS,BRAKE,BEARING,DRIVE WHEEL ASSLY | F28: NA | G28: Ravi Ranjan | H28: 45631 | K28: 150 | N28: 70 | O28: =SUM(K28:N28) -> 220 | T28: =SUM(P28:S28) -> 0 | U28: =K28-P28 -> 150 | V28: =L28-Q28 -> 0 | W28: =M28-R28 -> 0 | X28: =N28-S28 -> 70 | Y28: =SUM(U28:X28) -> 220 | Z28: =AS28 -> 0 | AA28: =BH28 -> 0 | AB28: =BW28 -> 0 | AC28: =CL28 -> 70 | AD28: =SUM(Z28:AC28) -> 70 | AE28: OTH | AF28: WBS | AS28: =SUM(AG28:AR28) -> 0 | AT28: OTH | AU28: WBS | BH28: =SUM(AV28:BG28) -> 0 | BI28: OTH | BJ28: WBS | BW28: =SUM(BK28:BV28) -> 0 | BX28: OTH | BY28: WBS | CB28: 70 | CL28: =SUM(BZ28:CK28) -> 70 | CM28: =U28-Z28 -> 150 | CN28: =V28-AA28 -> 0 | CO28: =W28-AB28 -> 0 | CP28: =X28-AC28 -> 0
A29: 27 | B29: S000611SMP.LSH.LAS.LAL1 S000611SMP.LSH.LAS.LAL2 S000611SMP.LSH.LAS.LAL3 S000611SMP.LSH.LAS.LAL4 S000611SMP.LSH.LAS.LAL5 S000611SMP.LSH.LAS.LAL6 | C29: 9149 | D29: 6 | E29: STEEL TEEMING LADLE | G29: KRISHNASIS | H29: 45625 | I29: 45991 | J29: 300000 | K29: 29215 | L29: 420 | O29: =SUM(K29:N29) -> 29635 | P29: 28222 | Q29: 376 | R29: 371 | S29: 591 | T29: =SUM(P29:S29) -> 29560 | U29: =K29-P29 -> 993 | V29: =L29-Q29 -> 44 | W29: =M29-R29 -> -371 | X29: =N29-S29 -> -591 | Y29: =SUM(U29:X29) -> 75 | Z29: =AS29 -> 993 | AA29: =BH29 -> 44 | AB29: =BW29 -> 0 | AC29: =CL29 -> 160 | AD29: =SUM(Z29:AC29) -> 1197 | AE29: Contract | AF29: DIRECT | AG29: 496.5 | AH29: 496.5 | AS29: =SUM(AG29:AR29) -> 993 | AT29: Contract | AU29: DIRECT | AV29: 44 | BH29: =SUM(AV29:BG29) -> 44 | BI29: Contract | BJ29: DIRECT | BW29: =SUM(BK29:BV29) -> 0 | BX29: Contract | BY29: DIRECT | BZ29: 160 | CL29: =SUM(BZ29:CK29) -> 160 | CM29: =U29-Z29 -> 0 | CN29: =V29-AA29 -> 0 | CO29: =W29-AB29 -> -371 | CP29: =X29-AC29 -> -751
A30: 28 | B30: 9179 | C30: SO | D30: 2 | E30: FINAL MACHINING OF EDGER HOUSING CASSETTE ASSEMBLY WITH LINERS | F30: Sanad | G30: SHASHIKUMAR | H30: 45636 | J30: 14000 | K30: 28 | L30: 400 | N30: 150 | O30: =SUM(K30:N30) -> 578 | T30: =SUM(P30:S30) -> 0 | U30: =K30-P30 -> 28 | V30: =L30-Q30 -> 400 | W30: =M30-R30 -> 0 | X30: =N30-S30 -> 150 | Y30: =SUM(U30:X30) -> 578 | Z30: =AS30 -> 0 | AA30: =BH30 -> 0 | AB30: =BW30 -> 0 | AC30: =CL30 -> 0 | AD30: =SUM(Z30:AC30) -> 0 | AE30: OTH | AF30: SERVICE | AS30: =SUM(AG30:AR30) -> 0 | AT30: OTH | AU30: SERVICE | BH30: =SUM(AV30:BG30) -> 0 | BI30: OTH | BJ30: SERVICE | BW30: =SUM(BK30:BV30) -> 0 | BX30: OTH | BY30: SERVICE | CL30: =SUM(BZ30:CK30) -> 0 | CM30: =U30-Z30 -> 28 | CN30: =V30-AA30 -> 400 | CO30: =W30-AB30 -> 0 | CP30: =X30-AC30 -> 150
A31: 29 | B31: A03520M220.55.40.20P0100 | C31: WBS | D31: 1 | E31: LADLE TILTER | G31: AMULYA JENA | H31: 45684 | I31: 45991 | J31: 30000 | K31: 5120 | L31: 280 | N31: 200 | O31: =SUM(K31:N31) -> 5600 | P31: 4485.02 | Q31: 141.7 | R31: 73.5 | T31: =SUM(P31:S31) -> 4700.22 | U31: =K31-P31 -> 634.98 | V31: =L31-Q31 -> 138.3 | W31: =M31-R31 -> -73.5 | X31: =N31-S31 -> 200 | Y31: =SUM(U31:X31) -> 899.78 | Z31: =AS31 -> 635 | AA31: =BH31 -> 138 | AB31: =BW31 -> 0 | AC31: =CL31 -> 200 | AD31: =SUM(Z31:AC31) -> 973 | AE31: OTH | AF31: WBS | AG31: 300 | AH31: 335 | AS31: =SUM(AG31:AR31) -> 635 | AT31: OTH | AU31: WBS | AV31: 138 | BH31: =SUM(AV31:BG31) -> 138 | BI31: OTH | BJ31: WBS | BW31: =SUM(BK31:BV31) -> 0 | BX31: OTH | BY31: WBS | BZ31: 200 | CL31: =SUM(BZ31:CK31) -> 200 | CM31: =U31-Z31 -> -0.02 | CN31: =V31-AA31 -> 0.3 | CO31: =W31-AB31 -> -73.5 | CP31: =X31-AC31 -> 0
A32: 30 | B32: S000348RML.FMA.URM.CHO S000348RML.FMA.EDM.CHO | C32: 9227 | D32: 3 | E32: ROLL CHOCK ASSEMBLY UR/UF & EDGER | F32: NA only ass | G32: SHASHIKUMAR | H32: 45687 | I32: 45700 | L32: 140 | N32: 420 | O32: =SUM(K32:N32) -> 560 | P32: 3.5 | Q32: 116.5 | R32: 82.5 | S32: 985 | T32: =SUM(P32:S32) -> 1187.5 | U32: =K32-P32 -> -3.5 | V32: =L32-Q32 -> 23.5 | W32: =M32-R32 -> -82.5 | X32: =N32-S32 -> -565 | Y32: =SUM(U32:X32) -> -627.5 | Z32: =AS32 -> 0 | AA32: =BH32 -> 0 | AB32: =BW32 -> 0 | AC32: =CL32 -> 0 | AD32: =SUM(Z32:AC32) -> 0 | AE32: OTH | AF32: SERVICE | AS32: =SUM(AG32:AR32) -> 0 | AT32: OTH | AU32: SERVICE | BH32: =SUM(AV32:BG32) -> 0 | BI32: OTH | BJ32: SERVICE | BW32: =SUM(BK32:BV32) -> 0 | BX32: OTH | BY32: SERVICE | CL32: =SUM(BZ32:CK32) -> 0 | CM32: =U32-Z32 -> -3.5 | CN32: =V32-AA32 -> 23.5 | CO32: =W32-AB32 -> -82.5 | CP32: =X32-AC32 -> -565
A33: 31 | B33: ET760096764 | C33: 72005686 | D33: 1 | E33: SEGMENT 11 | G33: Kameshwaran | H33: 45688 | I33: 46081 | J33: 4784 | K33: 3925 | L33: 370 | M33: 380 | N33: 700 | O33: =SUM(K33:N33) -> 5375 | P33: 3965.25 | Q33: 295.6 | R33: 672.35 | S33: 90 | T33: =SUM(P33:S33) -> 5023.2 | U33: =K33-P33 -> -40.25 | V33: =L33-Q33 -> 74.4 | W33: =M33-R33 -> -292.35 | X33: =N33-S33 -> 610 | Y33: =SUM(U33:X33) -> 351.8 | Z33: =AS33 -> 0 | AA33: =BH33 -> 74 | AB33: =BW33 -> 0 | AC33: =CL33 -> 610 | AD33: =SUM(Z33:AC33) -> 684 | AE33: OTH | AF33: SERVICE | AS33: =SUM(AG33:AR33) -> 0 | AT33: OTH | AU33: SERVICE | AW33: 74 | BH33: =SUM(AV33:BG33) -> 74 | BI33: OTH | BJ33: SERVICE | BW33: =SUM(BK33:BV33) -> 0 | BX33: OTH | BY33: SERVICE | BZ33: 610 | CL33: =SUM(BZ33:CK33) -> 610 | CM33: =U33-Z33 -> -40.25 | CN33: =V33-AA33 -> 0.4 | CO33: =W33-AB33 -> -292.35 | CP33: =X33-AC33 -> 0
A34: 32 | B34: 12301 | C34: SO | D34: 1 | E34: SEGMENT 12 | F34: NA | G34: Kameshwaran | H34: 45700 | I34: 46038 | J34: 14000 | K34: 1450 | L34: 405 | N34: 700 | O34: =SUM(K34:N34) -> 2555 | P34: 1489 | Q34: 1090 | R34: 1243 | S34: 872 | T34: =SUM(P34:S34) -> 4694 | U34: =K34-P34 -> -39 | V34: =L34-Q34 -> -685 | W34: =M34-R34 -> -1243 | X34: =N34-S34 -> -172 | Y34: =SUM(U34:X34) -> -2139 | Z34: =AS34 -> 0 | AA34: =BH34 -> 0 | AB34: =BW34 -> 0 | AC34: =CL34 -> 0 | AD34: =SUM(Z34:AC34) -> 0 | AE34: Group | AF34: DIRECT | AS34: =SUM(AG34:AR34) -> 0 | AT34: Group | AU34: DIRECT | BH34: =SUM(AV34:BG34) -> 0 | BI34: Group | BJ34: DIRECT | BW34: =SUM(BK34:BV34) -> 0 | BX34: Group | BY34: DIRECT | CL34: =SUM(BZ34:CK34) -> 0 | CM34: =U34-Z34 -> -39 | CN34: =V34-AA34 -> -685 | CO34: =W34-AB34 -> -1243 | CP34: =X34-AC34 -> -172
A35: 33 | B35: 13827 | C35: SO | D35: 2 | E35: REFURBISHMENT OF DSITRIBUTION CHUITE | F35: NA | G35: SANGRAM SWAIN | H35: 45742 | I35: 45850 | J35: 7420 | K35: =84*2 -> 168 | L35: =64*2 -> 128 | N35: 480 | O35: =SUM(K35:N35) -> 776 | P35: 14 | Q35: 15 | R35: 23.7 | S35: 747 | T35: =SUM(P35:S35) -> 799.7 | U35: =K35-P35 -> 154 | V35: =L35-Q35 -> 113 | W35: =M35-R35 -> -23.7 | X35: =N35-S35 -> -267 | Y35: =SUM(U35:X35) -> -23.7 | Z35: =AS35 -> 0 | AA35: =BH35 -> 0 | AB35: =BW35 -> 0 | AC35: =CL35 -> 0 | AD35: =SUM(Z35:AC35) -> 0 | AE35: OTH | AF35: SERVICE | AS35: =SUM(AG35:AR35) -> 0 | AT35: OTH | AU35: SERVICE | BH35: =SUM(AV35:BG35) -> 0 | BI35: OTH | BJ35: SERVICE | BW35: =SUM(BK35:BV35) -> 0 | BX35: OTH | BY35: SERVICE | CL35: =SUM(BZ35:CK35) -> 0 | CM35: =U35-Z35 -> 154 | CN35: =V35-AA35 -> 113 | CO35: =W35-AB35 -> -23.7 | CP35: =X35-AC35 -> -267
A36: 34 | B36: 11649 | C36: SO | D36: 3 | E36: F1-F4 BUR CHANGE SLEDGE ASSEMBLY | F36: NA | G36: Kameshwaran | H36: 45740 | J36: 15469 | O36: =SUM(K36:N36) -> 0 | P36: 27.5 | Q36: 660 | R36: 98.3 | S36: 1 | T36: =SUM(P36:S36) -> 786.8 | U36: =K36-P36 -> -27.5 | V36: =L36-Q36 -> -660 | W36: =M36-R36 -> -98.3 | X36: =N36-S36 -> -1 | Y36: =SUM(U36:X36) -> -786.8 | Z36: =AS36 -> 0 | AA36: =BH36 -> 0 | AB36: =BW36 -> 0 | AC36: =CL36 -> 0 | AD36: =SUM(Z36:AC36) -> 0 | AE36: OTH | AF36: SERVICE | AS36: =SUM(AG36:AR36) -> 0 | AT36: OTH | AU36: SERVICE | BH36: =SUM(AV36:BG36) -> 0 | BI36: OTH | BJ36: SERVICE | BW36: =SUM(BK36:BV36) -> 0 | BX36: OTH | BY36: SERVICE | CL36: =SUM(BZ36:CK36) -> 0 | CM36: =U36-Z36 -> -27.5 | CN36: =V36-AA36 -> -660 | CO36: =W36-AB36 -> -98.3 | CP36: =X36-AC36 -> -1
A37: 35 | B37: 14904 | C37: SO | D37: 1 | E37: REFURBISHMENT OF DSITRIBUTION CHUTE MIDI L-3.6M | F37: NA | G37: SANGRAM SWAIN | H37: 45764 | I37: 46081 | J37: 1631 | K37: 84 | L37: 64 | N37: 240 | O37: =SUM(K37:N37) -> 388 | S37: 238 | T37: =SUM(P37:S37) -> 238 | U37: =K37-P37 -> 84 | V37: =L37-Q37 -> 64 | W37: =M37-R37 -> 0 | X37: =N37-S37 -> 2 | Y37: =SUM(U37:X37) -> 150 | Z37: =AS37 -> 0 | AA37: =BH37 -> 0 | AB37: =BW37 -> 0 | AC37: =CL37 -> 0 | AD37: =SUM(Z37:AC37) -> 0 | AE37: OTH | AF37: SERVICE | AS37: =SUM(AG37:AR37) -> 0 | AT37: OTH | AU37: SERVICE | BH37: =SUM(AV37:BG37) -> 0 | BI37: OTH | BJ37: SERVICE | BW37: =SUM(BK37:BV37) -> 0 | BX37: OTH | BY37: SERVICE | CL37: =SUM(BZ37:CK37) -> 0 | CM37: =U37-Z37 -> 84 | CN37: =V37-AA37 -> 64 | CO37: =W37-AB37 -> 0 | CP37: =X37-AC37 -> 2
A38: 36 | B38: 15031 | C38: SO | D38: 6 | E38: ECCENTRIC WHEL ASSEMBLY | F38: NA | G38: SHASHIKUMAR | H38: 45777 | I38: 46022 | J38: 4728 | N38: 300 | O38: =SUM(K38:N38) -> 300 | T38: =SUM(P38:S38) -> 0 | U38: =K38-P38 -> 0 | V38: =L38-Q38 -> 0 | W38: =M38-R38 -> 0 | X38: =N38-S38 -> 300 | Y38: =SUM(U38:X38) -> 300 | Z38: =AS38 -> 0 | AA38: =BH38 -> 0 | AB38: =BW38 -> 0 | AC38: =CL38 -> 0 | AD38: =SUM(Z38:AC38) -> 0 | AE38: OTH | AF38: SERVICE | AS38: =SUM(AG38:AR38) -> 0 | AT38: OTH | AU38: SERVICE | BH38: =SUM(AV38:BG38) -> 0 | BI38: OTH | BJ38: SERVICE | BW38: =SUM(BK38:BV38) -> 0 | BX38: OTH | BY38: SERVICE | CL38: =SUM(BZ38:CK38) -> 0 | CM38: =U38-Z38 -> 0 | CN38: =V38-AA38 -> 0 | CO38: =W38-AB38 -> 0 | CP38: =X38-AC38 -> 300
A39: 37 | B39: 15541 | C39: SO | D39: 5 | E39: DOWNLEG ARRANGEMENT | F39: NA | G39: SANGRAM SWAIN | H39: 45784 | I39: 46022 | J39: 5995 | K39: 400 | N39: 80 | O39: =SUM(K39:N39) -> 480 | P39: 501 | S39: 241 | T39: =SUM(P39:S39) -> 742 | U39: =K39-P39 -> -101 | V39: =L39-Q39 -> 0 | W39: =M39-R39 -> 0 | X39: =N39-S39 -> -161 | Y39: =SUM(U39:X39) -> -262 | Z39: =AS39 -> 0 | AA39: =BH39 -> 0 | AB39: =BW39 -> 0 | AC39: =CL39 -> 0 | AD39: =SUM(Z39:AC39) -> 0 | AE39: OTH | AF39: SERVICE | AS39: =SUM(AG39:AR39) -> 0 | AT39: OTH | AU39: SERVICE | BH39: =SUM(AV39:BG39) -> 0 | BI39: OTH | BJ39: SERVICE | BW39: =SUM(BK39:BV39) -> 0 | BX39: OTH | BY39: SERVICE | CL39: =SUM(BZ39:CK39) -> 0 | CM39: =U39-Z39 -> -101 | CN39: =V39-AA39 -> 0 | CO39: =W39-AB39 -> 0 | CP39: =X39-AC39 -> -161
A40: 38 | B40: 16262 | C40: SO | D40: =2+2+2+2 -> 8 | E40: CHASSIS FRAME | F40: HOLD | G40: AVIJIT SAHA | H40: 45793 | I40: 45961 | J40: 7424 | K40: 3910 | L40: 160 | O40: =SUM(K40:N40) -> 4070 | P40: 2243 | Q40: 25.33 | R40: 89 | S40: 35 | T40: =SUM(P40:S40) -> 2392.33 | U40: =K40-P40 -> 1667 | V40: =L40-Q40 -> 134.67 | W40: =M40-R40 -> -89 | X40: =N40-S40 -> -35 | Y40: =SUM(U40:X40) -> 1677.67 | Z40: =AS40 -> 0 | AA40: =BH40 -> 0 | AB40: =BW40 -> 0 | AC40: =CL40 -> 0 | AD40: =SUM(Z40:AC40) -> 0 | AE40: Contract | AF40: DIRECT | AS40: =SUM(AG40:AR40) -> 0 | AT40: Contract | AU40: DIRECT | BH40: =SUM(AV40:BG40) -> 0 | BI40: Contract | BJ40: DIRECT | BW40: =SUM(BK40:BV40) -> 0 | BX40: Contract | BY40: DIRECT | CL40: =SUM(BZ40:CK40) -> 0 | CM40: =U40-Z40 -> 1667 | CN40: =V40-AA40 -> 134.67 | CO40: =W40-AB40 -> -89 | CP40: =X40-AC40 -> -35
A41: 39 | B41: 15540 | C41: SO | D41: =2+2+2+1 -> 7 | E41: WEAR PLATES | F41: NA | G41: SANGRAM SWAIN | H41: 45796 | I41: 45988 | J41: 2690 | N41: 4 | O41: =SUM(K41:N41) -> 4 | P41: 15 | Q41: 48 | R41: 1.75 | S41: 55 | T41: =SUM(P41:S41) -> 119.75 | U41: =K41-P41 -> -15 | V41: =L41-Q41 -> -48 | W41: =M41-R41 -> -1.75 | X41: =N41-S41 -> -51 | Y41: =SUM(U41:X41) -> -115.75 | Z41: =AS41 -> 0 | AA41: =BH41 -> 0 | AB41: =BW41 -> 0 | AC41: =CL41 -> 0 | AD41: =SUM(Z41:AC41) -> 0 | AE41: OTH | AF41: SERVICE | AS41: =SUM(AG41:AR41) -> 0 | AT41: OTH | AU41: SERVICE | BH41: =SUM(AV41:BG41) -> 0 | BI41: OTH | BJ41: SERVICE | BW41: =SUM(BK41:BV41) -> 0 | BX41: OTH | BY41: SERVICE | CL41: =SUM(BZ41:CK41) -> 0 | CM41: =U41-Z41 -> -15 | CN41: =V41-AA41 -> -48 | CO41: =W41-AB41 -> -1.75 | CP41: =X41-AC41 -> -51
A42: 40 | B42: 17368 | C42: SO | D42: 1 | E42: SKIP CAR ASSEMBLY | F42: NA only ass | G42: SANGRAM SWAIN | H42: 45825 | I42: 46178 | J42: 4310 | K42: 1277 | L42: 30 | M42: 108 | N42: 300 | O42: =SUM(K42:N42) -> 1715 | P42: 1616 | Q42: 178 | R42: 298 | S42: 447 | T42: =SUM(P42:S42) -> 2539 | U42: =K42-P42 -> -339 | V42: =L42-Q42 -> -148 | W42: =M42-R42 -> -190 | X42: =N42-S42 -> -147 | Y42: =SUM(U42:X42) -> -824 | Z42: =AS42 -> 0 | AA42: =BH42 -> 0 | AB42: =BW42 -> 0 | AC42: =CL42 -> 0 | AD42: =SUM(Z42:AC42) -> 0 | AE42: OTH | AF42: SERVICE | AS42: =SUM(AG42:AR42) -> 0 | AT42: OTH | AU42: SERVICE | BH42: =SUM(AV42:BG42) -> 0 | BI42: OTH | BJ42: SERVICE | BW42: =SUM(BK42:BV42) -> 0 | BX42: OTH | BY42: SERVICE | CL42: =SUM(BZ42:CK42) -> 0 | CM42: =U42-Z42 -> -339 | CN42: =V42-AA42 -> -148 | CO42: =W42-AB42 -> -190 | CP42: =X42-AC42 -> -147
A43: 41 | B43: S000765DIP.DUX.DIX.DYX1 S000765DIP.DUX.DIX.DYX2 S000765DIP.DUX.DIX.DYX3 | C43: 20140 | D43: 12 | E43: FRAMEWORK,CRUSHER,COMPLETE | G43: AVIJIT SAHA | H43: 45827 | I43: 46132 | J43: 100000 | K43: 24257.143 | L43: 60 | M43: 600 | O43: =SUM(K43:N43) -> 24917.143 | T43: =SUM(P43:S43) -> 0 | U43: =K43-P43 -> 24257.143 | V43: =L43-Q43 -> 60 | W43: =M43-R43 -> 600 | X43: =N43-S43 -> 0 | Y43: =SUM(U43:X43) -> 24917.143 | Z43: =AS43 -> 24257 | AA43: =BH43 -> 60 | AB43: =BW43 -> 600 | AC43: =CL43 -> 0 | AD43: =SUM(Z43:AC43) -> 24917 | AE43: Contract | AF43: DIRECT | AG43: 1757 | AH43: 2500 | AI43: 2500 | AJ43: 2500 | AK43: 2500 | AL43: 2500 | AM43: 2500 | AN43: 2500 | AO43: 2500 | AP43: 2500 | AS43: =SUM(AG43:AR43) -> 24257 | AT43: Contract | AU43: DIRECT | AX43: 10 | AY43: 10 | AZ43: 10 | BA43: 10 | BB43: 10 | BC43: 10 | BH43: =SUM(AV43:BG43) -> 60 | BI43: Contract | BJ43: DIRECT | BM43: 100 | BN43: 100 | BO43: 100 | BP43: 100 | BQ43: 100 | BR43: 100 | BW43: =SUM(BK43:BV43) -> 600 | BX43: Contract | BY43: DIRECT | CL43: =SUM(BZ43:CK43) -> 0 | CM43: =U43-Z43 -> 0.14285714 | CN43: =V43-AA43 -> 0 | CO43: =W43-AB43 -> 0 | CP43: =X43-AC43 -> 0
A44: 42 | B44: 20143 | C44: SO | D44: 12 | E44: SURFACE RECLAIM FEEDER | F44: NA | G44: AVIJIT SAHA | H44: 45827 | I44: 46142 | J44: 12000 | N44: 1800 | O44: =SUM(K44:N44) -> 1800 | T44: =SUM(P44:S44) -> 0 | U44: =K44-P44 -> 0 | V44: =L44-Q44 -> 0 | W44: =M44-R44 -> 0 | X44: =N44-S44 -> 1800 | Y44: =SUM(U44:X44) -> 1800 | Z44: =AS44 -> 0 | AA44: =BH44 -> 0 | AB44: =BW44 -> 0 | AC44: =CL44 -> 1800 | AD44: =SUM(Z44:AC44) -> 1800 | AE44: Contract | AF44: DIRECT | AS44: =SUM(AG44:AR44) -> 0 | AT44: Contract | AU44: DIRECT | BH44: =SUM(AV44:BG44) -> 0 | BI44: Contract | BJ44: DIRECT | BW44: =SUM(BK44:BV44) -> 0 | BX44: Contract | BY44: DIRECT | CD44: 300 | CE44: 300 | CF44: 300 | CG44: 300 | CH44: 300 | CI44: 300 | CL44: =SUM(BZ44:CK44) -> 1800 | CM44: =U44-Z44 -> 0 | CN44: =V44-AA44 -> 0 | CO44: =W44-AB44 -> 0 | CP44: =X44-AC44 -> 0
A45: 43 | B45: A03607X01P1 | C45: WBS | E45: Cladded Rolls & Copper plates | G45: AMAN SINGH | O45: =SUM(K45:N45) -> 0 | P45: 11271 | Q45: 933.1 | R45: 7638.05 | S45: 2192 | T45: =SUM(P45:S45) -> 22034.15 | U45: =K45-P45 -> -11271 | V45: =L45-Q45 -> -933.1 | W45: =M45-R45 -> -7638.05 | X45: =N45-S45 -> -2192 | Y45: =SUM(U45:X45) -> -22034.15 | Z45: =AS45 -> 3600 | AA45: =BH45 -> 1000 | AB45: =BW45 -> 1050 | AC45: =CL45 -> 0 | AD45: =SUM(Z45:AC45) -> 5650 | AE45: OTH | AF45: WBS | AG45: 300 | AH45: 300 | AI45: 300 | AJ45: 300 | AK45: 300 | AL45: 300 | AM45: 300 | AN45: 300 | AO45: 300 | AP45: 300 | AQ45: 300 | AR45: 300 | AS45: =SUM(AG45:AR45) -> 3600 | AT45: OTH | AU45: WBS | AV45: 200 | AW45: 200 | AX45: 200 | AY45: 200 | AZ45: 200 | BH45: =SUM(AV45:BG45) -> 1000 | BI45: OTH | BJ45: WBS | BK45: 350 | BL45: 350 | BM45: 350 | BW45: =SUM(BK45:BV45) -> 1050 | BX45: OTH | BY45: WBS | CL45: =SUM(BZ45:CK45) -> 0 | CM45: =U45-Z45 -> -14871 | CN45: =V45-AA45 -> -1933.1 | CO45: =W45-AB45 -> -8688.05 | CP45: =X45-AC45 -> -2192
A46: 44 | B46: A03608X01P1 | C46: WBS | E46: Narrow Foot Roll-Spare | F46: NA | G46: AMAN SINGH | O46: =SUM(K46:N46) -> 0 | P46: 1047.3 | R46: 1048.4 | S46: 1740 | T46: =SUM(P46:S46) -> 3835.7 | U46: =K46-P46 -> -1047.3 | V46: =L46-Q46 -> 0 | W46: =M46-R46 -> -1048.4 | X46: =N46-S46 -> -1740 | Y46: =SUM(U46:X46) -> -3835.7 | Z46: =AS46 -> 0 | AA46: =BH46 -> 0 | AB46: =BW46 -> 0 | AC46: =CL46 -> 0 | AD46: =SUM(Z46:AC46) -> 0 | AE46: OTH | AF46: WBS | AS46: =SUM(AG46:AR46) -> 0 | AT46: OTH | AU46: WBS | BH46: =SUM(AV46:BG46) -> 0 | BI46: OTH | BJ46: WBS | BW46: =SUM(BK46:BV46) -> 0 | BX46: OTH | BY46: WBS | CL46: =SUM(BZ46:CK46) -> 0 | CM46: =U46-Z46 -> -1047.3 | CN46: =V46-AA46 -> 0 | CO46: =W46-AB46 -> -1048.4 | CP46: =X46-AC46 -> -1740
A47: 45 | B47: 18010 | C47: SO | D47: 2 | E47: OXYGEN LANCE | F47: HOLD | G47: AMULYA JENA | H47: 45841 | I47: 46081 | J47: 5366 | K47: 508 | L47: 22 | O47: =SUM(K47:N47) -> 530 | T47: =SUM(P47:S47) -> 0 | U47: =K47-P47 -> 508 | V47: =L47-Q47 -> 22 | W47: =M47-R47 -> 0 | X47: =N47-S47 -> 0 | Y47: =SUM(U47:X47) -> 530 | Z47: =AS47 -> 0 | AA47: =BH47 -> 0 | AB47: =BW47 -> 0 | AC47: =CL47 -> 0 | AD47: =SUM(Z47:AC47) -> 0 | AE47: OTH | AF47: SERVICE | AS47: =SUM(AG47:AR47) -> 0 | AT47: OTH | AU47: SERVICE | BH47: =SUM(AV47:BG47) -> 0 | BI47: OTH | BJ47: SERVICE | BW47: =SUM(BK47:BV47) -> 0 | BX47: OTH | BY47: SERVICE | CL47: =SUM(BZ47:CK47) -> 0 | CM47: =U47-Z47 -> 508 | CN47: =V47-AA47 -> 22 | CO47: =W47-AB47 -> 0 | CP47: =X47-AC47 -> 0
A48: 46 | B48: 16925 | C48: SO | D48: 10 | E48: ELBOW, BLOWPIPE & SIGHT HOLE COVER | G48: SANGRAM SWAIN | H48: 45855 | I48: 45954 | J48: 15000 | K48: 800 | L48: 60 | N48: 140 | O48: =SUM(K48:N48) -> 1000 | P48: 1624 | Q48: 178.6 | R48: 297.3 | S48: 447 | T48: =SUM(P48:S48) -> 2546.9 | U48: =K48-P48 -> -824 | V48: =L48-Q48 -> -118.6 | W48: =M48-R48 -> -297.3 | X48: =N48-S48 -> -307 | Y48: =SUM(U48:X48) -> -1546.9 | Z48: =AS48 -> 0 | AA48: =BH48 -> 0 | AB48: =BW48 -> 0 | AC48: =CL48 -> 0 | AD48: =SUM(Z48:AC48) -> 0 | AE48: OTH | AF48: SERVICE | AS48: =SUM(AG48:AR48) -> 0 | AT48: OTH | AU48: SERVICE | BH48: =SUM(AV48:BG48) -> 0 | BI48: OTH | BJ48: SERVICE | BW48: =SUM(BK48:BV48) -> 0 | BX48: OTH | BY48: SERVICE | CL48: =SUM(BZ48:CK48) -> 0 | CM48: =U48-Z48 -> -824 | CN48: =V48-AA48 -> -118.6 | CO48: =W48-AB48 -> -297.3 | CP48: =X48-AC48 -> -307
A49: 47 | B49: 18905 | C49: SO | D49: 2 | E49: HYDRAULIC CYLINDER ASSEMBLY | F49: NA only ass | G49: Ravi Ranjan | H49: 45863 | I49: 46111 | J49: 2889 | K49: 8 | L49: 164 | N49: 80 | O49: =SUM(K49:N49) -> 252 | P49: 7 | Q49: 91 | R49: 426.7 | T49: =SUM(P49:S49) -> 524.7 | U49: =K49-P49 -> 1 | V49: =L49-Q49 -> 73 | W49: =M49-R49 -> -426.7 | X49: =N49-S49 -> 80 | Y49: =SUM(U49:X49) -> -272.7 | Z49: =AS49 -> 0 | AA49: =BH49 -> 0 | AB49: =BW49 -> 0 | AC49: =CL49 -> 0 | AD49: =SUM(Z49:AC49) -> 0 | AE49: OTH | AF49: SERVICE | AS49: =SUM(AG49:AR49) -> 0 | AT49: OTH | AU49: SERVICE | BH49: =SUM(AV49:BG49) -> 0 | BI49: OTH | BJ49: SERVICE | BW49: =SUM(BK49:BV49) -> 0 | BX49: OTH | BY49: SERVICE | CL49: =SUM(BZ49:CK49) -> 0 | CM49: =U49-Z49 -> 1 | CN49: =V49-AA49 -> 73 | CO49: =W49-AB49 -> -426.7 | CP49: =X49-AC49 -> 80
A50: 48 | B50: 21043 | C50: SO | D50: 1 | E50: LADLE ROOF | G50: Rejeesh | H50: 45862 | I50: 46290 | J50: 10122 | K50: 2642 | M50: 140 | N50: 200 | O50: =SUM(K50:N50) -> 2982 | S50: 6 | T50: =SUM(P50:S50) -> 6 | U50: =K50-P50 -> 2642 | V50: =L50-Q50 -> 0 | W50: =M50-R50 -> 140 | X50: =N50-S50 -> 194 | Y50: =SUM(U50:X50) -> 2976 | Z50: =AS50 -> 2642 | AA50: =BH50 -> 0 | AB50: =BW50 -> 140 | AC50: =CL50 -> 194 | AD50: =SUM(Z50:AC50) -> 2976 | AE50: OTH | AF50: DIRECT | AG50: 662 | AH50: 660 | AI50: 660 | AJ50: 660 | AS50: =SUM(AG50:AR50) -> 2642 | AT50: OTH | AU50: DIRECT | BH50: =SUM(AV50:BG50) -> 0 | BI50: OTH | BJ50: DIRECT | BM50: 140 | BW50: =SUM(BK50:BV50) -> 140 | BX50: OTH | BY50: DIRECT | CB50: 194 | CL50: =SUM(BZ50:CK50) -> 194 | CM50: =U50-Z50 -> 0 | CN50: =V50-AA50 -> 0 | CO50: =W50-AB50 -> 0 | CP50: =X50-AC50 -> 0
A51: 49 | B51: S000738EXP.ETP.EXR.CEH | C51: 19815 | D51: 1 | E51: CONTAINER HOLDER | G51: AMARSHI BEHERA | H51: 45862 | J51: 9731 | K51: 1252 | L51: 200 | M51: 60 | N51: 80 | O51: =SUM(K51:N51) -> 1592 | P51: 1355 | Q51: 57 | R51: 39 | T51: =SUM(P51:S51) -> 1451 | U51: =K51-P51 -> -103 | V51: =L51-Q51 -> 143 | W51: =M51-R51 -> 21 | X51: =N51-S51 -> 80 | Y51: =SUM(U51:X51) -> 141 | Z51: =AS51 -> 0 | AA51: =BH51 -> 143 | AB51: =BW51 -> 21 | AC51: =CL51 -> 80 | AD51: =SUM(Z51:AC51) -> 244 | AE51: OTH | AF51: SERVICE | AS51: =SUM(AG51:AR51) -> 0 | AT51: OTH | AU51: SERVICE | AV51: 100 | AW51: 43 | BH51: =SUM(AV51:BG51) -> 143 | BI51: OTH | BJ51: SERVICE | BK51: 21 | BW51: =SUM(BK51:BV51) -> 21 | BX51: OTH | BY51: SERVICE | CA51: 80 | CL51: =SUM(BZ51:CK51) -> 80 | CM51: =U51-Z51 -> -103 | CN51: =V51-AA51 -> 0 | CO51: =W51-AB51 -> 0 | CP51: =X51-AC51 -> 0
A52: 50 | B52: S000659CAS.SCP.STG.HOS S000659CAS.SCP.STG.HOS01 S000659CAS.SCP.STG.HOS02 | C52: 17892 | D52: 14 | E52: SEGMENT 3-5 ROLLER ASSEMBLY | G52: Kameshwaran | H52: 45866 | J52: 14374 | K52: 36 | M52: 320 | N52: 280 | O52: =SUM(K52:N52) -> 636 | P52: 220.06 | Q52: 817 | R52: 340.04 | T52: =SUM(P52:S52) -> 1377.1 | U52: =K52-P52 -> -184.06 | V52: =L52-Q52 -> -817 | W52: =M52-R52 -> -20.04 | X52: =N52-S52 -> 280 | Y52: =SUM(U52:X52) -> -741.1 | Z52: =AS52 -> 0 | AA52: =BH52 -> 0 | AB52: =BW52 -> 100 | AC52: =CL52 -> 280 | AD52: =SUM(Z52:AC52) -> 380 | AE52: OTH | AF52: SERVICE | AS52: =SUM(AG52:AR52) -> 0 | AT52: OTH | AU52: SERVICE | BH52: =SUM(AV52:BG52) -> 0 | BI52: OTH | BJ52: SERVICE | BK52: 100 | BW52: =SUM(BK52:BV52) -> 100 | BX52: OTH | BY52: SERVICE | CA52: 280 | CL52: =SUM(BZ52:CK52) -> 280 | CM52: =U52-Z52 -> -184.06 | CN52: =V52-AA52 -> -817 | CO52: =W52-AB52 -> -120.04 | CP52: =X52-AC52 -> 0
A53: 51 | B53: C01RB1PSMP.LSH.LTF.LTCK | C53: WBS | D53: 1 | E53: EAF & LF TRANSFER CARS | F53: NA | G53: AVIJIT SAHA | H53: 45840 | J53: 25000 | K53: 1985 | L53: 148 | M53: 32 | N53: 300 | O53: =SUM(K53:N53) -> 2465 | P53: 1748 | Q53: 173 | R53: 304 | S53: 333 | T53: 2572 | U53: =K53-P53 -> 237 | V53: =L53-Q53 -> -25 | W53: =M53-R53 -> -272 | X53: =N53-S53 -> -33 | Y53: =SUM(U53:X53) -> -93 | Z53: =AS53 -> 0 | AA53: =BH53 -> 0 | AB53: =BW53 -> 0 | AC53: =CL53 -> 0 | AD53: =SUM(Z53:AC53) -> 0 | AE53: OTH | AF53: WBS | AS53: =SUM(AG53:AR53) -> 0 | AT53: OTH | AU53: WBS | BH53: =SUM(AV53:BG53) -> 0 | BI53: OTH | BJ53: WBS | BW53: =SUM(BK53:BV53) -> 0 | BX53: OTH | BY53: WBS | CL53: =SUM(BZ53:CK53) -> 0 | CM53: =U53-Z53 -> 237 | CN53: =V53-AA53 -> -25 | CO53: =W53-AB53 -> -272 | CP53: =X53-AC53 -> -33
A54: 52 | B54: C01RB1PSMP.LHF.EAR.EASK | C54: WBS | D54: 1 | E54: ELECTRODE ARM ASSEMBLY | F54: NA | G54: Ravi Ranjan | H54: 45863 | J54: 13557 | K54: 4750 | L54: 640 | N54: 800 | O54: =SUM(K54:N54) -> 6190 | P54: 5857 | Q54: 508 | R54: 190 | S54: 678 | T54: =SUM(P54:S54) -> 7233 | U54: =K54-P54 -> -1107 | V54: =L54-Q54 -> 132 | W54: =M54-R54 -> -190 | X54: =N54-S54 -> 122 | Y54: =SUM(U54:X54) -> -1043 | Z54: =AS54 -> 0 | AA54: =BH54 -> 0 | AB54: =BW54 -> 0 | AC54: =CL54 -> 30 | AD54: =SUM(Z54:AC54) -> 30 | AE54: OTH | AF54: WBS | AS54: =SUM(AG54:AR54) -> 0 | AT54: OTH | AU54: WBS | BH54: =SUM(AV54:BG54) -> 0 | BI54: OTH | BJ54: WBS | BW54: =SUM(BK54:BV54) -> 0 | BX54: OTH | BY54: WBS | BZ54: 30 | CL54: =SUM(BZ54:CK54) -> 30 | CM54: =U54-Z54 -> -1107 | CN54: =V54-AA54 -> 132 | CO54: =W54-AB54 -> -190 | CP54: =X54-AC54 -> 92
A55: 53 | B55: C01RB1PSMP.LHF.ROS.WCRK | C55: WBS | D55: 1 | E55: WATER COOLED ROOF | F55: NA | G55: REJEESH | H55: 45863 | J55: 8885 | K55: 2253.25 | L55: 46 | O55: =SUM(K55:N55) -> 2299.25 | P55: 2573 | Q55: 1.4 | R55: 34.1 | S55: 22 | T55: =SUM(P55:S55) -> 2630.5 | U55: =K55-P55 -> -319.75 | V55: =L55-Q55 -> 44.6 | W55: =M55-R55 -> -34.1 | X55: =N55-S55 -> -22 | Y55: =SUM(U55:X55) -> -331.25 | Z55: =AS55 -> 0 | AA55: =BH55 -> 0 | AB55: =BW55 -> 0 | AC55: =CL55 -> 0 | AD55: =SUM(Z55:AC55) -> 0 | AE55: OTH | AF55: WBS | AS55: =SUM(AG55:AR55) -> 0 | AT55: OTH | AU55: WBS | BH55: =SUM(AV55:BG55) -> 0 | BI55: OTH | BJ55: WBS | BW55: =SUM(BK55:BV55) -> 0 | BX55: OTH | BY55: WBS | CL55: =SUM(BZ55:CK55) -> 0 | CM55: =U55-Z55 -> -319.75 | CN55: =V55-AA55 -> 44.6 | CO55: =W55-AB55 -> -34.1 | CP55: =X55-AC55 -> -22
A56: 54 | B56: C01RB1PSMP.LSH.LTL.LTCK | C56: WBS | D56: 1 | E56: Ladle transfer car (LF ladle car) | F56: NA | G56: AVIJIT SAHA | J56: 25000 | K56: 1975 | L56: 148 | M56: 32 | N56: 300 | O56: =SUM(K56:N56) -> 2455 | P56: 1770 | Q56: 148.6 | R56: 361.55 | S56: 117 | T56: =SUM(P56:S56) -> 2397.15 | U56: =K56-P56 -> 205 | V56: =L56-Q56 -> -0.6 | W56: =M56-R56 -> -329.55 | X56: =N56-S56 -> 183 | Y56: =SUM(U56:X56) -> 57.85 | Z56: =AS56 -> 0 | AA56: =BH56 -> 0 | AB56: =BW56 -> 0 | AC56: =CL56 -> 0 | AD56: =SUM(Z56:AC56) -> 0 | AE56: OTH | AF56: WBS | AS56: =SUM(AG56:AR56) -> 0 | AT56: OTH | AU56: WBS | BH56: =SUM(AV56:BG56) -> 0 | BI56: OTH | BJ56: WBS | BW56: =SUM(BK56:BV56) -> 0 | BX56: OTH | BY56: WBS | CL56: =SUM(BZ56:CK56) -> 0 | CM56: =U56-Z56 -> 205 | CN56: =V56-AA56 -> -0.6 | CO56: =W56-AB56 -> -329.55 | CP56: =X56-AC56 -> 183
A57: 55 | B57: C01RB1PSMP.LSH.LTL.LTC2K | C57: WBS | D57: 1 | E57: Ladle Transfer Car 2 Khurda | F57: NA | G57: AVIJIT SAHA | J57: 25000 | K57: 1985 | L57: 148 | M57: 32 | N57: 300 | O57: =SUM(K57:N57) -> 2465 | P57: 2364 | Q57: 114 | R57: 154 | S57: 312 | T57: =SUM(P57:S57) -> 2944 | U57: =K57-P57 -> -379 | V57: =L57-Q57 -> 34 | W57: =M57-R57 -> -122 | X57: =N57-S57 -> -12 | Y57: =SUM(U57:X57) -> -479 | Z57: =AS57 -> 0 | AA57: =BH57 -> 0 | AB57: =BW57 -> 0 | AC57: =CL57 -> 0 | AD57: =SUM(Z57:AC57) -> 0 | AE57: OTH | AF57: WBS | AS57: =SUM(AG57:AR57) -> 0 | AT57: OTH | AU57: WBS | BH57: =SUM(AV57:BG57) -> 0 | BI57: OTH | BJ57: WBS | BW57: =SUM(BK57:BV57) -> 0 | BX57: OTH | BY57: WBS | CL57: =SUM(BZ57:CK57) -> 0 | CM57: =U57-Z57 -> -379 | CN57: =V57-AA57 -> 34 | CO57: =W57-AB57 -> -122 | CP57: =X57-AC57 -> -12
A58: 56 | B58: 19678 | C58: SO | D58: 1 | E58: ROCKER FRAME ASSEMBLY | G58: AMULYA JENA | H58: 45870 | I58: 46295 | J58: 108785 | K58: 13731 | L58: 190 | M58: 120 | O58: =SUM(K58:N58) -> 14041 | P58: 9938 | T58: =SUM(P58:S58) -> 9938 | U58: =K58-P58 -> 3793 | V58: =L58-Q58 -> 190 | W58: =M58-R58 -> 120 | X58: =N58-S58 -> 0 | Y58: =SUM(U58:X58) -> 4103 | Z58: =AS58 -> 3793 | AA58: =BH58 -> 190 | AB58: =BW58 -> 120 | AC58: =CL58 -> 0 | AD58: =SUM(Z58:AC58) -> 4103 | AE58: OTH | AF58: SERVICE | AG58: 1897 | AH58: 1896 | AS58: =SUM(AG58:AR58) -> 3793 | AT58: OTH | AU58: SERVICE | AW58: 90 | AX58: 100 | BH58: =SUM(AV58:BG58) -> 190 | BI58: OTH | BJ58: SERVICE | BM58: 60 | BN58: 60 | BW58: =SUM(BK58:BV58) -> 120 | BX58: OTH | BY58: SERVICE | CL58: =SUM(BZ58:CK58) -> 0 | CM58: =U58-Z58 -> 0 | CN58: =V58-AA58 -> 0 | CO58: =W58-AB58 -> 0 | CP58: =X58-AC58 -> 0
A59: 57 | B59: A03607X01.10.3000 | C59: WBS | D59: 584 | E59: MOULD FOOT ROLLER | G59: AMAN SINGH | H59: 45870 | K59: 932 | M59: 1165 | N59: 60 | O59: =SUM(K59:N59) -> 2157 | T59: =SUM(P59:S59) -> 0 | U59: =K59-P59 -> 932 | V59: =L59-Q59 -> 0 | W59: =M59-R59 -> 1165 | X59: =N59-S59 -> 60 | Y59: =SUM(U59:X59) -> 2157 | Z59: =AS59 -> 932 | AA59: =BH59 -> 0 | AB59: =BW59 -> 1165 | AC59: =CL59 -> 60 | AD59: =SUM(Z59:AC59) -> 2157 | AE59: OTH | AF59: WBS | AG59: 200 | AH59: 200 | AI59: 200 | AJ59: 200 | AK59: 132 | AS59: =SUM(AG59:AR59) -> 932 | AT59: OTH | AU59: WBS | BH59: =SUM(AV59:BG59) -> 0 | BI59: OTH | BJ59: WBS | BK59: 250 | BL59: 250 | BM59: 250 | BN59: 250 | BO59: 165 | BW59: =SUM(BK59:BV59) -> 1165 | BX59: OTH | BY59: WBS | BZ59: 20 | CA59: 20 | CB59: 20 | CL59: =SUM(BZ59:CK59) -> 60 | CM59: =U59-Z59 -> 0 | CN59: =V59-AA59 -> 0 | CO59: =W59-AB59 -> 0 | CP59: =X59-AC59 -> 0
A60: 58 | B60: 18554 | C60: SO | D60: 1 | E60: WATERBOX,NARROW FACE CARRIER INCLUDING NECKDOWN BOLT & SWIVEL JOINT | G60: Kameshwaran | H60: 45880 | I60: 46132 | J60: 9240 | K60: 1710 | L60: 188 | M60: 55 | O60: =SUM(K60:N60) -> 1953 | P60: 767 | Q60: 179 | R60: 50 | T60: =SUM(P60:S60) -> 996 | U60: =K60-P60 -> 943 | V60: =L60-Q60 -> 9 | W60: =M60-R60 -> 5 | X60: =N60-S60 -> 0 | Y60: =SUM(U60:X60) -> 957 | Z60: =AS60 -> 943 | AA60: =BH60 -> 150 | AB60: =BW60 -> 5 | AC60: =CL60 -> 60 | AD60: =SUM(Z60:AC60) -> 1158 | AE60: OTH | AF60: SERVICE | AG60: 472 | AH60: 471 | AS60: =SUM(AG60:AR60) -> 943 | AT60: OTH | AU60: SERVICE | AX60: 150 | BH60: =SUM(AV60:BG60) -> 150 | BI60: OTH | BJ60: SERVICE | BK60: 5 | BW60: =SUM(BK60:BV60) -> 5 | BX60: OTH | BY60: SERVICE | CC60: 60 | CL60: =SUM(BZ60:CK60) -> 60 | CM60: =U60-Z60 -> 0 | CN60: =V60-AA60 -> -141 | CO60: =W60-AB60 -> 0 | CP60: =X60-AC60 -> -60
A61: 59 | B61: 19070 | C61: SO | D61: =1+1+1+1 -> 4 | E61: TOP & BOTTOM CHOCKS | F61: NA only ass | G61: SHASHIKUMAR | H61: 45888 | K61: 178 | L61: 320 | N61: 650 | O61: =SUM(K61:N61) -> 1148 | T61: =SUM(P61:S61) -> 0 | U61: =K61-P61 -> 178 | V61: =L61-Q61 -> 320 | W61: =M61-R61 -> 0 | X61: =N61-S61 -> 650 | Y61: =SUM(U61:X61) -> 1148 | Z61: =AS61 -> 0 | AA61: =BH61 -> 320 | AB61: =BW61 -> 650 | AC61: =CL61 -> 0 | AD61: =SUM(Z61:AC61) -> 970 | AE61: OTH | AF61: SERVICE | AS61: =SUM(AG61:AR61) -> 0 | AT61: OTH | AU61: SERVICE | AV61: 320 | BH61: =SUM(AV61:BG61) -> 320 | BI61: OTH | BJ61: SERVICE | BK61: 650 | BW61: =SUM(BK61:BV61) -> 650 | BX61: OTH | BY61: SERVICE | CL61: =SUM(BZ61:CK61) -> 0 | CM61: =U61-Z61 -> 178 | CN61: =V61-AA61 -> 0 | CO61: =W61-AB61 -> -650 | CP61: =X61-AC61 -> 650
A62: 60 | B62: 18082 | C62: SO | D62: 5 | E62: DOWNLEG ARRANGEMENT | G62: SANGRAM SWAIN | H62: 45889 | I62: 46071 | J62: 1453 | K62: 328 | N62: 80 | O62: =SUM(K62:N62) -> 408 | P62: 574 | R62: 22 | S62: 125 | T62: =SUM(P62:S62) -> 721 | U62: =K62-P62 -> -246 | V62: =L62-Q62 -> 0 | W62: =M62-R62 -> -22 | X62: =N62-S62 -> -45 | Y62: =SUM(U62:X62) -> -313 | Z62: =AS62 -> 0 | AA62: =BH62 -> 0 | AB62: =BW62 -> 0 | AC62: =CL62 -> 0 | AD62: =SUM(Z62:AC62) -> 0 | AE62: OTH | AF62: SERVICE | AS62: =SUM(AG62:AR62) -> 0 | AT62: OTH | AU62: SERVICE | BH62: =SUM(AV62:BG62) -> 0 | BI62: OTH | BJ62: SERVICE | BW62: =SUM(BK62:BV62) -> 0 | BX62: OTH | BY62: SERVICE | CL62: =SUM(BZ62:CK62) -> 0 | CM62: =U62-Z62 -> -246 | CN62: =V62-AA62 -> 0 | CO62: =W62-AB62 -> -22 | CP62: =X62-AC62 -> -45
A63: 61 | B63: 20565 | C63: SO | D63: 1 | E63: ETA PRESS 66- BALER ASSEMBLY | G63: KRISHNASIS | H63: 45880 | I63: 46173 | J63: 158000 | K63: 12420 | L63: 670 | M63: 1080 | N63: 2500 | O63: =SUM(K63:N63) -> 16670 | P63: 13633 | Q63: 875 | R63: 192 | S63: 461 | T63: =SUM(P63:S63) -> 15161 | U63: =K63-P63 -> -1213 | V63: =L63-Q63 -> -205 | W63: =M63-R63 -> 888 | X63: =N63-S63 -> 2039 | Y63: =SUM(U63:X63) -> 1509 | Z63: =AS63 -> 300 | AA63: =BH63 -> 600 | AB63: =BW63 -> 888 | AC63: =CL63 -> 2039 | AD63: =SUM(Z63:AC63) -> 3827 | AE63: Contract | AF63: DIRECT | AG63: 300 | AS63: =SUM(AG63:AR63) -> 300 | AT63: Contract | AU63: DIRECT | AV63: 600 | BH63: =SUM(AV63:BG63) -> 600 | BI63: Contract | BJ63: DIRECT | BK63: 445 | BL63: 443 | BW63: =SUM(BK63:BV63) -> 888 | BX63: Contract | BY63: DIRECT | BZ63: 1020 | CA63: 1019 | CL63: =SUM(BZ63:CK63) -> 2039 | CM63: =U63-Z63 -> -1513 | CN63: =V63-AA63 -> -805 | CO63: =W63-AB63 -> 0 | CP63: =X63-AC63 -> 0
A64: 62 | B64: 21311 | C64: SO | D64: 1 | E64: HSM F2 MAIN GB HOUSING | G64: ARUN KUMAR | H64: 45909 | I64: 46203 | J64: 13580 | K64: 1182 | L64: 170 | M64: 120 | N64: 80 | O64: =SUM(K64:N64) -> 1552 | P64: 1055 | Q64: 53.2 | R64: 16.9 | T64: =SUM(P64:S64) -> 1125.1 | U64: =K64-P64 -> 127 | V64: =L64-Q64 -> 116.8 | W64: =M64-R64 -> 103.1 | X64: =N64-S64 -> 80 | Y64: =SUM(U64:X64) -> 426.9 | Z64: =AS64 -> 127 | AA64: =BH64 -> 116.5 | AB64: =BW64 -> 103 | AC64: =CL64 -> 80 | AD64: =SUM(Z64:AC64) -> 426.5 | AE64: OTH | AF64: SERVICE | AG64: 127 | AS64: =SUM(AG64:AR64) -> 127 | AT64: OTH | AU64: SERVICE | AV64: 35 | AW64: =58.5+23 -> 81.5 | BH64: =SUM(AV64:BG64) -> 116.5 | BI64: OTH | BJ64: SERVICE | BK64: 103 | BW64: =SUM(BK64:BV64) -> 103 | BX64: OTH | BY64: SERVICE | CA64: 80 | CL64: =SUM(BZ64:CK64) -> 80 | CM64: =U64-Z64 -> 0 | CN64: =V64-AA64 -> 0.3 | CO64: =W64-AB64 -> 0.1 | CP64: =X64-AC64 -> 0
A65: 63 | B65: 21615 | C65: SO | D65: 1 | E65: RECONDITIONING OF WR & BUR CHOCKS | G65: RAVI RANJAN/SAMBIT | H65: 45912 | I65: 46168 | J65: 76705 | N65: 100 | O65: =SUM(K65:N65) -> 100 | P65: 1 | Q65: 116.5 | R65: 1786 | S65: 1169 | T65: =SUM(P65:S65) -> 3072.5 | U65: =K65-P65 -> -1 | V65: =L65-Q65 -> -116.5 | W65: =M65-R65 -> -1786 | X65: =N65-S65 -> -1069 | Y65: =SUM(U65:X65) -> -2972.5 | Z65: =AS65 -> 0 | AA65: =BH65 -> 0 | AB65: =BW65 -> 0 | AC65: =CL65 -> 0 | AD65: =SUM(Z65:AC65) -> 0 | AE65: OTH | AF65: SERVICE | AS65: =SUM(AG65:AR65) -> 0 | AT65: OTH | AU65: SERVICE | BH65: =SUM(AV65:BG65) -> 0 | BI65: OTH | BJ65: SERVICE | BW65: =SUM(BK65:BV65) -> 0 | BX65: OTH | BY65: SERVICE | CL65: =SUM(BZ65:CK65) -> 0 | CM65: =U65-Z65 -> -1 | CN65: =V65-AA65 -> -116.5 | CO65: =W65-AB65 -> -1786 | CP65: =X65-AC65 -> -1069
A66: 64 | B66: A02261M210.30.10.11P1010 | C66: WBS | D66: 2 | E66: LOWER SHELL | G66: AMULYA JENA | H66: 45915 | I66: 31ST MAR'26 15TH MAY'26 | J66: 109414 | K66: 9200 | M66: 200 | O66: =SUM(K66:N66) -> 9400 | P66: 6333.31 | Q66: 308 | R66: 138 | T66: =SUM(P66:S66) -> 6779.31 | U66: =K66-P66 -> 2866.69 | V66: =L66-Q66 -> -308 | W66: =M66-R66 -> 62 | X66: =N66-S66 -> 0 | Y66: =SUM(U66:X66) -> 2620.69 | Z66: =AS66 -> 2867 | AA66: =BH66 -> 0 | AB66: =BW66 -> 62 | AC66: =CL66 -> 0 | AD66: =SUM(Z66:AC66) -> 2929 | AE66: OTH | AF66: WBS | AG66: 1433.5 | AH66: 1433.5 | AS66: =SUM(AG66:AR66) -> 2867 | AT66: OTH | AU66: WBS | BH66: =SUM(AV66:BG66) -> 0 | BI66: OTH | BJ66: WBS | BK66: 62 | BW66: =SUM(BK66:BV66) -> 62 | BX66: OTH | BY66: WBS | CL66: =SUM(BZ66:CK66) -> 0 | CM66: =U66-Z66 -> -0.31 | CN66: =V66-AA66 -> -308 | CO66: =W66-AB66 -> 0 | CP66: =X66-AC66 -> 0
A67: 65 | B67: A02261M210.30.10.11P1020 | C67: WBS | D67: 2 | E67: UPPER SHELL | F67: NA | G67: REJEESH | H67: 45915 | I67: 31ST MAR'26 15TH MAY'26 | J67: 63966 | K67: 11470 | M67: 200 | O67: =SUM(K67:N67) -> 11670 | P67: 12229.14 | Q67: 11.8 | R67: 517.12 | T67: =SUM(P67:S67) -> 12758.06 | U67: =K67-P67 -> -759.14 | V67: =L67-Q67 -> -11.8 | W67: =M67-R67 -> -317.12 | X67: =N67-S67 -> 0 | Y67: =SUM(U67:X67) -> -1088.06 | Z67: =AS67 -> 4437 | AA67: =BH67 -> 3 | AB67: =BW67 -> 165 | AC67: =CL67 -> 0 | AD67: =SUM(Z67:AC67) -> 4605 | AE67: OTH | AF67: WBS | AG67: 4437 | AS67: =SUM(AG67:AR67) -> 4437 | AT67: OTH | AU67: WBS | AV67: 3 | BH67: =SUM(AV67:BG67) -> 3 | BI67: OTH | BJ67: WBS | BK67: 165 | BW67: =SUM(BK67:BV67) -> 165 | BX67: OTH | BY67: WBS | CL67: =SUM(BZ67:CK67) -> 0 | CM67: =U67-Z67 -> -5196.14 | CN67: =V67-AA67 -> -14.8 | CO67: =W67-AB67 -> -482.12 | CP67: =X67-AC67 -> 0
A68: 66 | B68: A02261M210.30.10.11P1010 | C68: WBS | D68: 12 | E68: INJECTOR BOX - 2 PC ,OXYGEN INJECTOR -10 PC | G68: RAVI RANJAN | H68: 45925 | I68: 31ST MAR'26 15TH MAY'26 | J68: 1780 | K68: 776 | L68: 62 | M68: 240 | O68: =SUM(K68:N68) -> 1078 | T68: =SUM(P68:S68) -> 0 | U68: =K68-P68 -> 776 | V68: =L68-Q68 -> 62 | W68: =M68-R68 -> 240 | X68: =N68-S68 -> 0 | Y68: =SUM(U68:X68) -> 1078 | Z68: =AS68 -> 776 | AA68: =BH68 -> 62 | AB68: =BW68 -> 240 | AC68: =CL68 -> 0 | AD68: =SUM(Z68:AC68) -> 1078 | AE68: OTH | AF68: WBS | AG68: 776 | AS68: =SUM(AG68:AR68) -> 776 | AT68: OTH | AU68: WBS | AW68: 62 | BH68: =SUM(AV68:BG68) -> 62 | BI68: OTH | BJ68: WBS | BK68: 240 | BW68: =SUM(BK68:BV68) -> 240 | BX68: OTH | BY68: WBS | CL68: =SUM(BZ68:CK68) -> 0 | CM68: =U68-Z68 -> 0 | CN68: =V68-AA68 -> 0 | CO68: =W68-AB68 -> 0 | CP68: =X68-AC68 -> 0
A69: 67 | B69: 22002 | C69: SO | D69: 1 | E69: CVC BLOCK F5-F7 OP EXIT SIDE | G69: RAVI RANJAN/SASHI | H69: 45919 | I69: 46070 | J69: 1781 | L69: 230 | N69: 100 | O69: =SUM(K69:N69) -> 330 | P69: 15 | Q69: 234.5 | R69: 164.5 | T69: =SUM(P69:S69) -> 414 | U69: =K69-P69 -> -15 | V69: =L69-Q69 -> -4.5 | W69: =M69-R69 -> -164.5 | X69: =N69-S69 -> 100 | Y69: =SUM(U69:X69) -> -84 | Z69: =AS69 -> 0 | AA69: =BH69 -> 0 | AB69: =BW69 -> 0 | AC69: =CL69 -> 100 | AD69: =SUM(Z69:AC69) -> 100 | AE69: OTH | AF69: SERVICE | AS69: =SUM(AG69:AR69) -> 0 | AT69: OTH | AU69: SERVICE | BH69: =SUM(AV69:BG69) -> 0 | BI69: OTH | BJ69: SERVICE | BW69: =SUM(BK69:BV69) -> 0 | BX69: OTH | BY69: SERVICE | BZ69: 100 | CL69: =SUM(BZ69:CK69) -> 100 | CM69: =U69-Z69 -> -15 | CN69: =V69-AA69 -> -4.5 | CO69: =W69-AB69 -> -164.5 | CP69: =X69-AC69 -> 0
A70: 68 | B70: S000722CAS.SCP.STG.HOS | C70: 21135 | D70: 1 | E70: SEGMENT 7(Loose side) | G70: Kameshwaran | H70: 45919 | I70: 46203 | J70: 33920 | K70: 310 | L70: 190 | M70: 190 | N70: 300 | O70: =SUM(K70:N70) -> 990 | P70: 1068.3 | Q70: 23.8 | R70: 72.6 | T70: =SUM(P70:S70) -> 1164.7 | U70: =K70-P70 -> -758.3 | V70: =L70-Q70 -> 166.2 | W70: =M70-R70 -> 117.4 | X70: =N70-S70 -> 300 | Y70: =SUM(U70:X70) -> -174.7 | Z70: =AS70 -> 100 | AA70: =BH70 -> 166 | AB70: =BW70 -> 0 | AC70: =CL70 -> 300 | AD70: =SUM(Z70:AC70) -> 566 | AE70: OTH | AF70: SERVICE | AG70: 100 | AS70: =SUM(AG70:AR70) -> 100 | AT70: OTH | AU70: SERVICE | AV70: 166 | BH70: =SUM(AV70:BG70) -> 166 | BI70: OTH | BJ70: SERVICE | BW70: =SUM(BK70:BV70) -> 0 | BX70: OTH | BY70: SERVICE | CA70: 300 | CL70: =SUM(BZ70:CK70) -> 300 | CM70: =U70-Z70 -> -858.3 | CN70: =V70-AA70 -> 0.2 | CO70: =W70-AB70 -> 117.4 | CP70: =X70-AC70 -> 0
A71: 69 | B71: 14154 | C71: SO | D71: 1 | E71: PIVOT ARM | F71: NA | G71: SHASHIKUMAR | H71: 45922 | I71: 46070 | J71: 5816 | K71: 7 | L71: 113 | O71: =SUM(K71:N71) -> 120 | P71: 10.8 | Q71: 183 | R71: 39.45 | S71: 10 | T71: =SUM(P71:S71) -> 243.25 | U71: =K71-P71 -> -3.8 | V71: =L71-Q71 -> -70 | W71: =M71-R71 -> -39.45 | X71: =N71-S71 -> -10 | Y71: =SUM(U71:X71) -> -123.25 | Z71: =AS71 -> 0 | AA71: =BH71 -> 0 | AB71: =BW71 -> 0 | AC71: =CL71 -> 0 | AD71: =SUM(Z71:AC71) -> 0 | AE71: OTH | AF71: SERVICE | AS71: =SUM(AG71:AR71) -> 0 | AT71: OTH | AU71: SERVICE | BH71: =SUM(AV71:BG71) -> 0 | BI71: OTH | BJ71: SERVICE | BW71: =SUM(BK71:BV71) -> 0 | BX71: OTH | BY71: SERVICE | CL71: =SUM(BZ71:CK71) -> 0 | CM71: =U71-Z71 -> -3.8 | CN71: =V71-AA71 -> -70 | CO71: =W71-AB71 -> -39.45 | CP71: =X71-AC71 -> -10
A72: 70 | B72: 22085 | C72: SO | D72: =1+1+1 -> 3 | E72: EAF ROOF SPOKE FRAME,ROOF LIFTING FRAME & LIFTING FORK | G72: REJEESH | H72: 45923 | I72: 46142 | J72: 27289 | K72: 3800 | L72: 40 | M72: 28 | O72: =SUM(K72:N72) -> 3868 | P72: 3634.5 | Q72: 14.6 | R72: 47.65 | T72: =SUM(P72:S72) -> 3696.75 | U72: =K72-P72 -> 165.5 | V72: =L72-Q72 -> 25.4 | W72: =M72-R72 -> -19.65 | X72: =N72-S72 -> 0 | Y72: =SUM(U72:X72) -> 171.25 | Z72: =AS72 -> 166 | AA72: =BH72 -> 25 | AB72: =BW72 -> 0 | AC72: =CL72 -> 0 | AD72: =SUM(Z72:AC72) -> 191 | AE72: OTH | AF72: SERVICE | AG72: 166 | AS72: =SUM(AG72:AR72) -> 166 | AT72: OTH | AU72: SERVICE | AV72: 25 | BH72: =SUM(AV72:BG72) -> 25 | BI72: OTH | BJ72: SERVICE | BW72: =SUM(BK72:BV72) -> 0 | BX72: OTH | BY72: SERVICE | CL72: =SUM(BZ72:CK72) -> 0 | CM72: =U72-Z72 -> -0.5 | CN72: =V72-AA72 -> 0.4 | CO72: =W72-AB72 -> -19.65 | CP72: =X72-AC72 -> 0
A73: 71 | B73: 21010 | C73: SO | D73: 1 | E73: REFURBISHMENT OF LSV/USV DRIVE | G73: SANGRAM SWAIN | H73: 45930 | J73: 210 | O73: =SUM(K73:N73) -> 0 | T73: =SUM(P73:S73) -> 0 | U73: =K73-P73 -> 0 | V73: =L73-Q73 -> 0 | W73: =M73-R73 -> 0 | X73: =N73-S73 -> 0 | Y73: =SUM(U73:X73) -> 0 | Z73: =AS73 -> 0 | AA73: =BH73 -> 0 | AB73: =BW73 -> 0 | AC73: =CL73 -> 0 | AD73: =SUM(Z73:AC73) -> 0 | AE73: OTH | AF73: SERVICE | AS73: =SUM(AG73:AR73) -> 0 | AT73: OTH | AU73: SERVICE | BH73: =SUM(AV73:BG73) -> 0 | BI73: OTH | BJ73: SERVICE | BW73: =SUM(BK73:BV73) -> 0 | BX73: OTH | BY73: SERVICE | CL73: =SUM(BZ73:CK73) -> 0 | CM73: =U73-Z73 -> 0 | CN73: =V73-AA73 -> 0 | CO73: =W73-AB73 -> 0 | CP73: =X73-AC73 -> 0
A74: 72 | B74: S000850SMP.FTP.WCG.DUC S000850SMP.FTP.WCG.COH | C74: 24910 | D74: 3 | E74: COOLED DUCT, MOVABLE ELBOW & MOVABLE ELBOW | G74: REJEESH | H74: 45931 | I74: 46356 | J74: 163400 | K74: 67096 | L74: 1634 | O74: =SUM(K74:N74) -> 68730 | P74: 5641.06 | T74: =SUM(P74:S74) -> 5641.06 | U74: =K74-P74 -> 61454.94 | V74: =L74-Q74 -> 1634 | W74: =M74-R74 -> 0 | X74: =N74-S74 -> 0 | Y74: =SUM(U74:X74) -> 63088.94 | Z74: =AS74 -> 61455 | AA74: =BH74 -> 1633 | AB74: =BW74 -> 0 | AC74: =CL74 -> 0 | AD74: =SUM(Z74:AC74) -> 63088 | AE74: Group | AF74: DIRECT | AG74: 10242.5 | AH74: 10242.5 | AI74: 10242.5 | AJ74: 10242.5 | AK74: 10242.5 | AL74: 10242.5 | AS74: =SUM(AG74:AR74) -> 61455 | AT74: Group | AU74: DIRECT | AV74: 327 | AW74: 327 | AX74: 327 | AY74: 326 | AZ74: 326 | BH74: =SUM(AV74:BG74) -> 1633 | BI74: Group | BJ74: DIRECT | BW74: =SUM(BK74:BV74) -> 0 | BX74: Group | BY74: DIRECT | CL74: =SUM(BZ74:CK74) -> 0 | CM74: =U74-Z74 -> -0.06 | CN74: =V74-AA74 -> 1 | CO74: =W74-AB74 -> 0 | CP74: =X74-AC74 -> 0
A75: 73 | B75: 22574 | C75: SO | D75: 2 | E75: EAF UPPER SHELL FRAME W/SLAG DOOR & EAF ROOF SPOKE FRAME | G75: REJEESH | H75: 45931 | I75: 46193 | J75: 13252 | K75: 4670 | M75: 46 | O75: =SUM(K75:N75) -> 4716 | P75: 323 | T75: =SUM(P75:S75) -> 323 | U75: =K75-P75 -> 4347 | V75: =L75-Q75 -> 0 | W75: =M75-R75 -> 46 | X75: =N75-S75 -> 0 | Y75: =SUM(U75:X75) -> 4393 | Z75: =AS75 -> 4347 | AA75: =BH75 -> 0 | AB75: =BW75 -> 46 | AC75: =CL75 -> 0 | AD75: =SUM(Z75:AC75) -> 4393 | AE75: OTH | AF75: SERVICE | AG75: 1449 | AH75: 1449 | AI75: 1449 | AS75: =SUM(AG75:AR75) -> 4347 | AT75: OTH | AU75: SERVICE | BH75: =SUM(AV75:BG75) -> 0 | BI75: OTH | BJ75: SERVICE | BM75: 46 | BW75: =SUM(BK75:BV75) -> 46 | BX75: OTH | BY75: SERVICE | CL75: =SUM(BZ75:CK75) -> 0 | CM75: =U75-Z75 -> 0 | CN75: =V75-AA75 -> 0 | CO75: =W75-AB75 -> 0 | CP75: =X75-AC75 -> 0
A76: 74 | B76: 22797 | C76: SO | D76: 5 | E76: SKIRT ASSEMBLY, LOWER STACK, COOLING RING, MOVABLE SKIRT & LOWER HOOD | G76: REJEESH | H76: 45938 | I76: 46173 | J76: 46190 | K76: 10456 | M76: 240 | O76: =SUM(K76:N76) -> 10696 | P76: 5411 | T76: =SUM(P76:S76) -> 5411 | U76: =K76-P76 -> 5045 | V76: =L76-Q76 -> 0 | W76: =M76-R76 -> 240 | X76: =N76-S76 -> 0 | Y76: =SUM(U76:X76) -> 5285 | Z76: =AS76 -> 5045 | AA76: =BH76 -> 0 | AB76: =BW76 -> 240 | AC76: =CL76 -> 0 | AD76: =SUM(Z76:AC76) -> 5285 | AE76: OTH | AF76: SERVICE | AG76: 1261.25 | AH76: 1261.25 | AI76: 1261.25 | AJ76: 1261.25 | AS76: =SUM(AG76:AR76) -> 5045 | AT76: OTH | AU76: SERVICE | BH76: =SUM(AV76:BG76) -> 0 | BI76: OTH | BJ76: SERVICE | BK76: 40 | BL76: 100 | BM76: 100 | BW76: =SUM(BK76:BV76) -> 240 | BX76: OTH | BY76: SERVICE | CL76: =SUM(BZ76:CK76) -> 0 | CM76: =U76-Z76 -> 0 | CN76: =V76-AA76 -> 0 | CO76: =W76-AB76 -> 0 | CP76: =X76-AC76 -> 0
A77: 75 | B77: 23426 | C77: SO | D77: 1 | E77: DIPPER HANDLE ASSY | G77: AVIJIT SAHA | H77: 45931 | I77: 46223 | J77: 47405 | N77: 50 | O77: =SUM(K77:N77) -> 50 | T77: =SUM(P77:S77) -> 0 | U77: =K77-P77 -> 0 | V77: =L77-Q77 -> 0 | W77: =M77-R77 -> 0 | X77: =N77-S77 -> 50 | Y77: =SUM(U77:X77) -> 50 | Z77: =AS77 -> 0 | AA77: =BH77 -> 0 | AB77: =BW77 -> 0 | AC77: =CL77 -> 50 | AD77: =SUM(Z77:AC77) -> 50 | AE77: Contract | AF77: DIRECT | AS77: =SUM(AG77:AR77) -> 0 | AT77: Contract | AU77: DIRECT | BH77: =SUM(AV77:BG77) -> 0 | BI77: Contract | BJ77: DIRECT | BW77: =SUM(BK77:BV77) -> 0 | BX77: Contract | BY77: DIRECT | CA77: 50 | CL77: =SUM(BZ77:CK77) -> 50 | CM77: =U77-Z77 -> 0 | CN77: =V77-AA77 -> 0 | CO77: =W77-AB77 -> 0 | CP77: =X77-AC77 -> 0
A78: 76 | B78: 23424 | C78: SO | D78: 1 | E78: HANDLE MACHINING | G78: AVIJIT SAHA | H78: 45931 | I78: 46218 | J78: 47405 | K78: 4112.2759 | L78: 110 | M78: 255 | O78: =SUM(K78:N78) -> 4477.2759 | P78: 3940 | T78: =SUM(P78:S78) -> 3940 | U78: =K78-P78 -> 172.27592 | V78: =L78-Q78 -> 110 | W78: =M78-R78 -> 255 | X78: =N78-S78 -> 0 | Y78: =SUM(U78:X78) -> 537.27592 | Z78: =AS78 -> 172 | AA78: =BH78 -> 110 | AB78: =BW78 -> 255 | AC78: =CL78 -> 0 | AD78: =SUM(Z78:AC78) -> 537 | AE78: Contract | AF78: DIRECT | AG78: 100 | AH78: 72 | AS78: =SUM(AG78:AR78) -> 172 | AT78: Contract | AU78: DIRECT | AW78: 110 | BH78: =SUM(AV78:BG78) -> 110 | BI78: Contract | BJ78: DIRECT | BL78: 255 | BW78: =SUM(BK78:BV78) -> 255 | BX78: Contract | BY78: DIRECT | CL78: =SUM(BZ78:CK78) -> 0 | CM78: =U78-Z78 -> 0.27592273 | CN78: =V78-AA78 -> 0 | CO78: =W78-AB78 -> 0 | CP78: =X78-AC78 -> 0
A79: 77 | B79: 22795 | C79: SO | D79: 2 | E79: ASSEMBLY ABGT L4000 & ACC. | G79: SANGRAM SWAIN | H79: 45940 | I79: 46074 | J79: 6100 | K79: 1850 | M79: 40 | O79: =SUM(K79:N79) -> 1890 | P79: 115.45 | R79: 22.8 | T79: =SUM(P79:S79) -> 138.25 | U79: =K79-P79 -> 1734.55 | V79: =L79-Q79 -> 0 | W79: =M79-R79 -> 17.2 | X79: =N79-S79 -> 0 | Y79: =SUM(U79:X79) -> 1751.75 | Z79: =AS79 -> 1735 | AA79: =BH79 -> 0 | AB79: =BW79 -> 17 | AC79: =CL79 -> 0 | AD79: =SUM(Z79:AC79) -> 1752 | AE79: OTH | AF79: SERVICE | AG79: 579 | AH79: 578 | AI79: 578 | AS79: =SUM(AG79:AR79) -> 1735 | AT79: OTH | AU79: SERVICE | BH79: =SUM(AV79:BG79) -> 0 | BI79: OTH | BJ79: SERVICE | BL79: 17 | BW79: =SUM(BK79:BV79) -> 17 | BX79: OTH | BY79: SERVICE | CL79: =SUM(BZ79:CK79) -> 0 | CM79: =U79-Z79 -> -0.45 | CN79: =V79-AA79 -> 0 | CO79: =W79-AB79 -> 0.2 | CP79: =X79-AC79 -> 0
A80: 78 | B80: S000781CAS1.SCP.STG.HOS S000781CAS2.SCP.STG.HOS S000781CAS3.SCP.STG.HOS | C80: 22335 | D80: 24 | E80: ROLLER ASSEMBLY | F80: NA only ass | G80: Kameshwaran | H80: 45946 | I80: 46203 | J80: 13570 | K80: 22 | N80: 400 | O80: =SUM(K80:N80) -> 422 | T80: =SUM(P80:S80) -> 0 | U80: =K80-P80 -> 22 | V80: =L80-Q80 -> 0 | W80: =M80-R80 -> 0 | X80: =N80-S80 -> 400 | Y80: =SUM(U80:X80) -> 422 | Z80: =AS80 -> 0 | AA80: =BH80 -> 0 | AB80: =BW80 -> 0 | AC80: =CL80 -> 400 | AD80: =SUM(Z80:AC80) -> 400 | AE80: OTH | AF80: SERVICE | AS80: =SUM(AG80:AR80) -> 0 | AT80: OTH | AU80: SERVICE | BH80: =SUM(AV80:BG80) -> 0 | BI80: OTH | BJ80: SERVICE | BW80: =SUM(BK80:BV80) -> 0 | BX80: OTH | BY80: SERVICE | CB80: 400 | CL80: =SUM(BZ80:CK80) -> 400 | CM80: =U80-Z80 -> 22 | CN80: =V80-AA80 -> 0 | CO80: =W80-AB80 -> 0 | CP80: =X80-AC80 -> 0
A81: 79 | B81: 23583 | C81: SO | D81: 3 | E81: REFURBISHMENT OF DISTRIBUTION CHUTE -3.8 & 3.5 | G81: SANGRAM SWAIN | H81: 45952 | I81: 46220 | J81: 9710 | M81: 18 | N81: 500 | O81: =SUM(K81:N81) -> 518 | P81: 15.5 | Q81: 35.4 | R81: 6 | S81: 25.5 | T81: =SUM(P81:S81) -> 82.4 | U81: =K81-P81 -> -15.5 | V81: =L81-Q81 -> -35.4 | W81: =M81-R81 -> 12 | X81: =N81-S81 -> 474.5 | Y81: =SUM(U81:X81) -> 435.6 | Z81: =AS81 -> 0 | AA81: =BH81 -> 0 | AB81: =BW81 -> 12 | AC81: =CL81 -> 0 | AD81: =SUM(Z81:AC81) -> 12 | AE81: OTH | AF81: SERVICE | AS81: =SUM(AG81:AR81) -> 0 | AT81: OTH | AU81: SERVICE | BH81: =SUM(AV81:BG81) -> 0 | BI81: OTH | BJ81: SERVICE | BK81: 12 | BW81: =SUM(BK81:BV81) -> 12 | BX81: OTH | BY81: SERVICE | CL81: =SUM(BZ81:CK81) -> 0 | CM81: =U81-Z81 -> -15.5 | CN81: =V81-AA81 -> -35.4 | CO81: =W81-AB81 -> 0 | CP81: =X81-AC81 -> 474.5
A82: 80 | B82: 23047 | C82: SO | D82: 1 | E82: ROLL FORCE CYLINDER VERTICAL AGC | G82: SHASHIKUMAR | H82: 45952 | I82: 46164 | J82: 3413 | K82: 24 | L82: 852 | M82: 152 | N82: 192 | O82: =SUM(K82:N82) -> 1220 | R82: 215 | T82: =SUM(P82:S82) -> 215 | U82: =K82-P82 -> 24 | V82: =L82-Q82 -> 852 | W82: =M82-R82 -> -63 | X82: =N82-S82 -> 192 | Y82: =SUM(U82:X82) -> 1005 | Z82: =AS82 -> 24 | AA82: =BH82 -> 852 | AB82: =BW82 -> 0 | AC82: =CL82 -> 0 | AD82: =SUM(Z82:AC82) -> 876 | AE82: OTH | AF82: SERVICE | AG82: 24 | AS82: =SUM(AG82:AR82) -> 24 | AT82: OTH | AU82: SERVICE | AV82: 426 | AW82: 426 | BH82: =SUM(AV82:BG82) -> 852 | BI82: OTH | BJ82: SERVICE | BW82: =SUM(BK82:BV82) -> 0 | BX82: OTH | BY82: SERVICE | CL82: =SUM(BZ82:CK82) -> 0 | CM82: =U82-Z82 -> 0 | CN82: =V82-AA82 -> 0 | CO82: =W82-AB82 -> -63 | CP82: =X82-AC82 -> 192
A83: 81 | B83: 23634 | C83: SO | D83: 5 | E83: ADJUSTING SKIRT & INSPECTION COVER | F83: APEX | G83: REJEESH | H83: 45957 | I83: 46231 | J83: 19350 | K83: 4969.5 | L83: 110 | O83: =SUM(K83:N83) -> 5079.5 | T83: =SUM(P83:S83) -> 0 | U83: =K83-P83 -> 4969.5 | V83: =L83-Q83 -> 110 | W83: =M83-R83 -> 0 | X83: =N83-S83 -> 0 | Y83: =SUM(U83:X83) -> 5079.5 | Z83: =AS83 -> 0 | AA83: =BH83 -> 0 | AB83: =BW83 -> 0 | AC83: =CL83 -> 0 | AD83: =SUM(Z83:AC83) -> 0 | AE83: OTH | AF83: SERVICE | AS83: =SUM(AG83:AR83) -> 0 | AT83: OTH | AU83: SERVICE | BH83: =SUM(AV83:BG83) -> 0 | BI83: OTH | BJ83: SERVICE | BW83: =SUM(BK83:BV83) -> 0 | BX83: OTH | BY83: SERVICE | CL83: =SUM(BZ83:CK83) -> 0 | CM83: =U83-Z83 -> 4969.5 | CN83: =V83-AA83 -> 110 | CO83: =W83-AB83 -> 0 | CP83: =X83-AC83 -> 0
A84: 82 | B84: 23814 | C84: SO | D84: 1 | E84: SPARE;COOLING RING FOR VESSEL 3,VESSEL | G84: REJEESH | H84: 45958 | I84: 46196 | J84: 6587 | K84: 1514 | M84: 46 | O84: =SUM(K84:N84) -> 1560 | P84: 893.8 | T84: =SUM(P84:S84) -> 893.8 | U84: =K84-P84 -> 620.2 | V84: =L84-Q84 -> 0 | W84: =M84-R84 -> 46 | X84: =N84-S84 -> 0 | Y84: =SUM(U84:X84) -> 666.2 | Z84: =AS84 -> 620 | AA84: =BH84 -> 0 | AB84: =BW84 -> 46 | AC84: =CL84 -> 0 | AD84: =SUM(Z84:AC84) -> 666 | AE84: OTH | AF84: SERVICE | AG84: 310 | AH84: 310 | AS84: =SUM(AG84:AR84) -> 620 | AT84: OTH | AU84: SERVICE | BH84: =SUM(AV84:BG84) -> 0 | BI84: OTH | BJ84: SERVICE | BL84: 46 | BW84: =SUM(BK84:BV84) -> 46 | BX84: OTH | BY84: SERVICE | CL84: =SUM(BZ84:CK84) -> 0 | CM84: =U84-Z84 -> 0.2 | CN84: =V84-AA84 -> 0 | CO84: =W84-AB84 -> 0 | CP84: =X84-AC84 -> 0
A85: 83 | B85: 24007 | C85: SO | D85: 2 | E85: BOOM & ARM | G85: Kameshwaran | H85: 45955 | I85: 46213 | J85: 44190 | K85: 3125 | L85: 175 | M85: 87 | N85: 150 | O85: =SUM(K85:N85) -> 3537 | P85: 865 | T85: =SUM(P85:S85) -> 865 | U85: =K85-P85 -> 2260 | V85: =L85-Q85 -> 175 | W85: =M85-R85 -> 87 | X85: =N85-S85 -> 150 | Y85: =SUM(U85:X85) -> 2672 | Z85: =AS85 -> 2260 | AA85: =BH85 -> 175 | AB85: =BW85 -> 87 | AC85: =CL85 -> 50 | AD85: =SUM(Z85:AC85) -> 2572 | AE85: Contract | AF85: DIRECT | AG85: 754 | AH85: 753 | AI85: 753 | AS85: =SUM(AG85:AR85) -> 2260 | AT85: Contract | AU85: DIRECT | AV85: 75 | AY85: 100 | BH85: =SUM(AV85:BG85) -> 175 | BI85: Contract | BJ85: DIRECT | BK85: 87 | BW85: =SUM(BK85:BV85) -> 87 | BX85: Contract | BY85: DIRECT | CC85: 50 | CL85: =SUM(BZ85:CK85) -> 50 | CM85: =U85-Z85 -> 0 | CN85: =V85-AA85 -> 0 | CO85: =W85-AB85 -> 0 | CP85: =X85-AC85 -> 100
A86: 84 | B86: 23817 | C86: SO | D86: 1 | E86: SPARE KIT FOR GSSV ND1200 | F86: NA | G86: SANGRAM SWAIN | H86: 45960 | I86: 46007 | J86: 2800 | O86: =SUM(K86:N86) -> 0 | T86: =SUM(P86:S86) -> 0 | U86: =K86-P86 -> 0 | V86: =L86-Q86 -> 0 | W86: =M86-R86 -> 0 | X86: =N86-S86 -> 0 | Y86: =SUM(U86:X86) -> 0 | Z86: =AS86 -> 0 | AA86: =BH86 -> 0 | AB86: =BW86 -> 0 | AC86: =CL86 -> 0 | AD86: =SUM(Z86:AC86) -> 0 | AE86: OTH | AF86: SERVICE | AS86: =SUM(AG86:AR86) -> 0 | AT86: OTH | AU86: SERVICE | BH86: =SUM(AV86:BG86) -> 0 | BI86: OTH | BJ86: SERVICE | BW86: =SUM(BK86:BV86) -> 0 | BX86: OTH | BY86: SERVICE | CL86: =SUM(BZ86:CK86) -> 0 | CM86: =U86-Z86 -> 0 | CN86: =V86-AA86 -> 0 | CO86: =W86-AB86 -> 0 | CP86: =X86-AC86 -> 0
A87: 85 | B87: 18848 | C87: SO | D87: 1 | E87: REFURBISHMENT OF DISTRIBUTION CHUTE -REINFORCED TYPE | G87: SANGRAM SWAIN | H87: 45960 | J87: 6820 | L87: 40 | N87: 500 | O87: =SUM(K87:N87) -> 540 | S87: 112 | T87: =SUM(P87:S87) -> 112 | U87: =K87-P87 -> 0 | V87: =L87-Q87 -> 40 | W87: =M87-R87 -> 0 | X87: =N87-S87 -> 388 | Y87: =SUM(U87:X87) -> 428 | Z87: =AS87 -> 0 | AA87: =BH87 -> 40 | AB87: =BW87 -> 0 | AC87: =CL87 -> 0 | AD87: =SUM(Z87:AC87) -> 40 | AE87: OTH | AF87: SERVICE | AS87: =SUM(AG87:AR87) -> 0 | AT87: OTH | AU87: SERVICE | AY87: 40 | BH87: =SUM(AV87:BG87) -> 40 | BI87: OTH | BJ87: SERVICE | BW87: =SUM(BK87:BV87) -> 0 | BX87: OTH | BY87: SERVICE | CL87: =SUM(BZ87:CK87) -> 0 | CM87: =U87-Z87 -> 0 | CN87: =V87-AA87 -> 0 | CO87: =W87-AB87 -> 0 | CP87: =X87-AC87 -> 388
A88: 86 | B88: 22911 | C88: SO | D88: 2 | E88: COOLING RING & SKIRT WITH LIFTING BRACKET | G88: REJEESH | H88: 45939 | I88: 46242 | J88: 6650 | K88: 1676 | M88: 46 | O88: =SUM(K88:N88) -> 1722 | P88: 191 | T88: =SUM(P88:S88) -> 191 | U88: =K88-P88 -> 1485 | V88: =L88-Q88 -> 0 | W88: =M88-R88 -> 46 | X88: =N88-S88 -> 0 | Y88: =SUM(U88:X88) -> 1531 | Z88: =AS88 -> 1485 | AA88: =BH88 -> 0 | AB88: =BW88 -> 46 | AC88: =CL88 -> 0 | AD88: =SUM(Z88:AC88) -> 1531 | AE88: OTH | AF88: SERVICE | AG88: 297 | AH88: 297 | AI88: 297 | AJ88: 297 | AK88: 297 | AS88: =SUM(AG88:AR88) -> 1485 | AT88: OTH | AU88: SERVICE | BH88: =SUM(AV88:BG88) -> 0 | BI88: OTH | BJ88: SERVICE | BN88: 46 | BW88: =SUM(BK88:BV88) -> 46 | BX88: OTH | BY88: SERVICE | CL88: =SUM(BZ88:CK88) -> 0 | CM88: =U88-Z88 -> 0 | CN88: =V88-AA88 -> 0 | CO88: =W88-AB88 -> 0 | CP88: =X88-AC88 -> 0
A89: 87 | B89: A03520M220.35.20.60P1100 | C89: WBS | D89: 1 | E89: INTERBAY TRANSFER CAR | G89: ARUN KUMAR | H89: 45965 | I89: 46275 | J89: 88945 | K89: 6755 | L89: 130 | M89: 42.7 | N89: 700 | O89: =SUM(K89:N89) -> 7627.7 | P89: 5122 | Q89: 205 | R89: 43 | T89: =SUM(P89:S89) -> 5370 | U89: =K89-P89 -> 1633 | V89: =L89-Q89 -> -75 | W89: =M89-R89 -> -0.3 | X89: =N89-S89 -> 700 | Y89: =SUM(U89:X89) -> 2257.7 | Z89: =AS89 -> 1633 | AA89: =BH89 -> 120 | AB89: =BW89 -> 30 | AC89: =CL89 -> 580 | AD89: =SUM(Z89:AC89) -> 2363 | AE89: OTH | AF89: WBS | AG89: 1000 | AH89: 633 | AS89: =SUM(AG89:AR89) -> 1633 | AT89: OTH | AU89: WBS | AV89: 60 | AW89: 60 | BH89: =SUM(AV89:BG89) -> 120 | BI89: OTH | BJ89: WBS | BK89: 22 | BL89: 8 | BW89: =SUM(BK89:BV89) -> 30 | BX89: OTH | BY89: WBS | CC89: 580 | CL89: =SUM(BZ89:CK89) -> 580 | CM89: =U89-Z89 -> 0 | CN89: =V89-AA89 -> -195 | CO89: =W89-AB89 -> -30.3 | CP89: =X89-AC89 -> 120
A90: 88 | B90: 23985 | C90: SO | D90: 2 | E90: DEWATERING DRUM & FEEDING OF DRUM | G90: SANGRAM SWAIN | H90: 45965 | I90: 46264 | J90: 42450 | K90: 1125 | L90: 16 | M90: 40 | O90: =SUM(K90:N90) -> 1181 | P90: 4797 | Q90: 199.8 | R90: 81.15 | T90: =SUM(P90:S90) -> 5077.95 | U90: =K90-P90 -> -3672 | V90: =L90-Q90 -> -183.8 | W90: =M90-R90 -> -41.15 | X90: =N90-S90 -> 0 | Y90: =SUM(U90:X90) -> -3896.95 | Z90: =AS90 -> 0 | AA90: =BH90 -> 0 | AB90: =BW90 -> 0 | AC90: =CL90 -> 0 | AD90: =SUM(Z90:AC90) -> 0 | AE90: OTH | AF90: SERVICE | AS90: =SUM(AG90:AR90) -> 0 | AT90: OTH | AU90: SERVICE | BH90: =SUM(AV90:BG90) -> 0 | BI90: OTH | BJ90: SERVICE | BW90: =SUM(BK90:BV90) -> 0 | BX90: OTH | BY90: SERVICE | CL90: =SUM(BZ90:CK90) -> 0 | CM90: =U90-Z90 -> -3672 | CN90: =V90-AA90 -> -183.8 | CO90: =W90-AB90 -> -41.15 | CP90: =X90-AC90 -> 0
A91: 89 | B91: S000645SMP.HMH.HMC.LTCKH | C91: 18685 | D91: =2+1 -> 3 | E91: HOT METAL TRANSFER CAR FOR KR-2 + 2 YEARS SPARE | G91: ARUN KUMAR | H91: 45965 | I91: 46275 | J91: 169540 | K91: 6755 | L91: 130 | M91: 170 | N91: 700 | O91: =SUM(K91:N91) -> 7755 | P91: 2609 | T91: =SUM(P91:S91) -> 2609 | U91: =K91-P91 -> 4146 | V91: =L91-Q91 -> 130 | W91: =M91-R91 -> 170 | X91: =N91-S91 -> 700 | Y91: =SUM(U91:X91) -> 5146 | Z91: =AS91 -> 4146 | AA91: =BH91 -> 70 | AB91: =BW91 -> 70 | AC91: =CL91 -> 600 | AD91: =SUM(Z91:AC91) -> 4886 | AE91: OTH | AF91: SERVICE | AG91: 1037 | AH91: 1037 | AI91: 1036 | AJ91: 1036 | AS91: =SUM(AG91:AR91) -> 4146 | AT91: OTH | AU91: SERVICE | AZ91: 70 | BH91: =SUM(AV91:BG91) -> 70 | BI91: OTH | BJ91: SERVICE | BO91: 70 | BW91: =SUM(BK91:BV91) -> 70 | BX91: OTH | BY91: SERVICE | CE91: 300 | CF91: 300 | CL91: =SUM(BZ91:CK91) -> 600 | CM91: =U91-Z91 -> 0 | CN91: =V91-AA91 -> 60 | CO91: =W91-AB91 -> 100 | CP91: =X91-AC91 -> 100
A92: 90 | B92: 24358 | C92: SO | D92: 1 | E92: MANDREL BEARING HOUSING | G92: ARUN KUMAR | H92: 45968 | I92: 46233 | J92: 8472 | K92: 1182 | L92: 170 | M92: 120 | N92: 80 | O92: =SUM(K92:N92) -> 1552 | P92: 823.78 | T92: =SUM(P92:S92) -> 823.78 | U92: =K92-P92 -> 358.22 | V92: =L92-Q92 -> 170 | W92: =M92-R92 -> 120 | X92: =N92-S92 -> 80 | Y92: =SUM(U92:X92) -> 728.22 | Z92: =AS92 -> 358 | AA92: =BH92 -> 170 | AB92: =BW92 -> 120 | AC92: =CL92 -> 80 | AD92: =SUM(Z92:AC92) -> 728 | AE92: OTH | AF92: SERVICE | AH92: 179 | AI92: 179 | AS92: =SUM(AG92:AR92) -> 358 | AT92: OTH | AU92: SERVICE | AY92: 170 | BH92: =SUM(AV92:BG92) -> 170 | BI92: OTH | BJ92: SERVICE | BM92: 120 | BW92: =SUM(BK92:BV92) -> 120 | BX92: OTH | BY92: SERVICE | CC92: 80 | CL92: =SUM(BZ92:CK92) -> 80 | CM92: =U92-Z92 -> 0.22 | CN92: =V92-AA92 -> 0 | CO92: =W92-AB92 -> 0 | CP92: =X92-AC92 -> 0
A93: 91 | B93: 24341 | C93: SO | D93: 2 | E93: REFURBISHMENT OF DISTRIBUTION CHUTE L-4M REFURBISHMENT OF HOT BLAST VALVE ND 1600 | F93: dispatched-10 | G93: SANGRAM SWAIN | H93: 45952 | I93: 46582 | J93: 29870 | K93: =108*2 -> 216 | L93: 12 | N93: 12 | O93: =SUM(K93:N93) -> 240 | P93: 13.3 | Q93: 19.3 | R93: 17.5 | S93: 492.5 | T93: =SUM(P93:S93) -> 542.6 | U93: =K93-P93 -> 202.7 | V93: =L93-Q93 -> -7.3 | W93: =M93-R93 -> -17.5 | X93: =N93-S93 -> -480.5 | Y93: =SUM(U93:X93) -> -302.6 | Z93: =AS93 -> 203 | AA93: =BH93 -> 0 | AB93: =BW93 -> 0 | AC93: =CL93 -> 0 | AD93: =SUM(Z93:AC93) -> 203 | AE93: OTH | AF93: SERVICE | AG93: 203 | AS93: =SUM(AG93:AR93) -> 203 | AT93: OTH | AU93: SERVICE | BH93: =SUM(AV93:BG93) -> 0 | BI93: OTH | BJ93: SERVICE | BW93: =SUM(BK93:BV93) -> 0 | BX93: OTH | BY93: SERVICE | CL93: =SUM(BZ93:CK93) -> 0 | CM93: =U93-Z93 -> -0.3 | CN93: =V93-AA93 -> -7.3 | CO93: =W93-AB93 -> -17.5 | CP93: =X93-AC93 -> -480.5
A94: 92 | B94: 24277 | C94: SO | D94: 2 | E94: REFURBISHMENT OF LMG DRIVE REFURBISHMENT OF DISTRIBUTION CHUTE L-4M | F94: DONE | G94: SANGRAM SWAIN | H94: 45971 | I94: 45971 | J94: 3430 | M94: 500 | N94: 400 | O94: =SUM(K94:N94) -> 900 | S94: 50 | T94: =SUM(P94:S94) -> 50 | U94: =K94-P94 -> 0 | V94: =L94-Q94 -> 0 | W94: =M94-R94 -> 500 | X94: =N94-S94 -> 350 | Y94: =SUM(U94:X94) -> 850 | Z94: =AS94 -> 0 | AA94: =BH94 -> 0 | AB94: =BW94 -> 500 | AC94: =CL94 -> 0 | AD94: =SUM(Z94:AC94) -> 500 | AE94: OTH | AF94: SERVICE | AS94: =SUM(AG94:AR94) -> 0 | AT94: OTH | AU94: SERVICE | BH94: =SUM(AV94:BG94) -> 0 | BI94: OTH | BJ94: SERVICE | BN94: 250 | BO94: 250 | BW94: =SUM(BK94:BV94) -> 500 | BX94: OTH | BY94: SERVICE | CL94: =SUM(BZ94:CK94) -> 0 | CM94: =U94-Z94 -> 0 | CN94: =V94-AA94 -> 0 | CO94: =W94-AB94 -> 0 | CP94: =X94-AC94 -> 350
A95: 93 | B95: S000885CAS.SCP.STG.HOS | C95: 26179 | D95: 1 | E95: SEGMENT 8 | G95: Kameshwaran | H95: 45972 | I95: 46356 | J95: 39000 | K95: 2605 | L95: 280 | M95: 160 | N95: 800 | O95: =SUM(K95:N95) -> 3845 | P95: 7 | T95: =SUM(P95:S95) -> 7 | U95: =K95-P95 -> 2598 | V95: =L95-Q95 -> 280 | W95: =M95-R95 -> 160 | X95: =N95-S95 -> 800 | Y95: =SUM(U95:X95) -> 3838 | Z95: =AS95 -> 2598 | AA95: =BH95 -> 280 | AB95: =BW95 -> 160 | AC95: =CL95 -> 800 | AD95: =SUM(Z95:AC95) -> 3838 | AE95: OTH | AF95: SERVICE | AH95: 862 | AI95: 868 | AJ95: 868 | AS95: =SUM(AG95:AR95) -> 2598 | AT95: OTH | AU95: SERVICE | AY95: 140 | AZ95: 140 | BH95: =SUM(AV95:BG95) -> 280 | BI95: OTH | BJ95: SERVICE | BN95: 60 | BO95: 100 | BW95: =SUM(BK95:BV95) -> 160 | BX95: OTH | BY95: SERVICE | CE95: 400 | CF95: 400 | CL95: =SUM(BZ95:CK95) -> 800 | CM95: =U95-Z95 -> 0 | CN95: =V95-AA95 -> 0 | CO95: =W95-AB95 -> 0 | CP95: =X95-AC95 -> 0
A96: 94 | B96: 22661 | C96: SO | D96: 2 | E96: DISTRIBUTION ROCKER NONE DRIVE ASSEMBLY DISTRIBUTOR ROCKER DRIVE CYLINDER SIDE | F96: NA | G96: SANGRAM SWAIN | H96: 45973 | I96: 46103 | J96: =607*2 -> 1214 | O96: =SUM(K96:N96) -> 0 | S96: 60 | T96: =SUM(P96:S96) -> 60 | U96: =K96-P96 -> 0 | V96: =L96-Q96 -> 0 | W96: =M96-R96 -> 0 | X96: =N96-S96 -> -60 | Y96: =SUM(U96:X96) -> -60 | Z96: =AS96 -> 0 | AA96: =BH96 -> 0 | AB96: =BW96 -> 0 | AC96: =CL96 -> 0 | AD96: =SUM(Z96:AC96) -> 0 | AE96: OTH | AF96: SERVICE | AS96: =SUM(AG96:AR96) -> 0 | AT96: OTH | AU96: SERVICE | BH96: =SUM(AV96:BG96) -> 0 | BI96: OTH | BJ96: SERVICE | BW96: =SUM(BK96:BV96) -> 0 | BX96: OTH | BY96: SERVICE | CL96: =SUM(BZ96:CK96) -> 0 | CM96: =U96-Z96 -> 0 | CN96: =V96-AA96 -> 0 | CO96: =W96-AB96 -> 0 | CP96: =X96-AC96 -> -60
A97: 95 | B97: 24971 | C97: SO | D97: 2 | E97: SPARE KIT FOR LSV DRIVE ND900 DISTRIBUTOR ROCKER DRIVE CYLINDER SIDE | F97: NA | G97: SANGRAM SWAIN | H97: 45982 | I97: 46302 | J97: 6490 | O97: =SUM(K97:N97) -> 0 | T97: =SUM(P97:S97) -> 0 | U97: =K97-P97 -> 0 | V97: =L97-Q97 -> 0 | W97: =M97-R97 -> 0 | X97: =N97-S97 -> 0 | Y97: =SUM(U97:X97) -> 0 | Z97: =AS97 -> 0 | AA97: =BH97 -> 0 | AB97: =BW97 -> 0 | AC97: =CL97 -> 0 | AD97: =SUM(Z97:AC97) -> 0 | AE97: OTH | AF97: SERVICE | AS97: =SUM(AG97:AR97) -> 0 | AT97: OTH | AU97: SERVICE | BH97: =SUM(AV97:BG97) -> 0 | BI97: OTH | BJ97: SERVICE | BW97: =SUM(BK97:BV97) -> 0 | BX97: OTH | BY97: SERVICE | CL97: =SUM(BZ97:CK97) -> 0 | CM97: =U97-Z97 -> 0 | CN97: =V97-AA97 -> 0 | CO97: =W97-AB97 -> 0 | CP97: =X97-AC97 -> 0
A98: 96 | B98: 23007 | C98: SO | D98: 2 | E98: FINAL MACHINNG OF TOP EDGER CHOCK FINAL MACHINNG OF BOTTOM EDGER CHOCK | F98: NA | G98: ARUN KUMAR | H98: 45978 | J98: 18230 | L98: 390 | O98: =SUM(K98:N98) -> 390 | T98: =SUM(P98:S98) -> 0 | U98: =K98-P98 -> 0 | V98: =L98-Q98 -> 390 | W98: =M98-R98 -> 0 | X98: =N98-S98 -> 0 | Y98: =SUM(U98:X98) -> 390 | Z98: =AS98 -> 0 | AA98: =BH98 -> 0 | AB98: =BW98 -> 0 | AC98: =CL98 -> 0 | AD98: =SUM(Z98:AC98) -> 0 | AE98: OTH | AF98: SERVICE | AS98: =SUM(AG98:AR98) -> 0 | AT98: OTH | AU98: SERVICE | BH98: =SUM(AV98:BG98) -> 0 | BI98: OTH | BJ98: SERVICE | BW98: =SUM(BK98:BV98) -> 0 | BX98: OTH | BY98: SERVICE | CL98: =SUM(BZ98:CK98) -> 0 | CM98: =U98-Z98 -> 0 | CN98: =V98-AA98 -> 390 | CO98: =W98-AB98 -> 0 | CP98: =X98-AC98 -> 0
A99: 97 | B99: 23097 | C99: SO | D99: 1 | E99: ROTATING FRAME ASSY OF GRIP TYPE TILTER | G99: RAVI RANJAN/AMAN | H99: 45981 | I99: 46179 | J99: 9362 | K99: 833 | L99: 98 | M99: 32 | N99: 200 | O99: =SUM(K99:N99) -> 1163 | P99: 264.24 | T99: =SUM(P99:S99) -> 264.24 | U99: =K99-P99 -> 568.76 | V99: =L99-Q99 -> 98 | W99: =M99-R99 -> 32 | X99: =N99-S99 -> 200 | Y99: =SUM(U99:X99) -> 898.76 | Z99: =AS99 -> 569 | AA99: =BH99 -> 90 | AB99: =BW99 -> 32 | AC99: =CL99 -> 160 | AD99: =SUM(Z99:AC99) -> 851 | AE99: OTH | AF99: SERVICE | AG99: 169 | AH99: 200 | AI99: 200 | AS99: =SUM(AG99:AR99) -> 569 | AT99: OTH | AU99: SERVICE | AV99: 45 | AW99: 45 | BH99: =SUM(AV99:BG99) -> 90 | BI99: OTH | BJ99: SERVICE | BK99: 32 | BW99: =SUM(BK99:BV99) -> 32 | BX99: OTH | BY99: SERVICE | CC99: 160 | CL99: =SUM(BZ99:CK99) -> 160 | CM99: =U99-Z99 -> -0.24 | CN99: =V99-AA99 -> 8 | CO99: =W99-AB99 -> 0 | CP99: =X99-AC99 -> 40
A100: 98 | B100: S000847CSP.TSC.STG.SSF S000847CSP.TSC.CAB.RUS | C100: 25240 | D100: 2 | E100: CARRIER FRAME & SEGMENT REMOVAL RAILS | F100: NA | G100: AMULYA JENA | H100: 45987 | I100: 46038 | J100: 42310 | K100: 2633.3168 | L100: 720 | N100: 350 | O100: =SUM(K100:N100) -> 3703.3168 | P100: 4629.6 | Q100: 79.2 | T100: =SUM(P100:S100) -> 4708.8 | U100: =K100-P100 -> -1996.2832 | V100: =L100-Q100 -> 640.8 | W100: =M100-R100 -> 0 | X100: =N100-S100 -> 350 | Y100: =SUM(U100:X100) -> -1005.4832 | Z100: =AS100 -> 0 | AA100: =BH100 -> 0 | AB100: =BW100 -> 0 | AC100: =CL100 -> 0 | AD100: =SUM(Z100:AC100) -> 0 | AE100: Group | AF100: DIRECT | AS100: =SUM(AG100:AR100) -> 0 | AT100: Group | AU100: DIRECT | BH100: =SUM(AV100:BG100) -> 0 | BI100: Group | BJ100: DIRECT | BW100: =SUM(BK100:BV100) -> 0 | BX100: Group | BY100: DIRECT | CL100: =SUM(BZ100:CK100) -> 0 | CM100: =U100-Z100 -> -1996.2832 | CN100: =V100-AA100 -> 640.8 | CO100: =W100-AB100 -> 0 | CP100: =X100-AC100 -> 350
...

Sheet SUMMARY-CP
A1: SUMMARY
A2: Sl No | B2: Planned | C2: Total Planned Hour | D2: 46174 | E2: 46204 | F2: 46235 | G2: 46266 | H2: 46297 | I2: 46327 | J2: 46357 | K2: 46388 | L2: 46419 | M2: 46447 | N2: 46478 | O2: 46508
A3: 1.1 | B3: OTHERS ORDERS | C3: =SUM(D3:O3) -> 190236.5 | D3: =GETPIVOTDATA("Sum of Jun/26",Welding!$A$3,"Order","OTH") -> 30360.25 | E3: =GETPIVOTDATA("Sum of Jul/26",Welding!$A$3,"Order","OTH") -> 28711.75 | F3: =GETPIVOTDATA("Sum of Aug/26",Welding!$A$3,"Order","OTH") -> 28053.25 | G3: =GETPIVOTDATA("Sum of Sep/26",Welding!$A$3,"Order","OTH") -> 24906.25 | H3: =GETPIVOTDATA("Sum of oct/26",Welding!$A$3,"Order","OTH") -> 20174 | I3: =GETPIVOTDATA("Sum of Nov/26",Welding!$A$3,"Order","OTH") -> 17836 | J3: =GETPIVOTDATA("Sum of Dec/26",Welding!$A$3,"Order","OTH") -> 12591 | K3: =GETPIVOTDATA("Sum of Jan/27",Welding!$A$3,"Order","OTH") -> 9104 | L3: =GETPIVOTDATA("Sum of Feb/27",Welding!$A$3,"Order","OTH") -> 6350 | M3: =GETPIVOTDATA("Sum of Mar/27",Welding!$A$3,"Order","OTH") -> 4050 | N3: =GETPIVOTDATA("Sum of Apr/27",Welding!$A$3,"Order","OTH") -> 4050 | O3: =GETPIVOTDATA("Sum of May/27",Welding!$A$3,"Order","OTH") -> 4050
A4: 1.2 | B4: GROUP COMPANY | C4: =SUM(D4:O4) -> 122796 | D4: =GETPIVOTDATA("Sum of Jun/26",Welding!$A$3,"Order","Group") -> 14938.5 | E4: =GETPIVOTDATA("Sum of Jul/26",Welding!$A$3,"Order","Group") -> 15175.5 | F4: =GETPIVOTDATA("Sum of Aug/26",Welding!$A$3,"Order","Group") -> 14938.5 | G4: =GETPIVOTDATA("Sum of Sep/26",Welding!$A$3,"Order","Group") -> 16142.5 | H4: =GETPIVOTDATA("Sum of Oct/26",Welding!$A$3,"Order","Group") -> 20441.5 | I4: =GETPIVOTDATA("Sum of Nov/26",Welding!$A$3,"Order","Group") -> 21440.5 | J4: =GETPIVOTDATA("Sum of Dec/26",Welding!$A$3,"Order","Group") -> 9884 | K4: =GETPIVOTDATA("Sum of Jan/27",Welding!$A$3,"Order","Group") -> 9385 | L4: =GETPIVOTDATA("Sum of Feb/27",Welding!$A$3,"Order","Group") -> 450 | M4: =GETPIVOTDATA("Sum of Mar/27",Welding!$A$3,"Order","Group") -> 0 | N4: =GETPIVOTDATA("Sum of Apr/27",Welding!$A$3,"Order","Group") -> 0 | O4: =GETPIVOTDATA("Sum of May/27",Welding!$A$3,"Order","Group") -> 0
A5: 1.3 | B5: CONTRACT MANUFACTURING | C5: =SUM(D5:O5) -> 33631 | D5: =GETPIVOTDATA("Sum of Jun/26",Welding!$A$3,"Order","Contract") -> 4532.5 | E5: =GETPIVOTDATA("Sum of Jul/26",Welding!$A$3,"Order","Contract") -> 5139.5 | F5: =GETPIVOTDATA("Sum of Aug/26",Welding!$A$3,"Order","Contract") -> 4322 | G5: =GETPIVOTDATA("Sum of Sep/26",Welding!$A$3,"Order","Contract") -> 3569 | H5: =GETPIVOTDATA("Sum of Oct/26",Welding!$A$3,"Order","Contract") -> 3568 | I5: =GETPIVOTDATA("Sum of Nov/26",Welding!$A$3,"Order","Contract") -> 2500 | J5: =GETPIVOTDATA("Sum of Dec/26",Welding!$A$3,"Order","Contract") -> 2500 | K5: =GETPIVOTDATA("Sum of Jan/27",Welding!$A$3,"Order","Contract") -> 2500 | L5: =GETPIVOTDATA("Sum of Feb/27",Welding!$A$3,"Order","Contract") -> 2500 | M5: =GETPIVOTDATA("Sum of Mar/27",Welding!$A$3,"Order","Contract") -> 2500 | N5: =GETPIVOTDATA("Sum of Apr/27",Welding!$A$3,"Order","Contract") -> 0 | O5: =GETPIVOTDATA("Sum of May/27",Welding!$A$3,"Order","Contract") -> 0
A6: 1 | B6: TOTAL WELDING | C6: =SUM(C3:C5) -> 346663.5 | D6: =SUM(D3:D5) -> 49831.25 | E6: =SUM(E3:E5) -> 49026.75 | F6: =SUM(F3:F5) -> 47313.75 | G6: =SUM(G3:G5) -> 44617.75 | H6: =SUM(H3:H5) -> 44183.5 | I6: =SUM(I3:I5) -> 41776.5 | J6: =SUM(J3:J5) -> 24975 | ... O6: =SUM(O3:O5) -> 4050
A8: 2.1 | B8: OTHERS ORDERS | C8: =SUM(D8:O8) -> 29134.5 | D8: =Machining!B23 -> 5035 | E8: =Machining!C23 -> 2557.5 | F8: =Machining!D23 -> 4425 | G8: =Machining!E23 -> 3619 | H8: =Machining!F23 -> 5507 | I8: =Machining!G23 -> 3565 | J8: =Machining!H23 -> 2304 | K8: =Machining!I23 -> 1215 | ... O8: =Machining!M23 -> 0
A9: 2.2 | B9: TS | C9: =SUM(D9:O9) -> 30000 | D9: =Machining!B24 -> 1850 | E9: =Machining!C24 -> 2600 | F9: =Machining!D24 -> 2600 | G9: =Machining!E24 -> 1950 | H9: =Machining!F24 -> 1550 | I9: =Machining!G24 -> 2000 | J9: =Machining!H24 -> 2500 | K9: =Machining!I24 -> 2500 | ... O9: =Machining!M24 -> 4282
A10: 2.3 | B10: GROUP COMPANY | C10: =SUM(D10:O10) -> 5587 | D10: =Machining!B22 -> 327 | E10: =Machining!C22 -> 327 | F10: =Machining!D22 -> 652 | G10: =Machining!E22 -> 711 | H10: =Machining!F22 -> 418 | I10: =Machining!G22 -> 800 | J10: =Machining!H22 -> 842 | K10: =Machining!I22 -> 785 | ... O10: =Machining!M22 -> 0
A11: 2.4 | B11: CONTRACT MANUFACTURING | C11: =SUM(D11:O11) -> 3863 | D11: =Machining!B21 -> 1263 | E11: =Machining!C21 -> 1308 | F11: =Machining!D21 -> 467 | G11: =Machining!E21 -> 260 | H11: =Machining!F21 -> 160 | I11: =Machining!G21 -> 185 | J11: =Machining!H21 -> 110 | K11: =Machining!I21 -> 110 | ... O11: =Machining!M21 -> 0
A12: 2 | B12: TOTAL MACHINING | C12: =SUM(C8:C11) -> 68584.5 | D12: =SUM(D8:D11) -> 8475 | E12: =SUM(E8:E11) -> 6792.5 | F12: =SUM(F8:F11) -> 8144 | G12: =SUM(G8:G11) -> 6540 | H12: =SUM(H8:H11) -> 7635 | I12: =SUM(I8:I11) -> 6550 | J12: =SUM(J8:J11) -> 5756 | ... O12: =SUM(O8:O11) -> 4282
A14: 3.1 | B14: OTHERS ORDERS | C14: =SUM(D14:O14) -> 25176 | D14: =GETPIVOTDATA("Sum of Jun-26",Assembly!$A$3,"Order","OTH") -> 3308 | E14: =GETPIVOTDATA("Sum of JuL-26",Assembly!$A$3,"Order","OTH") -> 2224 | F14: =GETPIVOTDATA("Sum of Aug-26",Assembly!$A$3,"Order","OTH") -> 1928 | G14: =GETPIVOTDATA("Sum of Sep-26",Assembly!$A$3,"Order","OTH") -> 1754 | H14: =GETPIVOTDATA("Sum of oct-26",Assembly!$A$3,"Order","OTH") -> 2302 | I14: =GETPIVOTDATA("Sum of Nov-26",Assembly!$A$3,"Order","OTH") -> 3775 | J14: =GETPIVOTDATA("Sum of Dec-26",Assembly!$A$3,"Order","OTH") -> 4265 | K14: =GETPIVOTDATA("Sum of Jan-27",Assembly!$A$3,"Order","OTH") -> 3090 | L14: =GETPIVOTDATA("Sum of Feb-27",Assembly!$A$3,"Order","OTH") -> 1470 | M14: =GETPIVOTDATA("Sum of Mar-27",Assembly!$A$3,"Order","OTH") -> 1060 | N14: =GETPIVOTDATA("Sum of Apr-27",Assembly!$A$3,"Order","OTH") -> 0 | O14: =GETPIVOTDATA("Sum of May-27",Assembly!$A$3,"Order","OTH") -> 0
A15: 3.2 | B15: GROUP COMPANY | C15: =SUM(D15:O15) -> 780 | D15: =GETPIVOTDATA("Sum of Jun-26",Assembly!$A$3,"Order","Group") -> 0 | E15: =GETPIVOTDATA("Sum of Jul-26",Assembly!$A$3,"Order","Group") -> 0 | F15: =GETPIVOTDATA("Sum of Aug-26",Assembly!$A$3,"Order","Group") -> 0 | G15: =GETPIVOTDATA("Sum of Sep-26",Assembly!$A$3,"Order","Group") -> 0 | H15: =GETPIVOTDATA("Sum of Oct-26",Assembly!$A$3,"Order","Group") -> 450 | I15: =GETPIVOTDATA("Sum of Nov-26",Assembly!$A$3,"Order","Group") -> 0 | J15: =GETPIVOTDATA("Sum of Dec-26",Assembly!$A$3,"Order","Group") -> 0 | K15: =GETPIVOTDATA("Sum of Jan-27",Assembly!$A$3,"Order","Group") -> 0 | L15: =GETPIVOTDATA("Sum of Feb-27",Assembly!$A$3,"Order","Group") -> 170 | M15: =GETPIVOTDATA("Sum of Mar-27",Assembly!$A$3,"Order","Group") -> 160 | N15: =GETPIVOTDATA("Sum of Apr-27",Assembly!$A$3,"Order","Group") -> 0 | O15: =GETPIVOTDATA("Sum of May-27",Assembly!$A$3,"Order","Group") -> 0
A16: 3.3 | B16: CONTRACT MANUFACTURING | C16: =SUM(D16:O16) -> 4099 | D16: =GETPIVOTDATA("Sum of Jun-26",Assembly!$A$3,"Order","Contract") -> 1180 | E16: =GETPIVOTDATA("Sum of Jul-26",Assembly!$A$3,"Order","Contract") -> 1069 | F16: =GETPIVOTDATA("Sum of Aug-26",Assembly!$A$3,"Order","Contract") -> 0 | G16: =GETPIVOTDATA("Sum of Sep-26",Assembly!$A$3,"Order","Contract") -> 50 | H16: =GETPIVOTDATA("Sum of Oct-26",Assembly!$A$3,"Order","Contract") -> 300 | I16: =GETPIVOTDATA("Sum of Nov-26",Assembly!$A$3,"Order","Contract") -> 300 | J16: =GETPIVOTDATA("Sum of Dec-26",Assembly!$A$3,"Order","Contract") -> 300 | K16: =GETPIVOTDATA("Sum of Jan-27",Assembly!$A$3,"Order","Contract") -> 300 | L16: =GETPIVOTDATA("Sum of Feb-27",Assembly!$A$3,"Order","Contract") -> 300 | M16: =GETPIVOTDATA("Sum of Mar-27",Assembly!$A$3,"Order","Contract") -> 300 | N16: =GETPIVOTDATA("Sum of Apr-27",Assembly!$A$3,"Order","Contract") -> 0 | O16: =GETPIVOTDATA("Sum of May-27",Assembly!$A$3,"Order","Contract") -> 0
A17: 3.4 | B17: ASSEMBLY-Hydraulic Test Stand | C17: 60 | D17: 10 | E17: 10 | F17: 10 | G17: 10 | H17: 10 | I17: 10 | J17: 0 | K17: 0 | L17: 0 | M17: 0 | N17: 0 | O17: 0
A18: 3.5 | B18: TS | C18: =SUM(D18:O18) -> 1800 | D18: =GETPIVOTDATA("Sum of Jun-26",Assembly!$A$3,"Order","TS") -> 30 | E18: =GETPIVOTDATA("Sum of Jul-26",Assembly!$A$3,"Order","TS") -> 40 | F18: =GETPIVOTDATA("Sum of Aug-26",Assembly!$A$3,"Order","TS") -> 250 | G18: =GETPIVOTDATA("Sum of Sep-26",Assembly!$A$3,"Order","TS") -> 300 | H18: =GETPIVOTDATA("Sum of Oct-26",Assembly!$A$3,"Order","TS") -> 280 | I18: =GETPIVOTDATA("Sum of Nov-26",Assembly!$A$3,"Order","TS") -> 200 | J18: =GETPIVOTDATA("Sum of Dec-26",Assembly!$A$3,"Order","TS") -> 200 | K18: =GETPIVOTDATA("Sum of Jan-27",Assembly!$A$3,"Order","TS") -> 100 | L18: =GETPIVOTDATA("Sum of Feb-27",Assembly!$A$3,"Order","TS") -> 100 | M18: =GETPIVOTDATA("Sum of Mar-27",Assembly!$A$3,"Order","TS") -> 100 | N18: =GETPIVOTDATA("Sum of Apr-27",Assembly!$A$3,"Order","TS") -> 100 | O18: =GETPIVOTDATA("Sum of May-27",Assembly!$A$3,"Order","TS") -> 100
A19: 3.6 | B19: IRON MAKING | C19: =SUM(D19:O19) -> 13820 | D19: =GETPIVOTDATA("Sum of Jun-26",Assembly!$A$3,"Order","IRON MAKING") -> 900 | E19: =GETPIVOTDATA("Sum of Jul-26",Assembly!$A$3,"Order","IRON MAKING") -> 2200 | F19: =GETPIVOTDATA("Sum of Aug-26",Assembly!$A$3,"Order","IRON MAKING") -> 3350 | G19: =GETPIVOTDATA("Sum of Sep-26",Assembly!$A$3,"Order","IRON MAKING") -> 3500 | H19: =GETPIVOTDATA("Sum of Oct-26",Assembly!$A$3,"Order","IRON MAKING") -> 2200 | I19: =GETPIVOTDATA("Sum of Nov-26",Assembly!$A$3,"Order","IRON MAKING") -> 500 | J19: =GETPIVOTDATA("Sum of Dec-26",Assembly!$A$3,"Order","IRON MAKING") -> 0 | K19: =GETPIVOTDATA("Sum of Jan-27",Assembly!$A$3,"Order","IRON MAKING") -> 670 | L19: =GETPIVOTDATA("Sum of Feb-27",Assembly!$A$3,"Order","IRON MAKING") -> 500 | M19: =GETPIVOTDATA("Sum of Mar-27",Assembly!$A$3,"Order","IRON MAKING") -> 0 | N19: =GETPIVOTDATA("Sum of Apr-27",Assembly!$A$3,"Order","IRON MAKING") -> 0 | O19: =GETPIVOTDATA("Sum of May-27",Assembly!$A$3,"Order","IRON MAKING") -> 0
A20: 3 | B20: TOTAL ASSEMBLY | C20: =SUM(C14:C16,C17:C19) -> 45735 | D20: =SUM(D14:D16,D17:D19) -> 5428 | E20: =SUM(E14:E16,E17:E19) -> 5543 | F20: =SUM(F14:F16,F17:F19) -> 5538 | G20: =SUM(G14:G16,G17:G19) -> 5614 | H20: =SUM(H14:H16,H17:H19) -> 5542 | I20: =SUM(I14:I16,I17:I19) -> 4785 | J20: =SUM(J14:J16,J17:J19) -> 4765 | ... O20: =SUM(O14:O16,O17:O19) -> 100
A22: 4 | B22: SERVICE-ROLL REFURBISHMENT | C22: 15276 | D22: 1800 | E22: 1600 | F22: 1500 | G22: 1400 | H22: 1300 | I22: 1200 | J22: 1100 | K22: 1100 | L22: 1100 | M22: 1176 | N22: 1000 | O22: 1000
A23: 5 | B23: SERVICE-PLATING | C23: 10260 | D23: 1300 | E23: 1300 | F23: 1200 | G23: 1000 | H23: 1000 | I23: 890 | J23: 800 | K23: 700 | L23: 600 | M23: 500 | N23: 500 | O23: 470
B25: TOTAL MANUFACTRING | C25: =C6+C12+C20+C22+C23 -> 486519 | D25: =D6+D12+D20+D22+D23 -> 66834.25 | E25: =E6+E12+E20+E22+E23 -> 64262.25 | F25: =F6+F12+F20+F22+F23 -> 63695.75 | G25: =G6+G12+G20+G22+G23 -> 59171.75 | H25: =H6+H12+H20+H22+H23 -> 59660.5 | I25: =I6+I12+I20+I22+I23 -> 55201.5 | J25: =J6+J12+J20+J22+J23 -> 37396 | ... O25: =O6+O12+O20+O22+O23 -> 9902
A27: Sl No | B27: Available Capacity (NPK) | C27: Total Available Hour | D27: 46174 | E27: 46204 | F27: 46235 | G27: 46266 | H27: 46296 | I27: 46327 | J27: 46357 | K27: 46388 | L27: 46419 | M27: 46447 | N27: 46478 | O27: 46508
A28: 1.1 | B28: KHURDA-WELDING-SMI | C28: =SUM(D28:O28) -> 19367.917 | D28: =NPK!I2 -> 1591.8836 | E28: =NPK!J2 -> 1644.9464 | F28: =NPK!K2 -> 1644.9464 | G28: =NPK!L2 -> 1591.8836 | H28: =NPK!M2 -> 1644.9464 | I28: =NPK!N2 -> 1591.8836 | J28: =NPK!O2 -> 1644.9464 | K28: =NPK!D2 -> 1644.9464 | L28: =NPK!E2 -> 1485.758 | M28: =NPK!F2 -> 1644.9464 | N28: =NPK!G2 -> 1591.8836 | O28: =NPK!H2 -> 1644.9464
A29: 1.2 | B29: KHURDA-WELDING-LS | C29: =SUM(D29:O29) -> 261466.88 | D29: =NPK!I3 -> 21490.428 | E29: =NPK!J3 -> 22206.776 | F29: =NPK!K3 -> 22206.776 | G29: =NPK!L3 -> 21490.428 | H29: =NPK!M3 -> 22206.776 | I29: =NPK!N3 -> 21490.428 | J29: =NPK!O3 -> 22206.776 | K29: =NPK!D3 -> 22206.776 | L29: =NPK!E3 -> 20057.733 | M29: =NPK!F3 -> 22206.776 | N29: =NPK!G3 -> 21490.428 | O29: =NPK!H3 -> 22206.776
A30: 1.3 | B30: KHURDA-WELDING-JC | C30: =SUM(D30:O30) -> 180767.22 | D30: =NPK!I4 -> 14857.58 | E30: =NPK!J4 -> 15352.833 | F30: =NPK!K4 -> 15352.833 | G30: =NPK!L4 -> 14857.58 | H30: =NPK!M4 -> 15352.833 | I30: =NPK!N4 -> 14857.58 | J30: =NPK!O4 -> 15352.833 | K30: =NPK!D4 -> 15352.833 | L30: =NPK!E4 -> 13867.075 | M30: =NPK!F4 -> 15352.833 | N30: =NPK!G4 -> 14857.58 | O30: =NPK!H4 -> 15352.833
A31: 1.1-1.3 | B31: KHURDA-WELDING (SMI+LS+JC) | C31: =C28+C29+C30 -> 461602.02 | D31: =D28+D29+D30 -> 37939.892 | E31: =E28+E29+E30 -> 39204.555 | F31: =F28+F29+F30 -> 39204.555 | G31: =G28+G29+G30 -> 37939.892 | H31: =H28+H29+H30 -> 39204.555 | I31: =I28+I29+I30 -> 37939.892 | J31: =J28+J29+J30 -> 39204.555 | ... O31: =O28+O29+O30 -> 39204.555
A32: 1.4 | B32: MANCHESWAR-WELDING-JC | C32: =SUM(D32:O32) -> 140252.1 | D32: =NPK!I6 -> 11527.57 | E32: =NPK!J6 -> 11911.822 | F32: =NPK!K6 -> 11911.822 | G32: =NPK!L6 -> 11527.57 | H32: =NPK!M6 -> 11911.822 | I32: =NPK!N6 -> 11527.57 | J32: =NPK!O6 -> 11911.822 | K32: =NPK!D6 -> 11911.822 | L32: =NPK!E6 -> 10759.065 | M32: =NPK!F6 -> 11911.822 | N32: =NPK!G6 -> 11527.57 | O32: =NPK!H6 -> 11911.822
A33: 1.5 | B33: MANCHESWAR-WELDING-LS | C33: =SUM(D33:O33) -> 6233.4265 | D33: =NPK!I7 -> 512.33643 | E33: =NPK!J7 -> 529.41431 | F33: =NPK!K7 -> 529.41431 | G33: =NPK!L7 -> 512.33643 | H33: =NPK!M7 -> 529.41431 | I33: =NPK!N7 -> 512.33643 | J33: =NPK!O7 -> 529.41431 | K33: =NPK!D7 -> 529.41431 | L33: =NPK!E7 -> 478.18067 | M33: =NPK!F7 -> 529.41431 | N33: =NPK!G7 -> 512.33643 | O33: =NPK!H7 -> 529.41431
A34: 1.6 | B34: MANCHESWAR-WELDING-SMI | C34: =SUM(D34:O34) -> 1558.3566 | D34: =NPK!I8 -> 128.08411 | E34: =NPK!J8 -> 132.35358 | F34: =NPK!K8 -> 132.35358 | G34: =NPK!L8 -> 128.08411 | H34: =NPK!M8 -> 132.35358 | I34: =NPK!N8 -> 128.08411 | J34: =NPK!O8 -> 132.35358 | K34: =NPK!D8 -> 132.35358 | L34: =NPK!E8 -> 119.54517 | M34: =NPK!F8 -> 132.35358 | N34: =NPK!G8 -> 128.08411 | O34: =NPK!H8 -> 132.35358
A35: 1.7 | B35: MANCHESWAR-WELDING (SMI+LS+JC) | C35: =SUM(C32:C34) -> 148043.88 | D35: =SUM(D32:D34) -> 12167.99 | E35: =SUM(E32:E34) -> 12573.59 | F35: =SUM(F32:F34) -> 12573.59 | G35: =SUM(G32:G34) -> 12167.99 | H35: =SUM(H32:H34) -> 12573.59 | I35: =SUM(I32:I34) -> 12167.99 | J35: =SUM(J32:J34) -> 12573.59 | ... O35: =SUM(O32:O34) -> 12573.59
A36: 1 | B36: K & M - WELDING (TOTAL) | C36: =C31+C32+C34+C33 -> 609645.9 | D36: =D31+D32+D34+D33 -> 50107.882 | E36: =E31+E32+E34+E33 -> 51778.145 | F36: =F31+F32+F34+F33 -> 51778.145 | G36: =G31+G32+G34+G33 -> 50107.882 | H36: =H31+H32+H34+H33 -> 51778.145 | I36: =I31+I32+I34+I33 -> 50107.882 | J36: =J31+J32+J34+J33 -> 51778.145 | ... O36: =O31+O32+O34+O33 -> 51778.145
A38: 2 | B38: TOTAL MACHINE SHOP | C38: =SUM(D38:O38) -> 106306.03 | D38: =NPK!I11 -> 8737.4818 | E38: =NPK!J11 -> 9028.7312 | F38: =NPK!K11 -> 9028.7312 | G38: =NPK!L11 -> 8737.4818 | H38: =NPK!M11 -> 9028.7312 | I38: =NPK!N11 -> 8737.4818 | J38: =NPK!O11 -> 9028.7312 | K38: =NPK!D11 -> 9028.7312 | L38: =NPK!E11 -> 8154.983 | M38: =NPK!F11 -> 9028.7312 | N38: =NPK!G11 -> 8737.4818 | O38: =NPK!H11 -> 9028.7312
A40: 3.1 | B40: ASSEMBLY-SMI | C40: =SUM(D40:O40) -> 16496.625 | D40: =NPK!I13 -> 1355.887 | E40: =NPK!J13 -> 1401.0832 | F40: =NPK!K13 -> 1401.0832 | G40: =NPK!L13 -> 1355.887 | H40: =NPK!M13 -> 1401.0832 | I40: =NPK!N13 -> 1355.887 | J40: =NPK!O13 -> 1401.0832 | K40: =NPK!D13 -> 1401.0832 | L40: =NPK!E13 -> 1265.4945 | M40: =NPK!F13 -> 1401.0832 | N40: =NPK!G13 -> 1355.887 | O40: =NPK!H13 -> 1401.0832
A41: 3.2 | B41: ASSEMBLY-LS | C41: =SUM(D41:O41) -> 32993.25 | D41: =NPK!I14 -> 2711.774 | E41: =NPK!J14 -> 2802.1664 | F41: =NPK!K14 -> 2802.1664 | G41: =NPK!L14 -> 2711.774 | H41: =NPK!M14 -> 2802.1664 | I41: =NPK!N14 -> 2711.774 | J41: =NPK!O14 -> 2802.1664 | K41: =NPK!D14 -> 2802.1664 | L41: =NPK!E14 -> 2530.989 | M41: =NPK!F14 -> 2802.1664 | N41: =NPK!G14 -> 2711.774 | O41: =NPK!H14 -> 2802.1664
A42: 3.3 | B42: ASSEMBLY-JS | C42: =SUM(D42:O42) -> 16496.625 | D42: =NPK!I15 -> 1355.887 | E42: =NPK!J15 -> 1401.0832 | F42: =NPK!K15 -> 1401.0832 | G42: =NPK!L15 -> 1355.887 | H42: =NPK!M15 -> 1401.0832 | I42: =NPK!N15 -> 1355.887 | J42: =NPK!O15 -> 1401.0832 | K42: =NPK!D15 -> 1401.0832 | L42: =NPK!E15 -> 1265.4945 | M42: =NPK!F15 -> 1401.0832 | N42: =NPK!G15 -> 1355.887 | O42: =NPK!H15 -> 1401.0832
A43: 3 | B43: ASSEMBLY-MFG | C43: =C40+C41+C42 -> 65986.5 | D43: =D40+D41+D42 -> 5423.5479 | E43: =E40+E41+E42 -> 5604.3329 | F43: =F40+F41+F42 -> 5604.3329 | G43: =G40+G41+G42 -> 5423.5479 | H43: =H40+H41+H42 -> 5604.3329 | I43: =I40+I41+I42 -> 5423.5479 | J43: =J40+J41+J42 -> 5604.3329 | ... O43: =O40+O41+O42 -> 5604.3329
A45: 4 | B45: ROLL REFURBISHMENT | C45: =SUM(D45:O45) -> 27553.475 | D45: =NPK!I18 -> 2264.6692 | E45: =NPK!J18 -> 2340.1581 | F45: =NPK!K18 -> 2340.1581 | G45: =NPK!L18 -> 2264.6692 | H45: =NPK!M18 -> 2340.1581 | I45: =NPK!N18 -> 2264.6692 | J45: =NPK!O18 -> 2340.1581 | K45: =NPK!D18 -> 2340.1581 | L45: =NPK!E18 -> 2113.6912 | M45: =NPK!F18 -> 2340.1581 | N45: =NPK!G18 -> 2264.6692 | O45: =NPK!H18 -> 2340.1581
A46: 5 | B46: PLATING | C46: =SUM(D46:O46) -> 29700.06 | D46: =NPK!I19 -> 2441.1008 | E46: =NPK!J19 -> 2522.4708 | F46: =NPK!K19 -> 2522.4708 | G46: =NPK!L19 -> 2441.1008 | H46: =NPK!M19 -> 2522.4708 | I46: =NPK!N19 -> 2441.1008 | J46: =NPK!O19 -> 2522.4708 | K46: =NPK!D19 -> 2522.4708 | L46: =NPK!E19 -> 2278.3608 | M46: =NPK!F19 -> 2522.4708 | N46: =NPK!G19 -> 2441.1008 | O46: =NPK!H19 -> 2522.4708
B47: TOTAL MANUFACTRING | C47: =C36+C38+C43+C45+C46 -> 839191.96 | D47: =D36+D38+D43+D45+D46 -> 68974.682 | E47: =E36+E38+E43+E45+E46 -> 71273.838 | F47: =F36+F38+F43+F45+F46 -> 71273.838 | G47: =G36+G38+G43+G45+G46 -> 68974.682 | H47: =H36+H38+H43+H45+H46 -> 71273.838 | I47: =I36+I38+I43+I45+I46 -> 68974.682 | J47: =J36+J38+J43+J45+J46 -> 71273.838 | ... O47: =O36+O38+O43+O45+O46 -> 71273.838
D48: =D25/D47 -> 0.96896786 | E48: =E25/E47 -> 0.90162466 | F48: =F25/F47 -> 0.89367644 | G48: =G25/G47 -> 0.85787637 | H48: =H25/H47 -> 0.8370603 | I48: =I25/I47 -> 0.8003154 | J48: =J25/J47 -> 0.5246806 | K48: =K25/K47 -> 0.44278519 | ... O48: =O25/O47 -> 0.13892896
A50: TOTAL GROUP COMPANY HOURS | C50: =SUM(D50:O50) -> 129163 | D50: =D4+D10+D15 -> 15265.5 | E50: =E4+E10+E15 -> 15502.5 | F50: =F4+F10+F15 -> 15590.5 | G50: =G4+G10+G15 -> 16853.5 | H50: =H4+H10+H15 -> 21309.5 | I50: =I4+I10+I15 -> 22240.5 | J50: =J4+J10+J15 -> 10726 | K50: =K4+K10+K15 -> 10170 | ... O50: =O4+O10+O15 -> 0
D51: =D50/1000 -> 15.2655 | E51: =E50/1000 -> 15.5025 | F51: =F50/1000 -> 15.5905 | G51: =G50/1000 -> 16.8535 | H51: =H50/1000 -> 21.3095 | I51: =I50/1000 -> 22.2405 | J51: =J50/1000 -> 10.726 | K51: =K50/1000 -> 10.17 | ... O51: =O50/1000 -> 0
A52: TOTAL CONTRACT MANUFACTURING HOURS | C52: =SUM(D52:O52) -> 41593 | D52: =D5+D11+D16 -> 6975.5 | E52: =E5+E11+E16 -> 7516.5 | F52: =F5+F11+F16 -> 4789 | G52: =G5+G11+G16 -> 3879 | H52: =H5+H11+H16 -> 4028 | I52: =I5+I11+I16 -> 2985 | J52: =J5+J11+J16 -> 2910 | K52: =K5+K11+K16 -> 2910 | ... O52: =O5+O11+O16 -> 0
D53: =D52/1000 -> 6.9755 | E53: =E52/1000 -> 7.5165 | F53: =F52/1000 -> 4.789 | G53: =G52/1000 -> 3.879 | H53: =H52/1000 -> 4.028 | I53: =I52/1000 -> 2.985 | J53: =J52/1000 -> 2.91 | K53: =K52/1000 -> 2.91 | ... O53: =O52/1000 -> 0
C54: Total | D54: =D51+D53 -> 22.241 | E54: =E51+E53 -> 23.019 | F54: =F51+F53 -> 20.3795 | G54: =G51+G53 -> 20.7325 | H54: =H51+H53 -> 25.3375 | I54: =I51+I53 -> 25.2255 | J54: =J51+J53 -> 13.636 | K54: =K51+K53 -> 13.08 | ... O54: =O51+O53 -> 0

Sheet SCB ACTUAL
A1: Planned | B1: 46028 | C1: 46060 | D1: 46092 | E1: 46124 | F1: 46156 | G1: 46188 | H1: 46220 | I1: 46252 | J1: 46284 | K1: 46316 | L1: 46348 | M1: 46380 | N1: Planned Hours Apr'26-Dec'26
A2: WELDING | B2: 51351.295 | C2: 47293 | D2: 51849 | E2: ='[62]SUMMARY-MFG'!D6 -> 52535 | F2: ='[62]SUMMARY-MFG'!E6 -> 52485 | G2: ='SUMMARY-CP'!D6 -> 49831.25 | H2: ='SUMMARY-CP'!E6 -> 49026.75 | I2: ='SUMMARY-CP'!F6 -> 47313.75 | J2: ='SUMMARY-CP'!G6 -> 44617.75 | K2: ='SUMMARY-CP'!H6 -> 44183.5 | L2: ='SUMMARY-CP'!I6 -> 41776.5 | M2: ='SUMMARY-CP'!J6 -> 24975 | N2: =SUM(G2:M2) -> 301724.5
A3: MACHINING | B3: 7519.22 | C3: 8153 | D3: 9028 | E3: ='[62]SUMMARY-MFG'!D12 -> 8947 | F3: ='[62]SUMMARY-MFG'!E12 -> 9129 | G3: ='SUMMARY-CP'!D12 -> 8475 | H3: ='SUMMARY-CP'!E12 -> 6792.5 | I3: ='SUMMARY-CP'!F12 -> 8144 | J3: ='SUMMARY-CP'!G12 -> 6540 | K3: ='SUMMARY-CP'!H12 -> 7635 | L3: ='SUMMARY-CP'!I12 -> 6550 | M3: ='SUMMARY-CP'!J12 -> 5756 | N3: =SUM(G3:M3) -> 49892.5
A4: ASSEMBLY | B4: 4945.01 | C4: 5159 | D4: 5700 | E4: ='[62]SUMMARY-MFG'!D20 -> 5686 | F4: ='[62]SUMMARY-MFG'!E20 -> 5630 | G4: ='SUMMARY-CP'!D20 -> 5428 | H4: ='SUMMARY-CP'!E20 -> 5543 | I4: ='SUMMARY-CP'!F20 -> 5538 | J4: ='SUMMARY-CP'!G20 -> 5614 | K4: ='SUMMARY-CP'!H20 -> 5542 | L4: ='SUMMARY-CP'!I20 -> 4785 | M4: ='SUMMARY-CP'!J20 -> 4765 | N4: =SUM(G4:M4) -> 37215
A5: ROLL REFURBISHMENT | B5: 2765.02 | C5: 2200 | D5: 1600 | E5: ='[62]SUMMARY-MFG'!D22 -> 1600 | F5: ='[62]SUMMARY-MFG'!E22 -> 1500 | G5: ='SUMMARY-CP'!D22 -> 1800 | H5: ='SUMMARY-CP'!E22 -> 1600 | I5: ='SUMMARY-CP'!F22 -> 1500 | J5: ='SUMMARY-CP'!G22 -> 1400 | K5: ='SUMMARY-CP'!H22 -> 1300 | L5: ='SUMMARY-CP'!I22 -> 1200 | M5: ='SUMMARY-CP'!J22 -> 1100 | N5: =SUM(G5:M5) -> 9900
A6: PLATING | B6: 4021 | C6: 2522 | D6: 2200 | E6: ='[62]SUMMARY-MFG'!D23 -> 1300 | F6: ='[62]SUMMARY-MFG'!E23 -> 1300 | G6: ='SUMMARY-CP'!D23 -> 1300 | H6: ='SUMMARY-CP'!E23 -> 1300 | I6: ='SUMMARY-CP'!F23 -> 1200 | J6: ='SUMMARY-CP'!G23 -> 1000 | K6: ='SUMMARY-CP'!H23 -> 1000 | L6: ='SUMMARY-CP'!I23 -> 890 | M6: ='SUMMARY-CP'!J23 -> 800 | N6: =SUM(G6:M6) -> 7490
A7: TOTAL | B7: =SUM(B2:B6) -> 70601.545 | C7: =SUM(C2:C6) -> 65327 | D7: =SUM(D2:D6) -> 70377 | E7: =SUM(E2:E6) -> 70068 | F7: =SUM(F2:F6) -> 70044 | G7: =SUM(G2:G6) -> 66834.25 | H7: =SUM(H2:H6) -> 64262.25 | I7: =SUM(I2:I6) -> 63695.75 | ... M7: =SUM(M2:M6) -> 37396 | N7: =SUM(G7:M7) -> 406222
A9: NPK Capacity | B9: 46028 | C9: 46060 | D9: 46092 | E9: 46124 | F9: 46156 | G9: 46188 | H9: 46220 | I9: 46252 | J9: 46284 | K9: 46316 | L9: 46348 | M9: 46380 | N9: Planned Hours Apr'26-Dec'26
A10: WELDING | B10: =[62]NPK!D9 -> 51778.145 | C10: 46767 | D10: 51778.145 | E10: ='[62]SUMMARY-MFG'!D36 -> 50107.882 | F10: ='[62]SUMMARY-MFG'!E36 -> 51778.145 | G10: ='SUMMARY-CP'!D36 -> 50107.882 | H10: ='SUMMARY-CP'!E36 -> 51778.145 | I10: ='SUMMARY-CP'!F36 -> 51778.145 | J10: ='SUMMARY-CP'!G36 -> 50107.882 | K10: ='SUMMARY-CP'!H36 -> 51778.145 | L10: ='SUMMARY-CP'!I36 -> 50107.882 | M10: ='SUMMARY-CP'!J36 -> 51778.145 | N10: =SUM(G10:M10) -> 357436.23
A11: MACHINING | B11: =[62]NPK!D11 -> 9028.7312 | C11: 8155 | D11: 9028.7312 | E11: ='[62]SUMMARY-MFG'!D38 -> 8737.4818 | F11: ='[62]SUMMARY-MFG'!E38 -> 9028.7312 | G11: ='SUMMARY-CP'!D38 -> 8737.4818 | H11: ='SUMMARY-CP'!E38 -> 9028.7312 | I11: ='SUMMARY-CP'!F38 -> 9028.7312 | J11: ='SUMMARY-CP'!G38 -> 8737.4818 | K11: ='SUMMARY-CP'!H38 -> 9028.7312 | L11: ='SUMMARY-CP'!I38 -> 8737.4818 | M11: ='SUMMARY-CP'!J38 -> 9028.7312 | N11: =SUM(G11:M11) -> 62327.37
A12: ASSEMBLY | B12: =[62]NPK!D16 -> 5604.3329 | C12: 5062 | D12: 5604.3329 | E12: ='[62]SUMMARY-MFG'!D43 -> 5423.5479 | F12: ='[62]SUMMARY-MFG'!E43 -> 5604.3329 | G12: ='SUMMARY-CP'!D43 -> 5423.5479 | H12: ='SUMMARY-CP'!E43 -> 5604.3329 | I12: ='SUMMARY-CP'!F43 -> 5604.3329 | J12: ='SUMMARY-CP'!G43 -> 5423.5479 | K12: ='SUMMARY-CP'!H43 -> 5604.3329 | L12: ='SUMMARY-CP'!I43 -> 5423.5479 | M12: ='SUMMARY-CP'!J43 -> 5604.3329 | N12: =SUM(G12:M12) -> 38687.975
A13: ROLL REFURBISHMENT | B13: =[62]NPK!D18 -> 2340.1581 | C13: 2340 | D13: 2340.1581 | E13: ='[62]SUMMARY-MFG'!D45 -> 2340.1581 | F13: ='[62]SUMMARY-MFG'!E45 -> 2264.6692 | G13: ='SUMMARY-CP'!D45 -> 2264.6692 | H13: ='SUMMARY-CP'!E45 -> 2340.1581 | I13: ='SUMMARY-CP'!F45 -> 2340.1581 | J13: ='SUMMARY-CP'!G45 -> 2264.6692 | K13: ='SUMMARY-CP'!H45 -> 2340.1581 | L13: ='SUMMARY-CP'!I45 -> 2264.6692 | M13: ='SUMMARY-CP'!J45 -> 2340.1581 | N13: =SUM(G13:M13) -> 16154.64
A14: PLATING | B14: =[62]NPK!D19 -> 2522.4708 | C14: 2522 | D14: 2522.4708 | E14: ='[62]SUMMARY-MFG'!D46 -> 2522.4708 | F14: ='[62]SUMMARY-MFG'!E46 -> 2441.1008 | G14: ='SUMMARY-CP'!D46 -> 2441.1008 | H14: ='SUMMARY-CP'!E46 -> 2522.4708 | I14: ='SUMMARY-CP'!F46 -> 2522.4708 | J14: ='SUMMARY-CP'!G46 -> 2441.1008 | K14: ='SUMMARY-CP'!H46 -> 2522.4708 | L14: ='SUMMARY-CP'!I46 -> 2441.1008 | M14: ='SUMMARY-CP'!J46 -> 2522.4708 | N14: =SUM(G14:M14) -> 17413.186
A15: TOTAL | B15: =SUM(B10:B14) -> 71273.838 | C15: =SUM(C10:C14) -> 64846 | D15: =SUM(D10:D14) -> 71273.838 | E15: =SUM(E10:E14) -> 69131.541 | F15: =SUM(F10:F14) -> 71116.979 | G15: =SUM(G10:G14) -> 68974.682 | H15: =SUM(H10:H14) -> 71273.838 | I15: =SUM(I10:I14) -> 71273.838 | ... M15: =SUM(M10:M14) -> 71273.838 | N15: =SUM(G15:M15) -> 492019.4
A17: Planned Hours | B17: 46028 | C17: 46060 | D17: 46092 | E17: 46124 | F17: 46156 | G17: 46188 | H17: 46220 | I17: 46252 | J17: 46284 | K17: 46316 | L17: 46348 | M17: 46380 | N17: Planned Hours Apr'26-Dec'26
A18: WELDING | B18: =B2/1000 -> 51.351295 | C18: =C2/1000 -> 47.293 | D18: =D2/1000 -> 51.849 | E18: =E2/1000 -> 52.535 | F18: =F2/1000 -> 52.485 | G18: =G2/1000 -> 49.83125 | H18: =H2/1000 -> 49.02675 | I18: =I2/1000 -> 47.31375 | ... M18: =M2/1000 -> 24.975 | N18: =SUM(G18:M18) -> 301.7245
A19: MACHINING | B19: =B3/1000 -> 7.51922 | C19: =C3/1000 -> 8.153 | D19: =D3/1000 -> 9.028 | E19: =E3/1000 -> 8.947 | F19: =F3/1000 -> 9.129 | G19: =G3/1000 -> 8.475 | H19: =H3/1000 -> 6.7925 | I19: =I3/1000 -> 8.144 | ... M19: =M3/1000 -> 5.756 | N19: =SUM(G19:M19) -> 49.8925
A20: ASSEMBLY | B20: =B4/1000 -> 4.94501 | C20: =C4/1000 -> 5.159 | D20: =D4/1000 -> 5.7 | E20: =E4/1000 -> 5.686 | F20: =F4/1000 -> 5.63 | G20: =G4/1000 -> 5.428 | H20: =H4/1000 -> 5.543 | I20: =I4/1000 -> 5.538 | ... M20: =M4/1000 -> 4.765 | N20: =SUM(G20:M20) -> 37.215
A21: ROLL REFURBISHMENT | B21: =B5/1000 -> 2.76502 | C21: =C5/1000 -> 2.2 | D21: =D5/1000 -> 1.6 | E21: =E5/1000 -> 1.6 | F21: =F5/1000 -> 1.5 | G21: =G5/1000 -> 1.8 | H21: =H5/1000 -> 1.6 | I21: =I5/1000 -> 1.5 | ... M21: =M5/1000 -> 1.1 | N21: =SUM(G21:M21) -> 9.9
A22: PLATING | B22: =B6/1000 -> 4.021 | C22: =C6/1000 -> 2.522 | D22: =D6/1000 -> 2.2 | E22: =E6/1000 -> 1.3 | F22: =F6/1000 -> 1.3 | G22: =G6/1000 -> 1.3 | H22: =H6/1000 -> 1.3 | I22: =I6/1000 -> 1.2 | ... M22: =M6/1000 -> 0.8 | N22: =SUM(G22:M22) -> 7.49
A23: LOI | B23: 0 | C23: 0 | D23: 0 | E23: 0 | F23: 0 | G23: 0 | H23: 0 | I23: 0 | J23: 0 | K23: 6 | L23: 11 | M23: 27 | N23: =SUM(G23:M23) -> 44
A24: GROUP COMPANY | B24: 10.9 | C24: 4.1 | D24: 5.4 | E24: ='[62]SUMMARY-MFG'!D51 -> 10.646 | F24: ='[62]SUMMARY-MFG'!E51 -> 8.49 | G24: ='SUMMARY-CP'!D51 -> 15.2655 | H24: ='SUMMARY-CP'!E51 -> 15.5025 | I24: ='SUMMARY-CP'!F51 -> 15.5905 | J24: ='SUMMARY-CP'!G51 -> 16.8535 | K24: ='SUMMARY-CP'!H51 -> 21.3095 | L24: ='SUMMARY-CP'!I51 -> 22.2405 | M24: ='SUMMARY-CP'!J51 -> 10.726 | N24: =SUM(G24:M24) -> 117.488
A25: CONTRACT MFG. | B25: 7.13958 | C25: 13.3 | D25: ='[62]SUMMARY-MFG'!D53 -> 11.57 | E25: ='[62]SUMMARY-MFG'!D53 -> 11.57 | F25: ='[62]SUMMARY-MFG'!E53 -> 11.779 | G25: ='SUMMARY-CP'!D53 -> 6.9755 | H25: ='SUMMARY-CP'!E53 -> 7.5165 | I25: ='SUMMARY-CP'!F53 -> 4.789 | J25: ='SUMMARY-CP'!G53 -> 3.879 | K25: ='SUMMARY-CP'!H53 -> 4.028 | L25: ='SUMMARY-CP'!I53 -> 2.985 | M25: ='SUMMARY-CP'!J53 -> 2.91 | N25: =SUM(G25:M25) -> 33.083
A26: PLANNED HOURS | B26: =SUM(B18:B22) -> 70.601545 | C26: =SUM(C18:C22) -> 65.327 | D26: =SUM(D18:D22) -> 70.377 | E26: =SUM(E18:E22) -> 70.068 | F26: =SUM(F18:F22) -> 70.044 | G26: =SUM(G18:G22) -> 66.83425 | H26: =SUM(H18:H22) -> 64.26225 | I26: =SUM(I18:I22) -> 63.69575 | ... M26: =SUM(M18:M22) -> 37.396 | N26: =SUM(G26:M26) -> 406.222
A29: NPK | B29: 46028 | C29: 46060 | D29: 46092 | E29: 46124 | F29: 46156 | G29: 46188 | H29: 46220 | I29: 46252 | J29: 46284 | K29: 46316 | L29: 46348 | M29: 46380 | N29: Planned Hours Apr'26-Dec'26
A30: WELDING | B30: =B10/1000 -> 51.778145 | C30: =C10/1000 -> 46.767 | D30: =D10/1000 -> 51.778145 | E30: =E10/1000 -> 50.107882 | F30: =F10/1000 -> 51.778145 | G30: =G10/1000 -> 50.107882 | H30: =H10/1000 -> 51.778145 | I30: =I10/1000 -> 51.778145 | ... M30: =M10/1000 -> 51.778145 | N30: =SUM(G30:M30) -> 357.43623
A31: MACHINING | B31: =B11/1000 -> 9.0287312 | C31: =C11/1000 -> 8.155 | D31: =D11/1000 -> 9.0287312 | E31: =E11/1000 -> 8.7374818 | F31: =F11/1000 -> 9.0287312 | G31: =G11/1000 -> 8.7374818 | H31: =H11/1000 -> 9.0287312 | I31: =I11/1000 -> 9.0287312 | ... M31: =M11/1000 -> 9.0287312 | N31: =SUM(G31:M31) -> 62.32737
A32: ASSEMBLY | B32: =B12/1000 -> 5.6043329 | C32: =C12/1000 -> 5.062 | D32: =D12/1000 -> 5.6043329 | E32: =E12/1000 -> 5.4235479 | F32: =F12/1000 -> 5.6043329 | G32: =G12/1000 -> 5.4235479 | H32: =H12/1000 -> 5.6043329 | I32: =I12/1000 -> 5.6043329 | ... M32: =M12/1000 -> 5.6043329 | N32: =SUM(G32:M32) -> 38.687975
A33: ROLL REFURBISHMENT | B33: =B13/1000 -> 2.3401581 | C33: =C13/1000 -> 2.34 | D33: =D13/1000 -> 2.3401581 | E33: =E13/1000 -> 2.3401581 | F33: =F13/1000 -> 2.2646692 | G33: =G13/1000 -> 2.2646692 | H33: =H13/1000 -> 2.3401581 | I33: =I13/1000 -> 2.3401581 | ... M33: =M13/1000 -> 2.3401581 | N33: =SUM(G33:M33) -> 16.15464
A34: PLATING | B34: =B14/1000 -> 2.5224708 | C34: =C14/1000 -> 2.522 | D34: =D14/1000 -> 2.5224708 | E34: =E14/1000 -> 2.5224708 | F34: =F14/1000 -> 2.4411008 | G34: =G14/1000 -> 2.4411008 | H34: =H14/1000 -> 2.5224708 | I34: =I14/1000 -> 2.5224708 | ... M34: =M14/1000 -> 2.5224708 | N34: =SUM(G34:M34) -> 17.413186
A35: PLANNED HOURS | B35: =SUM(B30:B34) -> 71.273838 | C35: =SUM(C30:C34) -> 64.846 | D35: =SUM(D30:D34) -> 71.273838 | E35: =SUM(E30:E34) -> 69.131541 | F35: =SUM(F30:F34) -> 71.116979 | G35: =SUM(G30:G34) -> 68.974682 | H35: =SUM(H30:H34) -> 71.273838 | I35: =SUM(I30:I34) -> 71.273838 | ... M35: =SUM(M30:M34) -> 71.273838 | N35: =SUM(G35:M35) -> 492.0194
A36: UTILIZATION (%) | B36: =B26/B35 -> 0.99056746 | C36: =C26/C35 -> 1.0074176 | D36: =D26/D35 -> 0.98741701 | E36: =E26/E35 -> 1.013546 | F36: =F26/F35 -> 0.98491248 | G36: =G26/G35 -> 0.96896786 | H36: =H26/H35 -> 0.90162466 | I36: =I26/I35 -> 0.89367644 | ... N36: =N26/N35 -> 0.82562192
A54: NPK | B54: =N15/1000 -> 492.0194 | C54: Planned Hour | D54: NPK
A55: Planned Hours | B55: =N7/1000 -> 406.222 | C55: 0.89 | D55: 0.11

Sheet SCB PLAN
A1: Planned | B1: 46174 | C1: 46204 | D1: 46235 | E1: 46266 | F1: 46296 | G1: 46327 | H1: 46357 | I1: 46388 | J1: 46419 | K1: 46447 | L1: 46478 | M1: 46508 | N1: Planned Hours Jun'26-May'27
A2: WELDING | B2: ='SUMMARY-CP'!D6 -> 49831.25 | C2: ='SUMMARY-CP'!E6 -> 49026.75 | D2: ='SUMMARY-CP'!F6 -> 47313.75 | E2: ='SUMMARY-CP'!G6 -> 44617.75 | F2: ='SUMMARY-CP'!H6 -> 44183.5 | G2: ='SUMMARY-CP'!I6 -> 41776.5 | H2: ='SUMMARY-CP'!J6 -> 24975 | I2: ='SUMMARY-CP'!K6 -> 20989 | ... M2: ='SUMMARY-CP'!O6 -> 4050 | N2: =SUM(B2:M2) -> 346663.5
A3: MACHINING | B3: ='SUMMARY-CP'!D12 -> 8475 | C3: ='SUMMARY-CP'!E12 -> 6792.5 | D3: ='SUMMARY-CP'!F12 -> 8144 | E3: ='SUMMARY-CP'!G12 -> 6540 | F3: ='SUMMARY-CP'!H12 -> 7635 | G3: ='SUMMARY-CP'!I12 -> 6550 | H3: ='SUMMARY-CP'!J12 -> 5756 | I3: ='SUMMARY-CP'!K12 -> 4610 | ... M3: ='SUMMARY-CP'!O12 -> 4282 | N3: =SUM(B3:M3) -> 68584.5
A4: ASSEMBLY | B4: ='SUMMARY-CP'!D20 -> 5428 | C4: ='SUMMARY-CP'!E20 -> 5543 | D4: ='SUMMARY-CP'!F20 -> 5538 | E4: ='SUMMARY-CP'!G20 -> 5614 | F4: ='SUMMARY-CP'!H20 -> 5542 | G4: ='SUMMARY-CP'!I20 -> 4785 | H4: ='SUMMARY-CP'!J20 -> 4765 | I4: ='SUMMARY-CP'!K20 -> 4160 | ... M4: ='SUMMARY-CP'!O20 -> 100 | N4: =SUM(B4:M4) -> 45735
A5: ROLL REFURBISHMENT | B5: ='SUMMARY-CP'!D22 -> 1800 | C5: ='SUMMARY-CP'!E22 -> 1600 | D5: ='SUMMARY-CP'!F22 -> 1500 | E5: ='SUMMARY-CP'!G22 -> 1400 | F5: ='SUMMARY-CP'!H22 -> 1300 | G5: ='SUMMARY-CP'!I22 -> 1200 | H5: ='SUMMARY-CP'!J22 -> 1100 | I5: ='SUMMARY-CP'!K22 -> 1100 | ... M5: ='SUMMARY-CP'!O22 -> 1000 | N5: =SUM(B5:M5) -> 15276
A6: PLATING | B6: ='SUMMARY-CP'!D23 -> 1300 | C6: ='SUMMARY-CP'!E23 -> 1300 | D6: ='SUMMARY-CP'!F23 -> 1200 | E6: ='SUMMARY-CP'!G23 -> 1000 | F6: ='SUMMARY-CP'!H23 -> 1000 | G6: ='SUMMARY-CP'!I23 -> 890 | H6: ='SUMMARY-CP'!J23 -> 800 | I6: ='SUMMARY-CP'!K23 -> 700 | ... M6: ='SUMMARY-CP'!O23 -> 470 | N6: =SUM(B6:M6) -> 10260
A7: TOTAL | B7: =SUM(B2:B6) -> 66834.25 | C7: =SUM(C2:C6) -> 64262.25 | D7: =SUM(D2:D6) -> 63695.75 | E7: =SUM(E2:E6) -> 59171.75 | F7: =SUM(F2:F6) -> 59660.5 | G7: =SUM(G2:G6) -> 55201.5 | H7: =SUM(H2:H6) -> 37396 | I7: =SUM(I2:I6) -> 31559 | ... M7: =SUM(M2:M6) -> 9902 | N7: =SUM(B7:M7) -> 486519
A9: NPK Capacity | B9: 46174 | C9: 46204 | D9: 46235 | E9: 46266 | F9: 46296 | G9: 46327 | H9: 46357 | I9: 46388 | J9: 46419 | K9: 46447 | L9: 46478 | M9: 46508 | N9: Planned Hours Jun'26-May'27
A10: WELDING | B10: ='SUMMARY-CP'!D36 -> 50107.882 | C10: ='SUMMARY-CP'!E36 -> 51778.145 | D10: ='SUMMARY-CP'!F36 -> 51778.145 | E10: ='SUMMARY-CP'!G36 -> 50107.882 | F10: ='SUMMARY-CP'!H36 -> 51778.145 | G10: ='SUMMARY-CP'!I36 -> 50107.882 | H10: ='SUMMARY-CP'!J36 -> 51778.145 | I10: ='SUMMARY-CP'!K36 -> 51778.145 | ... M10: ='SUMMARY-CP'!O36 -> 51778.145 | N10: =SUM(B10:M10) -> 609645.9
A11: MACHINING | B11: =NPK!D11 -> 9028.7312 | C11: =NPK!E11 -> 8154.983 | D11: =NPK!F11 -> 9028.7312 | E11: =NPK!G11 -> 8737.4818 | F11: =NPK!H11 -> 9028.7312 | G11: =NPK!I11 -> 8737.4818 | H11: =NPK!J11 -> 9028.7312 | I11: =NPK!K11 -> 9028.7312 | ... M11: =NPK!O11 -> 9028.7312 | N11: =SUM(B11:M11) -> 106306.03
A12: ASSEMBLY | B12: ='SUMMARY-CP'!D43 -> 5423.5479 | C12: ='SUMMARY-CP'!E43 -> 5604.3329 | D12: ='SUMMARY-CP'!F43 -> 5604.3329 | E12: ='SUMMARY-CP'!G43 -> 5423.5479 | F12: ='SUMMARY-CP'!H43 -> 5604.3329 | G12: ='SUMMARY-CP'!I43 -> 5423.5479 | H12: ='SUMMARY-CP'!J43 -> 5604.3329 | I12: ='SUMMARY-CP'!K43 -> 5604.3329 | ... M12: ='SUMMARY-CP'!O43 -> 5604.3329 | N12: =SUM(B12:M12) -> 65986.5
A13: ROLL REFURBISHMENT | B13: ='SUMMARY-CP'!D45 -> 2264.6692 | C13: ='SUMMARY-CP'!E45 -> 2340.1581 | D13: ='SUMMARY-CP'!F45 -> 2340.1581 | E13: ='SUMMARY-CP'!G45 -> 2264.6692 | F13: ='SUMMARY-CP'!H45 -> 2340.1581 | G13: ='SUMMARY-CP'!I45 -> 2264.6692 | H13: ='SUMMARY-CP'!J45 -> 2340.1581 | I13: ='SUMMARY-CP'!K45 -> 2340.1581 | ... M13: ='SUMMARY-CP'!O45 -> 2340.1581 | N13: =SUM(B13:M13) -> 27553.475
A14: PLATING | B14: ='SUMMARY-CP'!D46 -> 2441.1008 | C14: ='SUMMARY-CP'!E46 -> 2522.4708 | D14: ='SUMMARY-CP'!F46 -> 2522.4708 | E14: ='SUMMARY-CP'!G46 -> 2441.1008 | F14: ='SUMMARY-CP'!H46 -> 2522.4708 | G14: ='SUMMARY-CP'!I46 -> 2441.1008 | H14: ='SUMMARY-CP'!J46 -> 2522.4708 | I14: ='SUMMARY-CP'!K46 -> 2522.4708 | ... M14: ='SUMMARY-CP'!O46 -> 2522.4708 | N14: =SUM(B14:M14) -> 29700.06
A15: TOTAL | B15: =SUM(B10:B14) -> 69265.931 | C15: =SUM(C10:C14) -> 70400.09 | D15: =SUM(D10:D14) -> 71273.838 | E15: =SUM(E10:E14) -> 68974.682 | F15: =SUM(F10:F14) -> 71273.838 | G15: =SUM(G10:G14) -> 68974.682 | H15: =SUM(H10:H14) -> 71273.838 | I15: =SUM(I10:I14) -> 71273.838 | ... M15: =SUM(M10:M14) -> 71273.838 | N15: =SUM(B15:M15) -> 839191.96
A17: Planned Hours | B17: 46174 | C17: 46204 | D17: 46235 | E17: 46266 | F17: 46296 | G17: 46327 | H17: 46357 | I17: 46388 | J17: 46419 | K17: 46447 | L17: 46478 | M17: 46508 | N17: Planned Hours Jun'26-May'27
A18: WELDING | B18: =B2/1000 -> 49.83125 | C18: =C2/1000 -> 49.02675 | D18: =D2/1000 -> 47.31375 | E18: =E2/1000 -> 44.61775 | F18: =F2/1000 -> 44.1835 | G18: =G2/1000 -> 41.7765 | H18: =H2/1000 -> 24.975 | I18: =I2/1000 -> 20.989 | ... M18: =M2/1000 -> 4.05 | N18: =SUM(B18:M18) -> 346.6635
A19: MACHINING | B19: =B3/1000 -> 8.475 | C19: =C3/1000 -> 6.7925 | D19: =D3/1000 -> 8.144 | E19: =E3/1000 -> 6.54 | F19: =F3/1000 -> 7.635 | G19: =G3/1000 -> 6.55 | H19: =H3/1000 -> 5.756 | I19: =I3/1000 -> 4.61 | ... M19: =M3/1000 -> 4.282 | N19: =SUM(B19:M19) -> 68.5845
A20: ASSEMBLY | B20: =B4/1000 -> 5.428 | C20: =C4/1000 -> 5.543 | D20: =D4/1000 -> 5.538 | E20: =E4/1000 -> 5.614 | F20: =F4/1000 -> 5.542 | G20: =G4/1000 -> 4.785 | H20: =H4/1000 -> 4.765 | I20: =I4/1000 -> 4.16 | ... M20: =M4/1000 -> 0.1 | N20: =SUM(B20:M20) -> 45.735
A21: ROLL REFURBISHMENT | B21: =B5/1000 -> 1.8 | C21: =C5/1000 -> 1.6 | D21: =D5/1000 -> 1.5 | E21: =E5/1000 -> 1.4 | F21: =F5/1000 -> 1.3 | G21: =G5/1000 -> 1.2 | H21: =H5/1000 -> 1.1 | I21: =I5/1000 -> 1.1 | ... M21: =M5/1000 -> 1 | N21: =SUM(B21:M21) -> 15.276
A22: PLATING | B22: =B6/1000 -> 1.3 | C22: =C6/1000 -> 1.3 | D22: =D6/1000 -> 1.2 | E22: =E6/1000 -> 1 | F22: =F6/1000 -> 1 | G22: =G6/1000 -> 0.89 | H22: =H6/1000 -> 0.8 | I22: =I6/1000 -> 0.7 | ... M22: =M6/1000 -> 0.47 | N22: =SUM(B22:M22) -> 10.26
A23: LOI | B23: 0 | C23: 0 | D23: 0 | E23: 0 | F23: 6 | G23: 11 | H23: 27 | I23: 31 | J23: 35 | K23: 35 | L23: 35 | M23: 35 | N23: =SUM(B23:M23) -> 215
A24: GROUP COMPANY | B24: ='SUMMARY-CP'!D51 -> 15.2655 | C24: ='SUMMARY-CP'!E51 -> 15.5025 | D24: ='SUMMARY-CP'!F51 -> 15.5905 | E24: ='SUMMARY-CP'!G51 -> 16.8535 | F24: ='SUMMARY-CP'!H51 -> 21.3095 | G24: ='SUMMARY-CP'!I51 -> 22.2405 | H24: ='SUMMARY-CP'!J51 -> 10.726 | I24: ='SUMMARY-CP'!K51 -> 10.17 | ... M24: ='SUMMARY-CP'!O51 -> 0 | N24: =SUM(B24:M24) -> 129.163
A25: CONTRACT MFG. | B25: ='SUMMARY-CP'!D53 -> 6.9755 | C25: ='SUMMARY-CP'!E53 -> 7.5165 | D25: ='SUMMARY-CP'!F53 -> 4.789 | E25: ='SUMMARY-CP'!G53 -> 3.879 | F25: ='SUMMARY-CP'!H53 -> 4.028 | G25: ='SUMMARY-CP'!I53 -> 2.985 | H25: ='SUMMARY-CP'!J53 -> 2.91 | I25: ='SUMMARY-CP'!K53 -> 2.91 | ... M25: ='SUMMARY-CP'!O53 -> 0 | N25: =SUM(B25:M25) -> 41.593
A26: PLANNED HOURS | B26: =SUM(B18:B22) -> 66.83425 | C26: =SUM(C18:C22) -> 64.26225 | D26: =SUM(D18:D22) -> 63.69575 | E26: =SUM(E18:E22) -> 59.17175 | F26: =SUM(F18:F22) -> 59.6605 | G26: =SUM(G18:G22) -> 55.2015 | H26: =SUM(H18:H22) -> 37.396 | I26: =SUM(I18:I22) -> 31.559 | ... M26: =SUM(M18:M22) -> 9.902 | N26: =SUM(B26:M26) -> 486.519
A29: NPK | B29: 46174 | C29: 46204 | D29: 46235 | E29: 46266 | F29: 46296 | G29: 46327 | H29: 46357 | I29: 46388 | J29: 46419 | K29: 46447 | L29: 46478 | M29: 46508 | N29: Planned Hours Jun'26-May'27
A30: WELDING | B30: =B10/1000 -> 50.107882 | C30: =C10/1000 -> 51.778145 | D30: =D10/1000 -> 51.778145 | E30: =E10/1000 -> 50.107882 | F30: =F10/1000 -> 51.778145 | G30: =G10/1000 -> 50.107882 | H30: =H10/1000 -> 51.778145 | I30: =I10/1000 -> 51.778145 | ... M30: =M10/1000 -> 51.778145 | N30: =SUM(B30:M30) -> 609.6459
A31: MACHINING | B31: =B11/1000 -> 9.0287312 | C31: =C11/1000 -> 8.154983 | D31: =D11/1000 -> 9.0287312 | E31: =E11/1000 -> 8.7374818 | F31: =F11/1000 -> 9.0287312 | G31: =G11/1000 -> 8.7374818 | H31: =H11/1000 -> 9.0287312 | I31: =I11/1000 -> 9.0287312 | ... M31: =M11/1000 -> 9.0287312 | N31: =SUM(B31:M31) -> 106.30603
A32: ASSEMBLY | B32: =B12/1000 -> 5.4235479 | C32: =C12/1000 -> 5.6043329 | D32: =D12/1000 -> 5.6043329 | E32: =E12/1000 -> 5.4235479 | F32: =F12/1000 -> 5.6043329 | G32: =G12/1000 -> 5.4235479 | H32: =H12/1000 -> 5.6043329 | I32: =I12/1000 -> 5.6043329 | ... M32: =M12/1000 -> 5.6043329 | N32: =SUM(B32:M32) -> 65.9865
A33: ROLL REFURBISHMENT | B33: =B13/1000 -> 2.2646692 | C33: =C13/1000 -> 2.3401581 | D33: =D13/1000 -> 2.3401581 | E33: =E13/1000 -> 2.2646692 | F33: =F13/1000 -> 2.3401581 | G33: =G13/1000 -> 2.2646692 | H33: =H13/1000 -> 2.3401581 | I33: =I13/1000 -> 2.3401581 | ... M33: =M13/1000 -> 2.3401581 | N33: =SUM(B33:M33) -> 27.553475
A34: PLATING | B34: =B14/1000 -> 2.4411008 | C34: =C14/1000 -> 2.5224708 | D34: =D14/1000 -> 2.5224708 | E34: =E14/1000 -> 2.4411008 | F34: =F14/1000 -> 2.5224708 | G34: =G14/1000 -> 2.4411008 | H34: =H14/1000 -> 2.5224708 | I34: =I14/1000 -> 2.5224708 | ... M34: =M14/1000 -> 2.5224708 | N34: =SUM(B34:M34) -> 29.70006
A35: PLANNED HOURS | B35: =SUM(B30:B34) -> 69.265931 | C35: =SUM(C30:C34) -> 70.40009 | D35: =SUM(D30:D34) -> 71.273838 | E35: =SUM(E30:E34) -> 68.974682 | F35: =SUM(F30:F34) -> 71.273838 | G35: =SUM(G30:G34) -> 68.974682 | H35: =SUM(H30:H34) -> 71.273838 | I35: =SUM(I30:I34) -> 71.273838 | ... M35: =SUM(M30:M34) -> 71.273838 | N35: =SUM(B35:M35) -> 839.19196
A36: UTILIZATION (%) | B36: =B26/B35 -> 0.96489354 | C36: =C26/C35 -> 0.91281489 | D36: =D26/D35 -> 0.89367644 | E36: =E26/E35 -> 0.85787637 | F36: =F26/F35 -> 0.8370603 | G36: =G26/G35 -> 0.8003154 | H36: =H26/H35 -> 0.5246806 | I36: =I26/I35 -> 0.44278519 | ... N36: =N26/N35 -> 0.57974697
A54: NPK | B54: NPK
A55: Planned Hours | B55: 0.11

Sheet TS
A1: WORK centre | B1: Product Group | C1: Month | D1: capacity | E1: Planned | F1: Inactual job availability
A2: MAATASLY | B2: Assembly/ Testing | C2: 46174 | D2: 5537 | E2: 700 | F2: 700
C3: 46204 | D3: 5537 | E3: 700 | F3: 700
C4: 46235 | D4: 5537 | E4: 700 | F4: 700
C5: 46266 | D5: 5537 | E5: 1500 | F5: Job yet to receive | G5: =E5+E17 -> 1566
C6: 46296 | D6: 5537 | E6: 1500 | G6: =E6+E18 -> 1566
C7: 46327 | D7: 5537 | E7: 1500 | G7: =E7+E19 -> 1566
C8: 46357 | D8: 5537 | E8: 1500 | G8: =E8+E20 -> 1566
C9: 46414 | D9: 5537 | E9: 1500 | G9: =E9+E21 -> 1566
C10: 46419 | D10: 5537 | E10: 1500 | G10: =E10+E22 -> 1566
C11: 46473 | D11: 5537 | E11: 1500 | G11: =E11+E23 -> 1566
C12: 46478 | D12: 5537 | E12: 1500 | G12: =E12+E24 -> 1566
C13: 46143 | D13: 5537 | E13: 1500 | G13: =E13+E25 -> 1566
A14: SKCCCYRE | B14: Hydraulic Test Stand | C14: 46174 | D14: 66 | E14: 20 | F14: 20
C15: 46204 | D15: 66 | E15: 20 | F15: 20
C16: 46235 | D16: 66 | E16: 20 | F16: 20
C17: 46266 | D17: 66 | E17: 66 | F17: Job yet to receive
C18: 46296 | D18: 66 | E18: 66
C19: 46327 | D19: 66 | E19: 66
C20: 46357 | D20: 66 | E20: 66
C21: 46414 | D21: 66 | E21: 66
C22: 46419 | D22: 66 | E22: 66
C23: 46473 | D23: 66 | E23: 66
C24: 46478 | D24: 66 | E24: 66
C25: 46143 | D25: 66 | E25: 66
A26: CC | C26: Total | D26: =SUM(D2:D25) -> 67236 | E26: =SUM(E2:E25) -> 16254
A27: SKRRASDI | B27: Assembly / Disassembly | C27: 46174 | D27: 1153 | E27: 900 | F27: 900 | G27: =E27+E39+E51+E63 -> 1848
C28: 46204 | D28: 1153 | E28: 900 | F28: 900 | G28: =E28+E40+E52+E64 -> 1848
C29: 46235 | D29: 1153 | E29: 900 | F29: 900 | G29: =E29+E41+E53+E65 -> 1848
C30: 46266 | D30: 1153 | E30: 600 | F30: 900 | G30: =E30+E42+E54+E66 -> 1548
C31: 46296 | D31: 1153 | E31: 600 | F31: 900 | G31: =E31+E43+E55+E67 -> 1548
C32: 46327 | D32: 1153 | E32: 600 | F32: Job yet to receive | G32: =E44+E56+E68 -> 948
C33: 46357 | D33: 1153 | E33: 600 | G33: =E45+E57+E69 -> 948
C34: 46414 | D34: 1153 | E34: 600 | G34: =E46+E58+E70 -> 948
C35: 46419 | D35: 1153 | E35: 600 | G35: =E47+E59+E71 -> 948
C36: 46473 | D36: 1153 | E36: 600 | G36: =E48+E60+E72 -> 948
C37: 46478 | D37: 1153 | E37: 600 | G37: =E49+E61+E73 -> 948
C38: 46143 | D38: 1153 | E38: 600 | G38: =E50+E62+E74 -> 948
A39: SKRRL500 | B39: 500 mm - 2 Head Roll Welding Lathe | C39: 46174 | D39: 350 | E39: 350
C40: 46204 | D40: 350 | E40: 350
C41: 46235 | D41: 350 | E41: 350
C42: 46266 | D42: 350 | E42: 350
C43: 46296 | D43: 350 | E43: 350
C44: 46327 | D44: 350 | E44: 350
C45: 46357 | D45: 350 | E45: 350
C46: 46414 | D46: 350 | E46: 350
C47: 46419 | D47: 350 | E47: 350
C48: 46473 | D48: 350 | E48: 350
C49: 46478 | D49: 350 | E49: 350
C50: 46143 | D50: 350 | E50: 350
A51: SKRRL11M | B51: 1100 mm - 2 Head Roll Welding Lathe | C51: 46174 | D51: 350 | E51: 350
C52: 46204 | D52: 350 | E52: 350
C53: 46235 | D53: 350 | E53: 350
C54: 46266 | D54: 350 | E54: 350
C55: 46296 | D55: 350 | E55: 350
C56: 46327 | D56: 350 | E56: 350
C57: 46357 | D57: 350 | E57: 350
C58: 46414 | D58: 350 | E58: 350
C59: 46419 | D59: 350 | E59: 350
C60: 46473 | D60: 350 | E60: 350
C61: 46478 | D61: 350 | E61: 350
C62: 46143 | D62: 350 | E62: 350
A63: SKRRFURN | B63: Furnace | C63: 46174 | D63: 248 | E63: 248
C64: 46204 | D64: 248 | E64: 248
C65: 46235 | D65: 248 | E65: 248
C66: 46266 | D66: 248 | E66: 248
C67: 46296 | D67: 248 | E67: 248
C68: 46327 | D68: 248 | E68: 248
C69: 46357 | D69: 248 | E69: 248
C70: 46414 | D70: 248 | E70: 248
C71: 46419 | D71: 248 | E71: 248
C72: 46473 | D72: 248 | E72: 248
C73: 46478 | D73: 248 | E73: 248
C74: 46143 | D74: 248 | E74: 248
A75: RR | C75: Total | D75: =SUM(D27:D74) -> 25212 | E75: =SUM(E27:E74) -> 19476
A76: SKPLASDI | B76: Plating / HVOF Labour Hours | C76: 46174 | D76: 217 | E76: 200 | F76: 200 | G76: =SUM(E76,E88,E100,E112,E124) -> 2880
C77: 46204 | D77: 217 | E77: 200 | F77: 200 | G77: =SUM(E77,E89,E101,E113,E125) -> 2880
C78: 46235 | D78: 217 | E78: 200 | F78: 200 | G78: =SUM(E78,E90,E102,E114,E126) -> 2880
C79: 46266 | D79: 217 | E79: 150 | F79: Job yet to receive | G79: =SUM(E91,E127) -> 1620 | H79: =SUM(E79,E103,E115) -> 850
C80: 46296 | D80: 217 | E80: 150 | H80: =SUM(E80,E92,E104,E116,E128) -> 1650
C81: 46327 | D81: 217 | E81: 150 | H81: =SUM(E81,E93,E105,E117,E129) -> 1650
C82: 46357 | D82: 217 | E82: 150 | H82: =SUM(E82,E94,E106,E118,E130) -> 1650
C83: 46414 | D83: 217 | E83: 150 | H83: =SUM(E83,E95,E107,E119,E131) -> 1650
C84: 46419 | D84: 217 | E84: 150 | H84: =SUM(E84,E96,E108,E120,E132) -> 1650
C85: 46473 | D85: 217 | E85: 150 | H85: =SUM(E85,E97,E109,E121,E133) -> 1650
C86: 46478 | D86: 217 | E86: 150 | H86: =SUM(E86,E98,E110,E122,E134) -> 1650
C87: 46143 | D87: 217 | E87: 150 | H87: =SUM(E87,E99,E111,E123,E135) -> 1600
A88: SKPLBOXP | B88: Box Plating | C88: 46174 | D88: 1612 | E88: 1500 | F88: 1500
C89: 46204 | D89: 1612 | E89: 1500 | F89: 1500
C90: 46235 | D90: 1612 | E90: 1500 | F90: 1500
C91: 46266 | D91: 1612 | E91: 1500 | F91: 1500
C92: 46296 | D92: 1612 | E92: 700 | F92: Job yet to receive
C93: 46327 | D93: 1612 | E93: 700
C94: 46357 | D94: 1612 | E94: 700
C95: 46414 | D95: 1612 | E95: 700
C96: 46419 | D96: 1612 | E96: 700
C97: 46473 | D97: 1612 | E97: 700
C98: 46478 | D98: 1612 | E98: 700
C99: 46143 | D99: 1612 | E99: 700
A100: SKPLDIPP | B100: Dip Plating | C100: 46174 | D100: 780 | E100: 780 | F100: 780
...

Sheet NPK
A1: Sl No | B1: Available Capacity (NPK)-2026 | C1: Total Available Hour | D1: 46023 | E1: 46054 | F1: 46082 | G1: 46113 | H1: 46143 | I1: 46174 | J1: 46204 | K1: 46235 | L1: 46266 | M1: 46296 | N1: 46327 | O1: 46357
A2: 1.1 | B2: KHURDA-WELDING-SMI | C2: =SUM(D2:O2) -> 19367.917 | D2: 1644.9464 | E2: 1485.758 | F2: 1644.9464 | G2: 1591.8836 | H2: 1644.9464 | I2: 1591.8836 | J2: 1644.9464 | K2: 1644.9464 | L2: 1591.8836 | M2: 1644.9464 | N2: 1591.8836 | O2: 1644.9464
A3: 1.2 | B3: KHURDA-WELDING-LS | C3: =SUM(D3:O3) -> 261466.88 | D3: 22206.776 | E3: 20057.733 | F3: 22206.776 | G3: 21490.428 | H3: 22206.776 | I3: 21490.428 | J3: 22206.776 | K3: 22206.776 | L3: 21490.428 | M3: 22206.776 | N3: 21490.428 | O3: 22206.776
A4: 1.3 | B4: KHURDA-WELDING-JC | C4: =SUM(D4:O4) -> 180767.22 | D4: 15352.833 | E4: 13867.075 | F4: 15352.833 | G4: 14857.58 | H4: 15352.833 | I4: 14857.58 | J4: 15352.833 | K4: 15352.833 | L4: 14857.58 | M4: 15352.833 | N4: 14857.58 | O4: 15352.833
A5: 1.1-1.3 | B5: KHURDA-WELDING (SMI+LS+JC) | C5: =C2+C3+C4 -> 461602.02 | D5: =D2+D3+D4 -> 39204.555 | E5: =E2+E3+E4 -> 35410.566 | F5: =F2+F3+F4 -> 39204.555 | G5: =G2+G3+G4 -> 37939.892 | H5: =H2+H3+H4 -> 39204.555 | I5: =I2+I3+I4 -> 37939.892 | J5: =J2+J3+J4 -> 39204.555 | ... O5: =O2+O3+O4 -> 39204.555
A6: 1.4 | B6: MANCHESWAR-WELDING-JC | C6: =SUM(D6:O6) -> 140252.1 | D6: 11911.822 | E6: 10759.065 | F6: 11911.822 | G6: 11527.57 | H6: 11911.822 | I6: 11527.57 | J6: 11911.822 | K6: 11911.822 | L6: 11527.57 | M6: 11911.822 | N6: 11527.57 | O6: 11911.822
A7: 1.5 | B7: MANCHESWAR-WELDING-LS | C7: =SUM(D7:O7) -> 6233.4265 | D7: 529.41431 | E7: 478.18067 | F7: 529.41431 | G7: 512.33643 | H7: 529.41431 | I7: 512.33643 | J7: 529.41431 | K7: 529.41431 | L7: 512.33643 | M7: 529.41431 | N7: 512.33643 | O7: 529.41431
A8: 1.6 | B8: MANCHESWAR-WELDING-SMI | C8: =SUM(D8:O8) -> 1558.3566 | D8: 132.35358 | E8: 119.54517 | F8: 132.35358 | G8: 128.08411 | H8: 132.35358 | I8: 128.08411 | J8: 132.35358 | K8: 132.35358 | L8: 128.08411 | M8: 132.35358 | N8: 128.08411 | O8: 132.35358
A9: 1 | B9: K & M - WELDING (TOTAL) | C9: =C5+C6+C8+C7 -> 609645.9 | D9: =D5+D6+D8+D7 -> 51778.145 | E9: =E5+E6+E8+E7 -> 46767.357 | F9: =F5+F6+F8+F7 -> 51778.145 | G9: =G5+G6+G8+G7 -> 50107.882 | H9: =H5+H6+H8+H7 -> 51778.145 | I9: =I5+I6+I8+I7 -> 50107.882 | J9: =J5+J6+J8+J7 -> 51778.145 | ... O9: =O5+O6+O8+O7 -> 51778.145
A11: 2 | B11: TOTAL MACHINE SHOP | C11: =SUM(D11:O11) -> 106306.03 | D11: 9028.7312 | E11: 8154.983 | F11: 9028.7312 | G11: 8737.4818 | H11: 9028.7312 | I11: 8737.4818 | J11: 9028.7312 | K11: 9028.7312 | L11: 8737.4818 | M11: 9028.7312 | N11: 8737.4818 | O11: 9028.7312
A13: 3.1 | B13: ASSEMBLY-SMI | C13: =SUM(D13:O13) -> 16496.625 | D13: 1401.0832 | E13: 1265.4945 | F13: 1401.0832 | G13: 1355.887 | H13: 1401.0832 | I13: 1355.887 | J13: 1401.0832 | K13: 1401.0832 | L13: 1355.887 | M13: 1401.0832 | N13: 1355.887 | O13: 1401.0832
A14: 3.2 | B14: ASSEMBLY-LS | C14: =SUM(D14:O14) -> 32993.25 | D14: 2802.1664 | E14: 2530.989 | F14: 2802.1664 | G14: 2711.774 | H14: 2802.1664 | I14: 2711.774 | J14: 2802.1664 | K14: 2802.1664 | L14: 2711.774 | M14: 2802.1664 | N14: 2711.774 | O14: 2802.1664
A15: 3.3 | B15: ASSEMBLY-JS | C15: =SUM(D15:O15) -> 16496.625 | D15: 1401.0832 | E15: 1265.4945 | F15: 1401.0832 | G15: 1355.887 | H15: 1401.0832 | I15: 1355.887 | J15: 1401.0832 | K15: 1401.0832 | L15: 1355.887 | M15: 1401.0832 | N15: 1355.887 | O15: 1401.0832
A16: 3 | B16: ASSEMBLY-MFG | C16: =C13+C14+C15 -> 65986.5 | D16: =D13+D14+D15 -> 5604.3329 | E16: =E13+E14+E15 -> 5061.9781 | F16: =F13+F14+F15 -> 5604.3329 | G16: =G13+G14+G15 -> 5423.5479 | H16: =H13+H14+H15 -> 5604.3329 | I16: =I13+I14+I15 -> 5423.5479 | J16: =J13+J14+J15 -> 5604.3329 | ... O16: =O13+O14+O15 -> 5604.3329
A18: 4 | B18: ROLL REFURBISHMENT | C18: =SUM(D18:O18) -> 27553.475 | D18: 2340.1581 | E18: 2113.6912 | F18: 2340.1581 | G18: 2264.6692 | H18: 2340.1581 | I18: 2264.6692 | J18: 2340.1581 | K18: 2340.1581 | L18: 2264.6692 | M18: 2340.1581 | N18: 2264.6692 | O18: 2340.1581
A19: 5 | B19: PLATING | C19: =SUM(D19:O19) -> 29700.06 | D19: 2522.4708 | E19: 2278.3608 | F19: 2522.4708 | G19: 2441.1008 | H19: 2522.4708 | I19: 2441.1008 | J19: 2522.4708 | K19: 2522.4708 | L19: 2441.1008 | M19: 2522.4708 | N19: 2441.1008 | O19: 2522.4708
B21: TOTAL MANUFACTRING | C21: =C9+C11+C16+C18+C19 -> 839191.96 | D21: =D9+D11+D16+D18+D19 -> 71273.838 | E21: =E9+E11+E16+E18+E19 -> 64376.37 | F21: =F9+F11+F16+F18+F19 -> 71273.838 | G21: =G9+G11+G16+G18+G19 -> 68974.682 | H21: =H9+H11+H16+H18+H19 -> 71273.838 | I21: =I9+I11+I16+I18+I19 -> 68974.682 | J21: =J9+J11+J16+J18+J19 -> 71273.838 | ... O21: =O9+O11+O16+O18+O19 -> 71273.838

Sheet Welding
A3: Row Labels | B3: Sum of Jun/26 | C3: Sum of Jul/26 | D3: Sum of Aug/26 | E3: Sum of Sep/26 | F3: Sum of Oct/26 | G3: Sum of Nov/26 | H3: Sum of Dec/26 | I3: Sum of Jan/27 | J3: Sum of Feb/27 | K3: Sum of Mar/27 | L3: Sum of Apr/27 | M3: Sum of May/27
A4: Contract | B4: 4532.5 | C4: 5139.5 | D4: 4322 | E4: 3569 | F4: 3568 | G4: 2500 | H4: 2500 | I4: 2500 | J4: 2500 | K4: 2500
A5: Group | B5: 14938.5 | C5: 15175.5 | D5: 14938.5 | E5: 16142.5 | F5: 20441.5 | G5: 21440.5 | H5: 9884 | I5: 9385 | J5: 450
A6: OTH | B6: 30360.25 | C6: 28711.75 | D6: 28053.25 | E6: 24906.25 | F6: 20174 | G6: 17836 | H6: 12591 | I6: 9104 | J6: 6350 | K6: 4050 | L6: 4050 | M6: 4050
A7: (blank) | B7: 49831.25 | C7: 49026.75 | D7: 47313.75 | E7: 44617.75 | F7: 44183.5 | G7: 41776.5 | H7: 24975 | I7: 20989 | J7: 9300 | K7: 6550 | L7: 4050 | M7: 4050
A8: Grand Total | B8: 99662.5 | C8: 98053.5 | D8: 94627.5 | E8: 89235.5 | F8: 88367 | G8: 83553 | H8: 49950 | I8: 41978 | J8: 18600 | K8: 13100 | L8: 8100 | M8: 8100

Sheet Machining
A2: Milling Machining
A3: Row Labels | B3: Sum of Jun-26 | C3: Sum of Jul-26 | D3: Sum of Aug-26 | E3: Sum of Sep-26 | F3: Sum of Oct-26 | G3: Sum of Nov-26 | H3: Sum of Dec-26 | I3: Sum of Jan-27 | J3: Sum of Feb-27 | K3: Sum of Mar-27 | L3: Sum of Apr-27 | M3: Sum of May-27
A4: Contract | B4: 731 | C4: 610 | D4: 310 | E4: 110 | F4: 10 | G4: 85 | H4: 10 | I4: 10
A5: Group | B5: 327 | C5: 327 | D5: 552 | E5: 611 | F5: 326 | G5: 414 | H5: 470 | I5: 414 | J5: 414
A6: OTH | B6: 2213 | C6: 1556.5 | D6: 1768 | E6: 1715 | F6: 2650 | G6: 2107 | H6: 1697 | I6: 1215 | J6: 757
A7: (blank) | B7: 3521 | C7: 3493.5 | D7: 3630 | E7: 2786 | F7: 3036 | G7: 3106 | H7: 3177 | I7: 2639 | J7: 2171 | K7: 1000 | L7: 1000 | M7: 1850
A8: TS | B8: 250 | C8: 1000 | D8: 1000 | E8: 350 | F8: 50 | G8: 500 | H8: 1000 | I8: 1000 | J8: 1000 | K8: 1000 | L8: 1000 | M8: 1850
A9: Grand Total | B9: 7042 | C9: 6987 | D9: 7260 | E9: 5572 | F9: 6072 | G9: 6212 | H9: 6354 | I9: 5278 | J9: 4342 | K9: 2000 | L9: 2000 | M9: 3700
A11: CNC Lathe Machining
A12: Row Labels | B12: Sum of Jun-26 | C12: Sum of Jul-26 | D12: Sum of Aug-26 | E12: Sum of Sep-26 | F12: Sum of Oct-26 | G12: Sum of Nov-26 | H12: Sum of Dec-26 | I12: Sum of Jan-27 | J12: Sum of Feb-27 | K12: Sum of Mar-27 | L12: Sum of Apr-27 | M12: Sum of May-27
A13: Contract | B13: 532 | C13: 698 | D13: 157 | E13: 150 | F13: 150 | G13: 100 | H13: 100 | I13: 100
A14: Group | D14: 100 | E14: 100 | F14: 92 | G14: 386 | H14: 372 | I14: 371 | J14: 311
A15: OTH | B15: 2822 | C15: 1001 | D15: 2657 | E15: 1904 | F15: 2857 | G15: 1458 | H15: 607 | L15: 150
A16: (blank) | B16: 4954 | C16: 3299 | D16: 4514 | E16: 3754 | F16: 4599 | G16: 3444 | H16: 2579 | I16: 1971 | J16: 1811 | K16: 1236 | L16: 2582 | M16: 2432
A17: TS | B17: 1600 | C17: 1600 | D17: 1600 | E17: 1600 | F17: 1500 | G17: 1500 | H17: 1500 | I17: 1500 | J17: 1500 | K17: 1236 | L17: 2432 | M17: 2432
A18: Grand Total | B18: 9908 | C18: 6598 | D18: 9028 | E18: 7508 | F18: 9198 | G18: 6888 | H18: 5158 | I18: 3942 | J18: 3622 | K18: 2472 | L18: 5164 | M18: 4864
A20: Total Machinig | B20: 46174 | C20: 46204 | D20: 46235 | E20: 46266 | F20: 46296 | G20: 46327 | H20: 46357 | I20: 46388 | J20: 46419 | K20: 46447 | L20: 46478 | M20: 46508
A21: Contract | B21: =GETPIVOTDATA("Sum of Jun-26",$A$3,"Order","Contract")+GETPIVOTDATA("Sum of Jun-26",$A$12,"Order","Contract") -> 1263 | C21: =GETPIVOTDATA("Sum of Jul-26",$A$3,"Order","Contract")+GETPIVOTDATA("Sum of Jul-26",$A$12,"Order","Contract") -> 1308 | D21: =GETPIVOTDATA("Sum of Aug-26",$A$3,"Order","Contract")+GETPIVOTDATA("Sum of Aug-26",$A$12,"Order","Contract") -> 467 | E21: =GETPIVOTDATA("Sum of Sep-26",$A$3,"Order","Contract")+GETPIVOTDATA("Sum of Sep-26",$A$12,"Order","Contract") -> 260 | F21: =GETPIVOTDATA("Sum of Oct-26",$A$3,"Order","Contract")+GETPIVOTDATA("Sum of Oct-26",$A$12,"Order","Contract") -> 160 | G21: =GETPIVOTDATA("Sum of Nov-26",$A$3,"Order","Contract")+GETPIVOTDATA("Sum of Nov-26",$A$12,"Order","Contract") -> 185 | H21: =GETPIVOTDATA("Sum of Dec-26",$A$3,"Order","Contract")+GETPIVOTDATA("Sum of Dec-26",$A$12,"Order","Contract") -> 110 | I21: =GETPIVOTDATA("Sum of Jan-27",$A$3,"Order","Contract")+GETPIVOTDATA("Sum of Jan-27",$A$12,"Order","Contract") -> 110 | J21: =GETPIVOTDATA("Sum of Feb-27",$A$3,"Order","Contract")+GETPIVOTDATA("Sum of Feb-27",$A$12,"Order","Contract") -> 0 | K21: =GETPIVOTDATA("Sum of Mar-27",$A$3,"Order","Contract")+GETPIVOTDATA("Sum of Mar-27",$A$12,"Order","Contract") -> 0 | L21: =GETPIVOTDATA("Sum of Apr-27",$A$3,"Order","Contract")+GETPIVOTDATA("Sum of Apr-27",$A$12,"Order","Contract") -> 0 | M21: =GETPIVOTDATA("Sum of May-27",$A$3,"Order","Contract")+GETPIVOTDATA("Sum of May-27",$A$12,"Order","Contract") -> 0
A22: Group | B22: =GETPIVOTDATA("Sum of Jun-26",$A$3,"Order","Group")+GETPIVOTDATA("Sum of Jun-26",$A$12,"Order","Group") -> 327 | C22: =GETPIVOTDATA("Sum of Jul-26",$A$3,"Order","Group")+GETPIVOTDATA("Sum of Jul-26",$A$12,"Order","Group") -> 327 | D22: =GETPIVOTDATA("Sum of Aug-26",$A$3,"Order","Group")+GETPIVOTDATA("Sum of Aug-26",$A$12,"Order","Group") -> 652 | E22: =GETPIVOTDATA("Sum of Sep-26",$A$3,"Order","Group")+GETPIVOTDATA("Sum of Sep-26",$A$12,"Order","Group") -> 711 | F22: =GETPIVOTDATA("Sum of Oct-26",$A$3,"Order","Group")+GETPIVOTDATA("Sum of Oct-26",$A$12,"Order","Group") -> 418 | G22: =GETPIVOTDATA("Sum of Nov-26",$A$3,"Order","Group")+GETPIVOTDATA("Sum of Nov-26",$A$12,"Order","Group") -> 800 | H22: =GETPIVOTDATA("Sum of Dec-26",$A$3,"Order","Group")+GETPIVOTDATA("Sum of Dec-26",$A$12,"Order","Group") -> 842 | I22: =GETPIVOTDATA("Sum of Jan-27",$A$3,"Order","Group")+GETPIVOTDATA("Sum of Jan-27",$A$12,"Order","Group") -> 785 | J22: =GETPIVOTDATA("Sum of Feb-27",$A$3,"Order","Group")+GETPIVOTDATA("Sum of Feb-27",$A$12,"Order","Group") -> 725 | K22: =GETPIVOTDATA("Sum of Mar-27",$A$3,"Order","Group")+GETPIVOTDATA("Sum of Mar-27",$A$12,"Order","Group") -> 0 | L22: =GETPIVOTDATA("Sum of Apr-27",$A$3,"Order","Group")+GETPIVOTDATA("Sum of Apr-27",$A$12,"Order","Group") -> 0 | M22: =GETPIVOTDATA("Sum of May-27",$A$3,"Order","Group")+GETPIVOTDATA("Sum of May-27",$A$12,"Order","Group") -> 0
A23: OTH | B23: =GETPIVOTDATA("Sum of Jun-26",$A$3,"Order","OTH")+GETPIVOTDATA("Sum of Jun-26",$A$12,"Order","OTH") -> 5035 | C23: =GETPIVOTDATA("Sum of Jul-26",$A$3,"Order","OTH")+GETPIVOTDATA("Sum of Jul-26",$A$12,"Order","OTH") -> 2557.5 | D23: =GETPIVOTDATA("Sum of Aug-26",$A$3,"Order","OTH")+GETPIVOTDATA("Sum of Aug-26",$A$12,"Order","OTH") -> 4425 | E23: =GETPIVOTDATA("Sum of Sep-26",$A$3,"Order","OTH")+GETPIVOTDATA("Sum of Sep-26",$A$12,"Order","OTH") -> 3619 | F23: =GETPIVOTDATA("Sum of Oct-26",$A$3,"Order","OTH")+GETPIVOTDATA("Sum of Oct-26",$A$12,"Order","OTH") -> 5507 | G23: =GETPIVOTDATA("Sum of Nov-26",$A$3,"Order","OTH")+GETPIVOTDATA("Sum of Nov-26",$A$12,"Order","OTH") -> 3565 | H23: =GETPIVOTDATA("Sum of Dec-26",$A$3,"Order","OTH")+GETPIVOTDATA("Sum of Dec-26",$A$12,"Order","OTH") -> 2304 | I23: =GETPIVOTDATA("Sum of Jan-27",$A$3,"Order","OTH")+GETPIVOTDATA("Sum of Jan-27",$A$12,"Order","OTH") -> 1215 | J23: =GETPIVOTDATA("Sum of Feb-27",$A$3,"Order","OTH")+GETPIVOTDATA("Sum of Feb-27",$A$12,"Order","OTH") -> 757 | K23: =GETPIVOTDATA("Sum of Mar-27",$A$3,"Order","OTH")+GETPIVOTDATA("Sum of Mar-27",$A$12,"Order","OTH") -> 0 | L23: =GETPIVOTDATA("Sum of Apr-27",$A$3,"Order","OTH")+GETPIVOTDATA("Sum of Apr-27",$A$12,"Order","OTH") -> 150 | M23: =GETPIVOTDATA("Sum of May-27",$A$3,"Order","OTH")+GETPIVOTDATA("Sum of May-27",$A$12,"Order","OTH") -> 0
A24: TS | B24: =GETPIVOTDATA("Sum of Jun-26",$A$3,"Order","TS")+GETPIVOTDATA("Sum of Jun-26",$A$12,"Order","TS") -> 1850 | C24: =GETPIVOTDATA("Sum of Jul-26",$A$3,"Order","TS")+GETPIVOTDATA("Sum of Jul-26",$A$12,"Order","TS") -> 2600 | D24: =GETPIVOTDATA("Sum of Aug-26",$A$3,"Order","TS")+GETPIVOTDATA("Sum of Aug-26",$A$12,"Order","TS") -> 2600 | E24: =GETPIVOTDATA("Sum of Sep-26",$A$3,"Order","TS")+GETPIVOTDATA("Sum of Sep-26",$A$12,"Order","TS") -> 1950 | F24: =GETPIVOTDATA("Sum of Oct-26",$A$3,"Order","TS")+GETPIVOTDATA("Sum of Oct-26",$A$12,"Order","TS") -> 1550 | G24: =GETPIVOTDATA("Sum of Nov-26",$A$3,"Order","TS")+GETPIVOTDATA("Sum of Nov-26",$A$12,"Order","TS") -> 2000 | H24: =GETPIVOTDATA("Sum of Dec-26",$A$3,"Order","TS")+GETPIVOTDATA("Sum of Dec-26",$A$12,"Order","TS") -> 2500 | I24: =GETPIVOTDATA("Sum of Jan-27",$A$3,"Order","TS")+GETPIVOTDATA("Sum of Jan-27",$A$12,"Order","TS") -> 2500 | J24: =GETPIVOTDATA("Sum of Feb-27",$A$3,"Order","TS")+GETPIVOTDATA("Sum of Feb-27",$A$12,"Order","TS") -> 2500 | K24: =GETPIVOTDATA("Sum of Mar-27",$A$3,"Order","TS")+GETPIVOTDATA("Sum of Mar-27",$A$12,"Order","TS") -> 2236 | L24: =GETPIVOTDATA("Sum of Apr-27",$A$3,"Order","TS")+GETPIVOTDATA("Sum of Apr-27",$A$12,"Order","TS") -> 3432 | M24: =GETPIVOTDATA("Sum of May-27",$A$3,"Order","TS")+GETPIVOTDATA("Sum of May-27",$A$12,"Order","TS") -> 4282

Sheet Assembly
A3: Row Labels | B3: Sum of Jun-26 | C3: Sum of Jul-26 | D3: Sum of Aug-26 | E3: Sum of Sep-26 | F3: Sum of Oct-26 | G3: Sum of Nov-26 | H3: Sum of Dec-26 | I3: Sum of Jan-27 | J3: Sum of Feb-27 | K3: Sum of Mar-27 | L3: Sum of Apr-27 | M3: Sum of May-27
A4: Contract | B4: 1180 | C4: 1069 | E4: 50 | F4: 300 | G4: 300 | H4: 300 | I4: 300 | J4: 300 | K4: 300
A5: Group | F5: 450 | J5: 170 | K5: 160
A6: OTH | B6: 3308 | C6: 2224 | D6: 1928 | E6: 1754 | F6: 2302 | G6: 3775 | H6: 4265 | I6: 3090 | J6: 1470 | K6: 1060
A7: (blank) | B7: 5418 | C7: 5533 | D7: 5528 | E7: 5604 | F7: 5532 | G7: 4775 | H7: 4765 | I7: 4160 | J7: 2540 | K7: 1620 | L7: 100 | M7: 100
A8: IRON MAKING | B8: 900 | C8: 2200 | D8: 3350 | E8: 3500 | F8: 2200 | G8: 500 | I8: 670 | J8: 500
A9: TS | B9: 30 | C9: 40 | D9: 250 | E9: 300 | F9: 280 | G9: 200 | H9: 200 | I9: 100 | J9: 100 | K9: 100 | L9: 100 | M9: 100
A10: Grand Total | B10: 10836 | C10: 11066 | D10: 11056 | E10: 11208 | F10: 11064 | G10: 9550 | H10: 9530 | I10: 8320 | J10: 5080 | K10: 3240 | L10: 200 | M10: 200

Sheet Plan Vs Actual
A1: S.No. | B1: WBS/SO | C1: Equipment Name | D1: Planner | E1: Category | F1: Customer | G1: Project Budget Value (INR) | H1: MRM | I1: MBOD | J1: MBOS | K1: BO/FIM (LLD) | L1: MSC | M1: LOG | N1: Total Purchase Budget | O1: MRM (Plate, Structural & Pipe) | P1: MBOD ( Drawing Parts) | Q1: MBOS (Standard Parts) | R1: FIM/LLD | S1: MSC | T1: Consumables | U1: GGN BOOKED | V1: Packing | W1: Freight | X1: Others (Bank service, Business Trip, Indirect Materail cost & Miscellaneous Expenses | Y1: Adjustment Cost | Z1: Total Material Cost | AA1: Fabrication | AC1: Machining -1 (SKODA+INNSE+GIANA+5 Axis) | AD1: Machining-2 (RD,UD & HMT) | AE1: Total | AF1: Assembly | AH1: Total Manufacturing Budget | AI1: Fabrication | AK1: Machining -1 (SKODA+INNSE+GIANA+ 5 Axis+VTL+HMC) | AL1: Machining-2 Others Machine | AM1: Total | AN1: Assembly | AP1: Adjustment Hours | AQ1: Total Hours | AR1: Total Hours Cost | AS1: Total Manufacturing Cost 2022 ( A ) | AT1: Purchase Order Commitments ( B ) | AU1: Total EXP. Order Cost ( A+B) | AV1: Project Result | AW1: SCM Result | AX1: Manufacturing Result | AY1: Gross Margin %
AA2: Hours | AB2: Budget | AC2: Hours | AD2: Hours | AE2: Budget | AF2: Hours | AG2: Budget | AI2: Hours | AJ2: Cost | AK2: Hours | AL2: Hours | AM2: Cost | AN2: Hours | AO2: Cost | AP2: Cost
A3: 1 | B3: A03141M220.21.20P0110 | C3: Converter Oxygen Lance - 2 Nos | D3: PRRR | E3: WBS | F3: HOA PHAT | G3: 6091915 | H3: 3293972 | I3: 539981.6 | J3: 163818.2 | M3: 231527.8 | N3: =SUM(H3:M3) -> 4229299.6 | O3: 4709722.5 | P3: 774108.31 | Q3: 853077.46 | S3: 12957.6 | X3: 2124.5 | Z3: =SUM(O3:X3) -> 6351990.4 | AA3: 998 | AB3: 691700 | AD3: 43 | AE3: 32600 | AH3: =AB3+AE3+AG3 -> 724300 | AI3: 2008.45 | AJ3: 1236788 | AL3: 18.8 | AM3: 4360 | AQ3: =AI3+AK3+AL3+AN3 -> 2027.25 | AR3: =AJ3+AM3+AO3 -> 1241148 | AS3: =Z3+AR3 -> 7593138.4 | AT3: 97425.45 | AU3: =AS3+AT3 -> 7690563.8 | AV3: =G3-AU3+U3 -> -1598648.8 | AW3: =N3-Z3 -> -2122690.8 | AX3: =AH3-AR3 -> -516848 | AY3: =AV3/G3 -> -0.26242139
A4: 2 | B4: A03141M220.22.20P0110 | C4: Converter Oxygen Lance - 2 Nos | D4: PRRR | E4: WBS | F4: HOA PHAT | G4: 6091915 | H4: 3293972 | I4: 539981.6 | J4: 163818.2 | M4: 231527.8 | N4: =SUM(H4:M4) -> 4229299.6 | O4: 3998416.4 | P4: 387387.3 | Q4: 271518.49 | S4: 64780.2 | X4: 72474.88 | Y4: 3540052.9 | Z4: =SUM(O4:X4) -> 4794577.3 | AA4: 998 | AB4: 691700 | AD4: 43 | AE4: 32600 | AH4: =AB4+AE4+AG4 -> 724300 | AI4: 12.75 | AJ4: 20073 | AQ4: =AI4+AK4+AL4+AN4 -> 12.75 | AR4: =AJ4+AM4+AO4 -> 20073 | AS4: =Z4+AR4 -> 4814650.3 | AT4: 32951.8 | AU4: =AS4+AT4 -> 4847602.1 | AV4: =G4-AU4+U4 -> 1244312.9 | AW4: =N4-Z4 -> -565277.65 | AX4: =AH4-AR4 -> 704227 | AY4: =AV4/G4 -> 0.20425645
A5: 3 | B5: A03141M220.21.10.10P1150 | C5: Lamella Suspension | D5: JEAM01 | E5: WBS | F5: HOA PHAT | G5: 12716649 | H5: 4446345.1 | I5: 265376 | J5: 918720 | M5: 480505.6 | N5: =SUM(H5:M5) -> 6110946.7 | O5: 4464173.8 | P5: 540989.44 | Q5: 90955.68 | S5: 141771 | T5: 143127.62 | W5: 240000 | X5: 100612.98 | Z5: =SUM(O5:X5) -> 5721630.5 | AA5: 2491 | AB5: 1568439.2 | AC5: 736 | AD5: 120 | AE5: 3148800 | AF5: 500 | AG5: 600000 | AH5: =AB5+AE5+AG5 -> 5317239.2 | AI5: 1954.59 | AJ5: 1530916.2 | AK5: 406.9 | AL5: 366.3 | AM5: 2528415 | AN5: 413.5 | AO5: 496200 | AQ5: =AI5+AK5+AL5+AN5 -> 3141.29 | AR5: =AJ5+AM5+AO5 -> 4555531.2 | AS5: =Z5+AR5 -> 10277162 | AT5: 312316.3 | AU5: =AS5+AT5 -> 10589478 | AV5: =G5-AU5+U5 -> 2127171 | AW5: =N5-Z5 -> 389316.22 | AX5: =AH5-AR5 -> 761708 | AY5: =AV5/G5 -> 0.16727449
A6: 4 | B6: A03141M220.40.10.40P1020 | C6: GANTRY ASSEMBLY | D6: SAHAXAVI | E6: WBS | F6: HOA PHAT | G6: =7314780+122600 -> 7437380 | N6: =SUM(H6:M6) -> 0 | O6: -722649.92 | P6: 2923877.1 | Q6: 735834.86 | S6: 286884.7 | T6: 73229.46 | W6: 558000 | X6: 125652.73 | Y6: -3714130 | Z6: =SUM(O6:X6) -> 3980828.9 | AA6: =5600+32*100 -> 8800 | AC6: =250+180 -> 430 | AF6: =350+200 -> 550 | AH6: =AB6+AE6+AG6 -> 0 | AI6: 2828.24 | AJ6: 1628519 | AK6: 209.4 | AL6: 201.5 | AM6: 1073037.5 | AN6: 368.5 | AO6: 442200 | AP6: -312250 | AQ6: =AI6+AK6+AL6+AN6 -> 3607.64 | AR6: =AJ6+AM6+AO6 -> 3143756.5 | AS6: =Z6+AR6 -> 7124585.4 | AT6: 201270 | AU6: =AS6+AT6 -> 7325855.4 | AV6: =G6-AU6+U6 -> 111524.6 | AW6: =N6-Z6 -> -3980828.9 | AX6: =AH6-AR6 -> -3143756.5 | AY6: =AV6/G6 -> 0.014995146
A7: 5 | B7: A03332M610.60.20.30P1000 | C7: Ladle Transport Car No.1 | D7: RRAN | E7: WBS | F7: AURUBIS-USA | G7: 9213198 | H7: 1561587.3 | I7: 1812655 | J7: 39830 | M7: 124594.93 | N7: =SUM(H7:M7) -> 3538667.2 | O7: 1939236.9 | P7: 1796301.9 | Q7: 141116.13 | R7: 2648319.8 | S7: 189070.34 | T7: 2403.6 | V7: 98375 | W7: 97167 | X7: 51006.09 | Y7: -33554.818 | Z7: =SUM(O7:X7) -> 6962996.7 | AA7: 1844 | AB7: 1224400 | AC7: 243.66667 | AD7: 50 | AE7: 1141333.3 | AF7: 166.66667 | AG7: 200000 | AH7: =AB7+AE7+AG7 -> 2565733.3 | AI7: 2184.44 | AJ7: 1253734 | AK7: 65.3 | AL7: 197.6 | AM7: 393872.5 | AN7: 256.5 | AO7: 307800 | AQ7: =AI7+AK7+AL7+AN7 -> 2703.84 | AR7: =AJ7+AM7+AO7 -> 1955406.5 | AS7: =Z7+AR7 -> 8918403.2 | AT7: 36017.71 | AU7: =AS7+AT7 -> 8954420.9 | AV7: =G7-AU7+U7 -> 258777.11 | AW7: =N7-Z7 -> -3424329.4 | AX7: =AH7-AR7 -> 610326.83 | AY7: =AV7/G7 -> 0.028087653
A8: 6 | B8: A03332M610.60.20.30P2000 | C8: Ladle Transport Car No.2 | D8: RRAN | E8: WBS | F8: AURUBIS-USA | G8: 9213198 | H8: 1561587.3 | I8: 1812655 | J8: 39830 | M8: 124594.93 | N8: =SUM(H8:M8) -> 3538667.2 | O8: 1615420.4 | P8: 1796301.5 | Q8: 39006.08 | R8: 2617950.6 | S8: 450836.34 | T8: 2878.89 | V8: 98375 | W8: 104166 | X8: 44869.68 | Z8: =SUM(O8:X8) -> 6769804.5 | AA8: 1844 | AB8: 1224400 | AC8: 243.66667 | AD8: 50 | AE8: 1141333.3 | AF8: 166.66667 | AG8: 200000 | AH8: =AB8+AE8+AG8 -> 2565733.3 | AI8: 2166.74 | AJ8: 1224677 | AK8: 38.5 | AL8: 19.4 | AM8: 211195 | AN8: 317 | AO8: 380400 | AQ8: =AI8+AK8+AL8+AN8 -> 2541.64 | AR8: =AJ8+AM8+AO8 -> 1816272 | AS8: =Z8+AR8 -> 8586076.5 | AT8: 25219.29 | AU8: =AS8+AT8 -> 8611295.8 | AV8: =G8-AU8+U8 -> 601902.21 | AW8: =N8-Z8 -> -3231137.3 | AX8: =AH8-AR8 -> 749461.33 | AY8: =AV8/G8 -> 0.065330432
A9: 7 | B9: A03332M610.60.20.30P3000 | C9: Ladle Transport Car No.3 | D9: RRAN | E9: WBS | F9: AURUBIS-USA | G9: 9213198 | H9: 1561587.3 | I9: 1812655 | J9: 39830 | M9: 124594.93 | N9: =SUM(H9:M9) -> 3538667.2 | O9: 1678745.1 | P9: 1796301.3 | Q9: 44567.92 | R9: 2618029.1 | S9: 161591.32 | T9: 2628.87 | V9: 873881.39 | W9: 96667 | X9: 46670.16 | Z9: =SUM(O9:X9) -> 7319082.2 | AA9: 1844 | AB9: 1224400 | AC9: 243.66667 | AD9: 50 | AE9: 1141333.3 | AF9: 166.66667 | AG9: 200000 | AH9: =AB9+AE9+AG9 -> 2565733.3 | AI9: 2069.72 | AJ9: 1228144 | AK9: 45.6 | AL9: 20.1 | AM9: 218455 | AQ9: =AI9+AK9+AL9+AN9 -> 2135.42 | AR9: =AJ9+AM9+AO9 -> 1446599 | AS9: =Z9+AR9 -> 8765681.2 | AT9: 34587 | AU9: =AS9+AT9 -> 8800268.2 | AV9: =G9-AU9+U9 -> 412929.82 | AW9: =N9-Z9 -> -3780414.9 | AX9: =AH9-AR9 -> 1119134.3 | AY9: =AV9/G9 -> 0.04481938
A10: 8 | B10: A03141M220.21.10.10P1050 | C10: TRUNNION RING | D10: ASDH01 | E10: WBS | F10: HOA PHAT | G10: 59100000 | H10: 20238237 | I10: 14772200 | L10: 5697500 | M10: 4375600 | N10: =SUM(H10:M10) -> 45083537 | O10: 18959806 | P10: 44000 | Q10: 20247.38 | R10: 14255242 | S10: 4953186 | T10: 1495.38 | V10: 173258 | W10: 3312425 | X10: 1003041.6 | Y10: 448284.27 | Z10: =SUM(O10:X10) -> 42722701 | AA10: 19177 | AB10: 10685368 | AC10: 300 | AD10: 60 | AE10: 1189500 | AH10: =AB10+AE10+AG10 -> 11874868 | AI10: 13175.715 | AJ10: 9110413.5 | AK10: 106.4 | AL10: 43.8 | AM10: 692762.5 | AP10: -8325 | AQ10: =AI10+AK10+AL10+AN10 -> 13325.915 | AR10: =AJ10+AM10+AO10 -> 9803176 | AS10: =Z10+AR10 -> 52525877 | AT10: 62832.8 | AU10: =AS10+AT10 -> 52588710 | AV10: =G10-AU10+U10 -> 6511289.8 | AW10: =N10-Z10 -> 2360835.6 | AX10: =AH10-AR10 -> 2071692 | AY10: =AV10/G10 -> 0.11017411
A11: 9 | B11: A03307M220.40.10.10P1010 | C11: LF ROOF | D11: PADE | E11: WBS | F11: TATA-KPO | G11: =3667000+599421 -> 4266421 | H11: 1553396 | I11: 7358 | J11: 149404 | L11: 42105 | M11: =120000+33220 -> 153220 | N11: =SUM(H11:M11) -> 1905483 | O11: 1235754 | P11: 131371.05 | Q11: 132373.97 | R11: 510082.66 | S11: 98729.3 | W11: 67000 | X11: 4502.32 | Z11: =SUM(O11:X11) -> 2179813.3 | AA11: 2704 | AB11: 1561800 | AD11: 50 | AE11: 10000 | AH11: =AB11+AE11+AG11 -> 1571800 | AI11: 3321.03 | AJ11: 1941993.1 | AL11: 79 | AM11: 17775 | AQ11: =AI11+AK11+AL11+AN11 -> 3400.03 | AR11: =AJ11+AM11+AO11 -> 1959768.1 | AS11: =Z11+AR11 -> 4139581.5 | AT11: 58909 | AU11: =AS11+AT11 -> 4198490.5 | AV11: =G11-AU11+U11 -> 67930.53 | AW11: =N11-Z11 -> -274330.35 | AX11: =AH11-AR11 -> -387968.12 | AY11: =AV11/G11 -> 0.015922135
A12: 10 | B12: A03314M220.21.10.10P1000 | C12: Convertor Vessel (Unit -1) | D12: ASDH01 | E12: WBS | F12: AMNS-HAZIRA | G12: 48336000 | H12: 32125600 | L12: 1834700 | M12: 717600 | N12: =SUM(H12:M12) -> 34677900 | O12: 33747496 | Q12: 310832.53 | S12: 3214776.9 | T12: 321234.13 | W12: 3839758 | X12: 851645.15 | Y12: 2472882.5 | Z12: =SUM(O12:X12) -> 42285742 | AA12: 12703.333 | AB12: 7046300 | AD12: 130 | AE12: 72666.667 | AH12: =AB12+AE12+AG12 -> 7118966.7 | AI12: 10585.05 | AJ12: 6220659.8 | AK12: 17 | AL12: 30 | AM12: 118100 | AQ12: =AI12+AK12+AL12+AN12 -> 10632.05 | AR12: =AJ12+AM12+AO12 -> 6338759.8 | AS12: =Z12+AR12 -> 48624502 | AT12: 18809.02 | AU12: =AS12+AT12 -> 48643311 | AV12: =G12-AU12+U12 -> -307311.12 | AW12: =N12-Z12 -> -7607842.3 | AX12: =AH12-AR12 -> 780206.87 | AY12: =AV12/G12 -> -0.0063578103
A13: 11 | B13: A03314M220.21.10.10P1010 | C13: Lip Ring Segment 1 Nos | D13: ASDH01 | E13: WBS | F13: AMNS-HAZIRA | G13: 2555667 | H13: 2014683.3 | I13: 0 | J13: 266666.67 | M13: =(200000+70185)/3 -> 90061.667 | N13: =SUM(H13:M13) -> 2371411.7 | O13: 1686617.7 | Q13: 257220.01 | X13: 38876.76 | Z13: =SUM(O13:X13) -> 1982714.5 | AA13: 27.666667 | AB13: 87900 | AC13: 21.333333 | AD13: 0 | AE13: 60800 | AH13: =AB13+AE13+AG13 -> 148700 | AI13: 35.87 | AJ13: 82619 | AK13: 51.6 | AM13: 337980 | AQ13: =AI13+AK13+AL13+AN13 -> 87.47 | AR13: =AJ13+AM13+AO13 -> 420599 | AS13: =Z13+AR13 -> 2403313.5 | AU13: =AS13+AT13 -> 2403313.5 | AV13: =G13-AU13+U13 -> 152353.54 | AW13: =N13-Z13 -> 388697.21 | AX13: =AH13-AR13 -> -271899 | AY13: =AV13/G13 -> 0.059614003
A14: 12 | B14: A03080M221.20.10.10P1050 | C14: Converter Trunnion Ring | D14: ASDH01 | E14: WBS | F14: JSOL-ANGUL | G14: 42685992 | H14: 18908162 | I14: 12684140 | L14: 5630000 | M14: 608800 | N14: =SUM(H14:M14) -> 37831102 | O14: 17254658 | P14: 159051.32 | Q14: 20424.01 | S14: 5392590.3 | T14: 210468.86 | V14: 95450 | W14: 765425 | X14: 429452.08 | Y14: -931978.09 | Z14: =SUM(O14:X14) -> 24327519 | AA14: 17694 | AB14: 9815040 | AC14: 300 | AD14: 60 | AE14: 1189500 | AH14: =AB14+AE14+AG14 -> 11004540 | AI14: 10164.877 | AJ14: 7387354.5 | AK14: 171.5 | AL14: 180.5 | AM14: 1084795 | AQ14: =AI14+AK14+AL14+AN14 -> 10516.877 | AR14: =AJ14+AM14+AO14 -> 8472149.5 | AS14: =Z14+AR14 -> 32799669 | AT14: 450000 | AU14: =AS14+AT14 -> 33249669 | AV14: =G14-AU14+U14 -> 9436323.1 | AW14: =N14-Z14 -> 13503583 | AX14: =AH14-AR14 -> 2532390.5 | AY14: =AV14/G14 -> 0.22106369
A15: 13 | B15: A03080M221.20.10.10P1350 | C15: Drive Side Trunnion Pin | D15: ASDH01 | E15: WBS | F15: JSOL-ANGUL | G15: 7423341 | N15: =SUM(H15:M15) -> 0 | Z15: =SUM(O15:X15) -> 0 | AH15: =AB15+AE15+AG15 -> 0 | AI15: 2005 | AJ15: 1050620 | AL15: 95.7 | AM15: 62205 | AP15: 62205 | AQ15: =AI15+AK15+AL15+AN15 -> 2100.7 | AR15: =AJ15+AM15+AO15 -> 1112825 | AS15: =Z15+AR15 -> 1112825 | AU15: =AS15+AT15 -> 1112825 | AV15: =G15-AU15+U15 -> 6310516 | AW15: =N15-Z15 -> 0 | AX15: =AH15-AR15 -> -1112825 | AY15: =AV15/G15 -> 0.85009108
A16: 14 | B16: A03080M221.20.10.10P1400 | C16: Non drive side trunnion pin | D16: ASDH01 | E16: WBS | F16: JSOL-ANGUL | G16: 4840666 | N16: =SUM(H16:M16) -> 0 | O16: 2686776.8 | X16: 53735.54 | Y16: 2686776.8 | Z16: =SUM(O16:X16) -> 2740512.4 | AH16: =AB16+AE16+AG16 -> 0 | AI16: 1999 | AJ16: 1047476 | AQ16: =AI16+AK16+AL16+AN16 -> 1999 | AR16: =AJ16+AM16+AO16 -> 1047476 | AS16: =Z16+AR16 -> 3787988.4 | AU16: =AS16+AT16 -> 3787988.4 | AV16: =G16-AU16+U16 -> 1052677.6 | AW16: =N16-Z16 -> -2740512.4 | AX16: =AH16-AR16 -> -1047476 | AY16: =AV16/G16 -> 0.21746546 | AZ16: 6031770233
A17: 15 | B17: C00593X010.1000 C00593X010.2000 C00593X010.3000 C00593X010.4000 | C17: UNDER CARRIAGE BOTTOM PART | D17: RRAN | E17: DIRECT | F17: TAKRAF | G17: 11415816 | H17: 3590130 | I17: 1200000 | J17: 184000 | M17: 402272 | N17: =SUM(H17:M17) -> 5376402 | O17: 4298689 | P17: 12220 | Q17: 72656.31 | R17: 0 | S17: 384467.74 | T17: 47836.99 | V17: 0 | W17: 0 | X17: 7185.62 | Y17: -263686.32 | Z17: =SUM(O17:X17) -> 4823055.7 | AA17: 4353 | AB17: 2888380 | AC17: 314 | AD17: 75 | AE17: 1585000 | AF17: 200 | AG17: 240000 | AH17: =AB17+AE17+AG17 -> 4713380 | AI17: 6765.527 | AJ17: 3779387.5 | AK17: 6.7 | AL17: 102.5 | AM17: 70338.75 | AP17: -2741200 | AQ17: =AI17+AK17+AL17+AN17 -> 6874.727 | AR17: =AJ17+AM17+AO17 -> 3849726.2 | AS17: =Z17+AR17 -> 8672781.9 | AU17: =AS17+AT17 -> 8672781.9 | AV17: =G17-AU17+U17 -> 2743034.1 | AW17: =N17-Z17 -> 553346.34 | AX17: =AH17-AR17 -> 863653.75 | AY17: =AV17/G17 -> 0.24028366
A18: 16 | B18: C00629X010.1000 | C18: MANDREL THRUST BLOCK SPARE ITEMS | D18: PRRR | E18: DIRECT | F18: SMS-BAHRAIN | G18: 2042884.4 | N18: =SUM(H18:M18) -> 0 | P18: 120752 | Q18: 393724.2 | V18: 12950 | Z18: =SUM(O18:X18) -> 527426.2 | AH18: =AB18+AE18+AG18 -> 0 | AQ18: =AI18+AK18+AL18+AN18 -> 0 | AR18: =AJ18+AM18+AO18 -> 0 | AS18: =Z18+AR18 -> 527426.2 | AT18: 11261.6 | AU18: =AS18+AT18 -> 538687.8 | AV18: =G18-AU18+U18 -> 1504196.6 | AW18: =N18-Z18 -> -527426.2 | AX18: =AH18-AR18 -> 0 | AY18: =AV18/G18 -> 0.73631019
A19: 17 | B19: C00594X010 C00595X010 | C19: Bogies & Equalisers Service | D19: RRAN | E19: DIRECT | F19: TAKRAF | G19: 10446266 | H19: 2000000 | I19: 2000000 | L19: 400000 | M19: 150000 | N19: =SUM(H19:M19) -> 4550000 | O19: 1670629.1 | P19: 1368200.6 | Q19: 2169692.4 | R19: 0 | S19: 476620.3 | T19: 232497.98 | V19: 2480 | W19: 0 | X19: 12783.43 | Y19: -1643232.3 | Z19: =SUM(O19:X19) -> 5932903.8 | AA19: 2274.4 | AB19: 1515770.4 | AC19: 509.6 | AD19: 150 | AE19: 2454630.4 | AF19: 250 | AG19: 300000 | AH19: =AB19+AE19+AG19 -> 4270400.8 | AI19: 3141.92 | AJ19: 1871735 | AK19: 30.5 | AL19: 578.2 | AM19: 403732.5 | AP19: -4399100 | AQ19: =AI19+AK19+AL19+AN19 -> 3750.62 | AR19: =AJ19+AM19+AO19 -> 2275467.5 | AS19: =Z19+AR19 -> 8208371.3 | AU19: =AS19+AT19 -> 8208371.3 | AV19: =G19-AU19+U19 -> 2237894.6 | AW19: =N19-Z19 -> -1382903.8 | AX19: =AH19-AR19 -> 1994933.3 | AY19: =AV19/G19 -> 0.21422914
A20: 18 | B20: C00596X010.1000 C00596X010.2000 | C20: Bogies & Equalisers Service | D20: RRAN | E20: DIRECT | F20: TAKRAF | G20: 2341667 | H20: 982812 | I20: 410905 | L20: 200000 | M20: 100000 | N20: =SUM(H20:M20) -> 1693717 | O20: 954.24 | S20: 5050 | W20: 1200 | X20: 4150 | Z20: =SUM(O20:X20) -> 11354.24 | AA20: 568.6 | AB20: 378942.6 | AC20: 127.4 | AD20: 63 | AE20: 613657.6 | AF20: 100 | AG20: 120000 | AH20: =AB20+AE20+AG20 -> 1112600.2 | AI20: 0.09 | AJ20: 315 | AL20: 135.9 | AM20: 202335 | AN20: 504.5 | AO20: 605400 | AP20: 62335 | AQ20: =AI20+AK20+AL20+AN20 -> 640.49 | AR20: =AJ20+AM20+AO20 -> 808050 | AS20: =Z20+AR20 -> 819404.24 | AU20: =AS20+AT20 -> 819404.24 | AV20: =G20-AU20+U20 -> 1522262.8 | AW20: =N20-Z20 -> 1682362.8 | AX20: =AH20-AR20 -> 304550.2 | AY20: =AV20/G20 -> 0.65007653
A21: 19 | B21: C00683X010.1000 | C21: LANTERN PINION SEGMENT | D21: PRRR | E21: DIRECT | F21: HOA PHAT | G21: 5753599.1 | H21: 1056400 | I21: 238080 | M21: 150000 | N21: =SUM(H21:M21) -> 1444480 | O21: 468194.73 | P21: 461880 | Q21: 43493.36 | T21: 14301.82 | Z21: =SUM(O21:X21) -> 987869.91 | AA21: 910 | AB21: 519000 | AC21: 160 | AD21: 50 | AE21: 1058000 | AF21: 64 | AG21: 76800 | AH21: =AB21+AE21+AG21 -> 1653800 | AI21: 172.17 | AJ21: 223368 | AK21: 90 | AL21: 52 | AM21: 604612.5 | AN21: 276 | AO21: 331200 | AQ21: =AI21+AK21+AL21+AN21 -> 590.17 | AR21: =AJ21+AM21+AO21 -> 1159180.5 | AS21: =Z21+AR21 -> 2147050.4 | AT21: 181830.9 | AU21: =AS21+AT21 -> 2328881.3 | AV21: =G21-AU21+U21 -> 3424717.8 | AW21: =N21-Z21 -> 456610.09 | AX21: =AH21-AR21 -> 494619.5 | AY21: =AV21/G21 -> 0.59523052
A22: 20 | B22: C00630X010.1000 | C22: HOUSING & BEARING ASSEMBLY (IS12/450) | D22: JEAM01 | E22: DIRECT | F22: VOITH | G22: 12916000 | H22: 3950000 | I22: 2212382 | J22: 664200 | M22: 65000 | N22: =SUM(H22:M22) -> 6891582 | O22: 5838669.1 | P22: 1164715 | Q22: 736251.8 | S22: 219864.2 | T22: 176737.24 | X22: 293.28 | Y22: -31983.12 | Z22: =SUM(O22:X22) -> 8136530.6 | AA22: 3080 | AB22: 1889600 | AC22: 200 | AD22: 894.54545 | AE22: 1210818.2 | AF22: 600 | AG22: 720000 | AH22: =AB22+AE22+AG22 -> 3820418.2 | AI22: 3407.003 | AJ22: 1991712 | AK22: 142.9 | AL22: 957.9 | AM22: 1122548.5 | AN22: 114.5 | AO22: 137400 | AP22: -2934205 | AQ22: =AI22+AK22+AL22+AN22 -> 4622.303 | AR22: =AJ22+AM22+AO22 -> 3251660.5 | AS22: =Z22+AR22 -> 11388191 | AT22: 50775.06 | AU22: =AS22+AT22 -> 11438966 | AV22: =G22-AU22+U22 -> 1477033.8 | AW22: =N22-Z22 -> -1244948.6 | AX22: =AH22-AR22 -> 568757.68 | AY22: =AV22/G22 -> 0.11435691
A23: 21 | B23: C00656X010.1000 | C23: TUNDISH | D23: SAHAXAVI | E23: DIRECT | F23: SMS Concast AG | G23: 8401287.6 | H23: 3132000 | M23: 830000 | N23: =SUM(H23:M23) -> 3962000 | O23: 1769990.9 | Q23: 23029.9 | S23: 206874 | T23: 3791.01 | W23: 225000 | X23: 36955.92 | Y23: -1100000 | Z23: =SUM(O23:X23) -> 2265641.8 | AA23: 3715 | AB23: 2210250 | AC23: 30 | AD23: 120 | AE23: 174000 | AH23: =AB23+AE23+AG23 -> 2384250 | AI23: 4053.05 | AJ23: 2266976 | AK23: 155 | AL23: 190.2 | AM23: 555670 | AP23: 465000 | AQ23: =AI23+AK23+AL23+AN23 -> 4398.25 | AR23: =AJ23+AM23+AO23 -> 2822646 | AS23: =Z23+AR23 -> 5088287.8 | AT23: 400000 | AU23: =AS23+AT23 -> 5488287.8 | AV23: =G23-AU23+U23 -> 2912999.9 | AW23: =N23-Z23 -> 1696358.2 | AX23: =AH23-AR23 -> -438396 | AY23: =AV23/G23 -> 0.34673255
A24: 22 | B24: C00686X010.1000 | C24: TIGHTENER DISC SPRING 763 MM | D24: RRAN | E24: DIRECT | F24: PAUL WURTH-LUXEMBOURG | G24: 816423.81 | I24: 504000 | J24: 168000 | M24: 12000 | N24: =SUM(H24:M24) -> 684000 | P24: 546000 | Q24: 284651.33 | X24: 10920 | Z24: =SUM(O24:X24) -> 841571.33 | AH24: =AB24+AE24+AG24 -> 0 | AI24: 5 | AJ24: 15325 | AQ24: =AI24+AK24+AL24+AN24 -> 5 | AR24: =AJ24+AM24+AO24 -> 15325 | AS24: =Z24+AR24 -> 856896.33 | AU24: =AS24+AT24 -> 856896.33 | AV24: =G24-AU24+U24 -> -40472.52 | AW24: =N24-Z24 -> -157571.33 | AX24: =AH24-AR24 -> -15325 | AY24: =AV24/G24 -> -0.04957293
A25: 23 | B25: C00687X010.3000 | C25: Segment 8 | D25: RRAN | E25: DIRECT | F25: TATA-KPO | G25: 2750000 | N25: =SUM(H25:M25) -> 0 | O25: 31912.09 | P25: 965.79 | S25: 2500 | X25: 707.56 | Z25: =SUM(O25:X25) -> 36085.44 | AC25: 172.5 | AD25: 112 | AE25: 901300 | AF25: 900 | AG25: 1080000 | AH25: =AB25+AE25+AG25 -> 1981300 | AI25: 69.29 | AJ25: 242665 | AN25: 791.5 | AO25: 949800 | AQ25: =AI25+AK25+AL25+AN25 -> 860.79 | AR25: =AJ25+AM25+AO25 -> 1192465 | AS25: =Z25+AR25 -> 1228550.4 | AT25: 110000 | AU25: =AS25+AT25 -> 1338550.4 | AV25: =G25-AU25+U25 -> 1411449.6 | AW25: =N25-Z25 -> -36085.44 | AX25: =AH25-AR25 -> 788835 | AY25: =AV25/G25 -> 0.51325439
A26: 24 | B26: ET470089284-72004880 | C26: UPPER SELING RING COMPONENTS | D26: GOKR | E26: SERVICE | F26: TATA-KPO | G26: 789000 | N26: =SUM(H26:M26) -> 0 | O26: 274122.88 | Q26: 241971.15 | U26: 4166.44 | W26: 30000 | Z26: =SUM(O26:X26) -> 550260.47 | AI26: 116.5 | AJ26: 143100.4 | AN26: 279 | AO26: 334800 | AQ26: =AI26+AK26+AL26+AN26 -> 395.5 | AR26: =AJ26+AM26+AO26 -> 477900.4 | AS26: =Z26+AR26 -> 1028160.9 | AT26: 11137.78 | AU26: =AS26+AT26 -> 1039298.7 | AV26: =G26-AU26+U26 -> -246132.21 | AW26: =N26-Z26 -> -550260.47 | AX26: =AH26-AR26 -> -477900.4 | AY26: =AV26/G26 -> -0.31195464
A27: 25 | B27: ET430076201-72004060 | C27: ADJUSTABLE SKIRT & COOLING RING | D27: PADE | E27: SERVICE | F27: TATA-JSR | G27: 2195296 | H27: 567031 | I27: 15018 | J27: 209902 | L27: 222580 | M27: 184870 | N27: =SUM(H27:M27) -> 1199401 | O27: 962327.02 | P27: 66902.66 | Q27: 330310.26 | S27: 426163.03 | U27: 56196.67 | W27: 110000 | Y27: -346600.8 | Z27: =SUM(O27:X27) -> 1951899.6 | AI27: 420 | AJ27: 264480 | AP27: 180000 | AQ27: =AI27+AK27+AL27+AN27 -> 420 | AR27: =AJ27+AM27+AO27 -> 264480 | AS27: =Z27+AR27 -> 2216379.6 | AT27: 16650.5 | AU27: =AS27+AT27 -> 2233030.1 | AV27: =G27-AU27+U27 -> 18462.53 | AW27: =N27-Z27 -> -752498.64 | AX27: =AH27-AR27 -> -264480 | AY27: =AV27/G27 -> 0.0084100413
A28: 26 | B28: ET470089468-72004894 | C28: FLUX CHUTES | D28: PADE | E28: SERVICE | F28: TATA-NINL | G28: 819000 | N28: =SUM(H28:M28) -> 0 | O28: 116544.53 | Q28: 9666.53 | S28: 850 | U28: 22924.22 | Z28: =SUM(O28:X28) -> 149985.28 | AI28: 826 | AJ28: 644168 | AP28: 480088 | AQ28: =AI28+AK28+AL28+AN28 -> 826 | AR28: =AJ28+AM28+AO28 -> 644168 | AS28: =Z28+AR28 -> 794153.28 | AT28: 945 | AU28: =AS28+AT28 -> 795098.28 | AV28: =G28-AU28+U28 -> 46825.94 | AW28: =N28-Z28 -> -149985.28 | AX28: =AH28-AR28 -> -644168 | AY28: =AV28/G28 -> 0.05717453
A33: GRAND TOTAL | G33: =SUBTOTAL(9,G3:G32) -> 2.8987278e+08 | H33: =SUBTOTAL(9,H3:H32) -> 1.058375e+08 | I33: =SUBTOTAL(9,I3:I32) -> 40827387 | J33: =SUBTOTAL(9,J3:J32) -> 3008019.1 | K33: =SUBTOTAL(9,K3:K32) -> 0 | L33: =SUBTOTAL(9,L3:L32) -> 14026885 | M33: =SUBTOTAL(9,M3:M32) -> 9156769.7 | N33: =SUBTOTAL(9,N3:N32) -> 1.7285656e+08 | ... AX33: =SUBTOTAL(9,AX3:AX32) -> 6023454.3
AS53: .
